Workbook

Sheet Hoja1
A2: ID | B2: Modulo | C2: Fase | D2: Tipo | E2: Funcionalidad/Entregable | F2: Criterio de aceptación | G2: horas | H2: factor | I2: precio hora | J2: Precio final | K2: Avance (jul-2026)
A3: A001 | B3: Transversal | C3: MVP | D3: Análisis | E3: Levantamiento y alcance funcional | F3: Procesos, actores, excepciones y criterios de aceptación documentados. | G3: 4 | H3: 4 | I3: =IF($H3=1,preciosxhora!C$3,IF($H3=2,preciosxhora!C$4,IF($H3=3,preciosxhora!C$5,IF($H3=4,preciosxhora!C$6,0)))) | J3: =I3*G3
A4: A002 | B4: Transversal | C4: MVP | D4: Backend | E4: Modelo de datos y migraciones | F4: Modelos, relaciones, restricciones e índices migran sin errores. | G4: 2 | H4: 1 | I4: =IF($H4=1,preciosxhora!C$3,IF($H4=2,preciosxhora!C$4,IF($H4=3,preciosxhora!C$5,IF($H4=4,preciosxhora!C$6,0)))) | J4: =I4*G4
A5: A003 | B5: Transversal | C5: MVP | D5: Análisis | E5: Estados y reglas de negocio | F5: Matriz de estados, transiciones y excepciones validada. | G5: 2 | H5: 2 | I5: =IF($H5=1,preciosxhora!C$3,IF($H5=2,preciosxhora!C$4,IF($H5=3,preciosxhora!C$5,IF($H5=4,preciosxhora!C$6,0)))) | J5: =I5*G5
A6: A004 | B6: Transversal | C6: MVP | D6: Backend | E6: Permisos y roles | F6: Acceso por rol y acción verificado en casos permitidos y denegados. | G6: 2 | H6: 2 | I6: =IF($H6=1,preciosxhora!C$3,IF($H6=2,preciosxhora!C$4,IF($H6=3,preciosxhora!C$5,IF($H6=4,preciosxhora!C$6,0)))) | J6: =I6*G6
A7: A005 | B7: Transversal | C7: MVP | D7: Backend | E7: Auditoría e historial | F7: Cambios críticos conservan usuario, fecha, valor anterior y motivo. | G7: 2 | H7: 2 | I7: =IF($H7=1,preciosxhora!C$3,IF($H7=2,preciosxhora!C$4,IF($H7=3,preciosxhora!C$5,IF($H7=4,preciosxhora!C$6,0)))) | J7: =I7*G7
A8: A006 | B8: Transversal | C8: MVP | D8: Backend | E8: Gestión de archivos adjuntos | F8: Validación, almacenamiento, acceso y descarga segura de respaldos. | G8: 1 | H8: 1 | I8: =IF($H8=1,preciosxhora!C$3,IF($H8=2,preciosxhora!C$4,IF($H8=3,preciosxhora!C$5,IF($H8=4,preciosxhora!C$6,0)))) | J8: =I8*G8
A9: A007 | B9: Transversal | C9: MVP | D9: Frontend | E9: Diseño UX y navegación | F9: Flujos y pantallas principales aprobados antes de la construcción final. | G9: 0 | H9: 0 | I9: =IF($H9=1,preciosxhora!C$3,IF($H9=2,preciosxhora!C$4,IF($H9=3,preciosxhora!C$5,IF($H9=4,preciosxhora!C$6,0)))) | J9: =I9*G9
A10: R001 | B10: Rendiciones | C10: MVP | D10: Frontend | E10: Lista y búsqueda de rendiciones | F10: Lista de rendiciones con totales y acceso a escritorio; falta búsqueda avanzada/paginación fina. | G10: 2 | H10: 2 | I10: =IF($H10=1,preciosxhora!C$3,IF($H10=2,preciosxhora!C$4,IF($H10=3,preciosxhora!C$5,IF($H10=4,preciosxhora!C$6,0)))) | J10: =I10*G10 | K10: Hecho
A11: R002 | B11: Rendiciones | C11: MVP | D11: Backend | E11: Crear y editar rendición | F11: Inicio claro de cabecera + escritorio editable (flujo operacional listo). | G11: 3 | H11: 2 | I11: =IF($H11=1,preciosxhora!C$3,IF($H11=2,preciosxhora!C$4,IF($H11=3,preciosxhora!C$5,IF($H11=4,preciosxhora!C$6,0)))) | J11: =I11*G11 | K11: Hecho
A12: R003 | B12: Rendiciones | C12: MVP | D12: Backend | E12: Responsables de rendición | F12: Hoy se crea responsable desde el usuario; falta UI de catálogo y datos históricos formales. | G12: 2 | H12: 2 | I12: =IF($H12=1,preciosxhora!C$3,IF($H12=2,preciosxhora!C$4,IF($H12=3,preciosxhora!C$5,IF($H12=4,preciosxhora!C$6,0)))) | J12: =I12*G12 | K12: Parcial
A13: R004 | B13: Rendiciones | C13: MVP | D13: Backend | E13: Categorías y subcategorías de gasto | F13: Catálogos administrables, activos y sin duplicados. | G13: 2 | H13: 1 | I13: =IF($H13=1,preciosxhora!C$3,IF($H13=2,preciosxhora!C$4,IF($H13=3,preciosxhora!C$5,IF($H13=4,preciosxhora!C$6,0)))) | J13: =I13*G13 | K13: Pendiente
A14: R005 | B14: Rendiciones | C14: MVP | D14: Backend | E14: Entregas de fondo | F14: Modelos listos; falta UI de múltiples entregas y saldo de fondos. | G14: 4 | H14: 2 | I14: =IF($H14=1,preciosxhora!C$3,IF($H14=2,preciosxhora!C$4,IF($H14=3,preciosxhora!C$5,IF($H14=4,preciosxhora!C$6,0)))) | J14: =I14*G14 | K14: Pendiente
A15: R006 | B15: Rendiciones | C15: MVP | D15: Backend | E15: Detalle de gastos | F15: Detalle en BD + ingreso por foto con OCR (RapidOCR), corrección manual, editar/eliminar. Esfuerzo real mayor por OCR. | G15: 8 | H15: 3 | I15: =IF($H15=1,preciosxhora!C$3,IF($H15=2,preciosxhora!C$4,IF($H15=3,preciosxhora!C$5,IF($H15=4,preciosxhora!C$6,0)))) | J15: =I15*G15 | K15: Hecho
A16: R007 | B16: Rendiciones | C16: MVP | D16: Frontend | E16: Adjuntos y previsualización | F16: Subida, previsualización, reemplazo y galería en escritorio/PDF. | G16: 3 | H16: 2 | I16: =IF($H16=1,preciosxhora!C$3,IF($H16=2,preciosxhora!C$4,IF($H16=3,preciosxhora!C$5,IF($H16=4,preciosxhora!C$6,0)))) | J16: =I16*G16 | K16: Hecho
A17: R008 | B17: Rendiciones | C17: MVP | D17: Backend | E17: Validación documental | F17: Validaciones básicas al guardar; falta control fuerte de duplicados y reglas documentales avanzadas. | G17: 3 | H17: 2 | I17: =IF($H17=1,preciosxhora!C$3,IF($H17=2,preciosxhora!C$4,IF($H17=3,preciosxhora!C$5,IF($H17=4,preciosxhora!C$6,0)))) | J17: =I17*G17 | K17: Parcial
A18: R009 | B18: Rendiciones | C18: MVP | D18: Backend | E18: Cálculos de rendición | F18: Suma de soportes y totales en escritorio/lista/PDF. | G18: 2 | H18: 1 | I18: =IF($H18=1,preciosxhora!C$3,IF($H18=2,preciosxhora!C$4,IF($H18=3,preciosxhora!C$5,IF($H18=4,preciosxhora!C$6,0)))) | J18: =I18*G18 | K18: Hecho
A19: R010 | B19: Rendiciones | C19: MVP | D19: Backend | E19: Presentación de rendición | F19: Cerrar carga (PRESENTADA), reabrir y bloqueo de edición según estado. | G19: 2 | H19: 1 | I19: =IF($H19=1,preciosxhora!C$3,IF($H19=2,preciosxhora!C$4,IF($H19=3,preciosxhora!C$5,IF($H19=4,preciosxhora!C$6,0)))) | J19: =I19*G19 | K19: Hecho
A20: R011 | B20: Rendiciones | C20: MVP | D20: Frontend | E20: Revisión y observaciones | F20: Observaciones por gasto y devolución a corrección. | G20: 4 | H20: 2 | I20: =IF($H20=1,preciosxhora!C$3,IF($H20=2,preciosxhora!C$4,IF($H20=3,preciosxhora!C$5,IF($H20=4,preciosxhora!C$6,0)))) | J20: =I20*G20 | K20: Pendiente
A21: R012 | B21: Rendiciones | C21: MVP | D21: Backend | E21: Aprobación y rechazo | F21: Modelo de aprobaciones existe; falta flujo UI completo de aprobación/rechazo. | G21: 4 | H21: 2 | I21: =IF($H21=1,preciosxhora!C$3,IF($H21=2,preciosxhora!C$4,IF($H21=3,preciosxhora!C$5,IF($H21=4,preciosxhora!C$6,0)))) | J21: =I21*G21 | K21: Pendiente
... A31: R022 | B31: Rendiciones | C31: Opcional | D31: Documentación | E31: Manual de rendiciones | F31: Guía operativa y resolución de casos frecuentes. | G31: 2 | H31: 1 | I31: =IF($H31=1,preciosxhora!C$3,IF($H31=2,preciosxhora!C$4,IF($H31=3,preciosxhora!C$5,IF($H31=4,preciosxhora!C$6,0)))) | J31: =I31*G31 | K31: Pendiente
A32: B001 | B32: Banco y conciliación | C32: MVP | D32: Backend | E32: Catálogo de bancos | F32: Bancos activos y datos consistentes. | G32: 0 | H32: 0 | I32: =IF($H32=1,preciosxhora!C$3,IF($H32=2,preciosxhora!C$4,IF($H32=3,preciosxhora!C$5,IF($H32=4,preciosxhora!C$6,0)))) | J32: =I32*G32
A33: B002 | B33: Banco y conciliación | C33: MVP | D33: Backend | E33: Cuentas bancarias | F33: Cuenta, moneda, banco, titular y estado. | G33: 0 | H33: 0 | I33: =IF($H33=1,preciosxhora!C$3,IF($H33=2,preciosxhora!C$4,IF($H33=3,preciosxhora!C$5,IF($H33=4,preciosxhora!C$6,0)))) | J33: =I33*G33
A34: B003 | B34: Banco y conciliación | C34: MVP | D34: Integración | E34: Importación de cartolas CSV/XLSX | F34: Archivo importado con validación y resumen de errores. | G34: 0 | H34: 0 | I34: =IF($H34=1,preciosxhora!C$3,IF($H34=2,preciosxhora!C$4,IF($H34=3,preciosxhora!C$5,IF($H34=4,preciosxhora!C$6,0)))) | J34: =I34*G34
A35: B004 | B35: Banco y conciliación | C35: MVP | D35: Integración | E35: Plantillas de mapeo bancario | F35: Columnas configurables por banco y formato. | G35: 0 | H35: 0 | I35: =IF($H35=1,preciosxhora!C$3,IF($H35=2,preciosxhora!C$4,IF($H35=3,preciosxhora!C$5,IF($H35=4,preciosxhora!C$6,0)))) | J35: =I35*G35
A36: B005 | B36: Banco y conciliación | C36: MVP | D36: Backend | E36: Detección de duplicados | F36: Hash de archivo y fingerprint por movimiento. | G36: 0 | H36: 0 | I36: =IF($H36=1,preciosxhora!C$3,IF($H36=2,preciosxhora!C$4,IF($H36=3,preciosxhora!C$5,IF($H36=4,preciosxhora!C$6,0)))) | J36: =I36*G36
A37: B006 | B37: Banco y conciliación | C37: MVP | D37: Frontend | E37: Lista de movimientos | F37: Filtros por cuenta, fecha, monto, texto y estado. | G37: 0 | H37: 0 | I37: =IF($H37=1,preciosxhora!C$3,IF($H37=2,preciosxhora!C$4,IF($H37=3,preciosxhora!C$5,IF($H37=4,preciosxhora!C$6,0)))) | J37: =I37*G37
A38: B007 | B38: Banco y conciliación | C38: MVP | D38: Frontend | E38: Detalle de movimiento | F38: Datos originales, aplicaciones y trazabilidad. | G38: 0 | H38: 0 | I38: =IF($H38=1,preciosxhora!C$3,IF($H38=2,preciosxhora!C$4,IF($H38=3,preciosxhora!C$5,IF($H38=4,preciosxhora!C$6,0)))) | J38: =I38*G38
A39: B008 | B39: Banco y conciliación | C39: MVP | D39: Backend | E39: Clasificación manual | F39: Tipo, contraparte y observación justificable. | G39: 0 | H39: 0 | I39: =IF($H39=1,preciosxhora!C$3,IF($H39=2,preciosxhora!C$4,IF($H39=3,preciosxhora!C$5,IF($H39=4,preciosxhora!C$6,0)))) | J39: =I39*G39
A40: B009 | B40: Banco y conciliación | C40: MVP | D40: Backend | E40: Aplicaciones bancarias múltiples | F40: Un movimiento se distribuye entre varios destinos financieros. | G40: 0 | H40: 0 | I40: =IF($H40=1,preciosxhora!C$3,IF($H40=2,preciosxhora!C$4,IF($H40=3,preciosxhora!C$5,IF($H40=4,preciosxhora!C$6,0)))) | J40: =I40*G40
A41: B010 | B41: Banco y conciliación | C41: MVP | D41: Integración | E41: Un movimiento paga varias facturas | F41: Distribución por monto sin exceder saldos ni movimiento. | G41: 0 | H41: 0 | I41: =IF($H41=1,preciosxhora!C$3,IF($H41=2,preciosxhora!C$4,IF($H41=3,preciosxhora!C$5,IF($H41=4,preciosxhora!C$6,0)))) | J41: =I41*G41
A42: B011 | B42: Banco y conciliación | C42: MVP | D42: Backend | E42: Conciliación parcial | F42: Saldo aplicado, pendiente y estado calculado. | G42: 0 | H42: 0 | I42: =IF($H42=1,preciosxhora!C$3,IF($H42=2,preciosxhora!C$4,IF($H42=3,preciosxhora!C$5,IF($H42=4,preciosxhora!C$6,0)))) | J42: =I42*G42
A43: B012 | B43: Banco y conciliación | C43: Fase 2 | D43: Backend | E43: Reglas de cruce automático | F43: Coincidencia por monto, referencia, RUT y fecha. | G43: 0 | H43: 0 | I43: =IF($H43=1,preciosxhora!C$3,IF($H43=2,preciosxhora!C$4,IF($H43=3,preciosxhora!C$5,IF($H43=4,preciosxhora!C$6,0)))) | J43: =I43*G43
... A87: Q008 | B87: Calidad y despliegue | C87: MVP | D87: QA | E87: Estabilización post-entrega | F87: Correcciones dentro del período acordado. | G87: 0 | H87: 0 | I87: =IF($H87=1,preciosxhora!C$3,IF($H87=2,preciosxhora!C$4,IF($H87=3,preciosxhora!C$5,IF($H87=4,preciosxhora!C$6,0)))) | J87: =I87*G87
G90: =SUM(G3:G87) | J90: =SUM(J3:J87)
A92: RESUMEN MÓDULO RENDICIONES (estimado realista según avance actual)
A93: Horas Rendiciones (R001–R022) | G93: =SUM(G10:G31) | J93: =SUM(J10:J31) | K93: Total $ estimado módulo
A94: Horas ya hechas / parciales (costo hundido aprox.) | G94: =SUMIF(K10:K31,"Hecho",G10:G31)+SUMIF(K10:K31,"Parcial",G10:G31)*0.5 | J94: =SUMIF(K10:K31,"Hecho",J10:J31)+SUMIF(K10:K31,"Parcial",J10:J31)*0.5 | K94: Hecho + 50% de Parcial
A95: Horas pendientes (resto MVP/Fase2/QA) | G95: =G93-G94 | J95: =J93-J94 | K95: Pendiente + 50% Parcial restante
A96: Nota | B96: Base preciosxhora=$18.000. Factores: 1=muy sencilla(0.8), 2=sencilla(1), 3=media(1.25), 4=compleja(1.5). Estimación ajustada al trabajo real: lista/escritorio/OCR/PDF/cierre ya operativos; faltan fondos, liquidación, aprobación formal, Excel y conciliación bancaria de liquidaciones.

Sheet Hoja2
A1: Recurso | B1: Valor Hora
A2: Analista Funcional | B2: $45.000
A3: Programador Backend | B3: $42.000
A4: Programador Frontend | B4: $40.000
A5: Full Stack | B5: $48.000
A6: Diseñador UI/UX | B6: $38.000
A7: DBA | B7: $50.000
A8: DevOps | B8: $55.000
A9: QA | B9: $32.000
A10: Jefe de Proyecto | B10: $60.000
A11: Arquitecto | B11: $75.000

Sheet Hoja3
A1: Perfil | B1: Valor hora recomendado
A2: Programador Junior | B2: $18.000 – $30.000
A3: Programador Semi Senior | B3: $30.000 – $45.000
A4: Programador Senior | B4: $45.000 – $70.000
A5: Arquitecto de Software | B5: $70.000 – $100.000
A6: Consultor Especialista / IA / Ciberseguridad | B6: $80.000 – $150.000+

Sheet preciosxhora
A1: valor | B1: 18000
A3: 1 | B3: muy sencilla | C3: =B1*0.8
A4: 2 | B4: sencilla | C4: =B1*1
A5: 3 | B5: media | C5: =B1*1.25
A6: 4 | B6: compleja | C6: =B1*1.5

Sheet NotasRendiciones
A1: Criterio de estimación — Módulo Rendiciones
A3: Contexto: según desarrollo realizado en el proyecto (modelos adm_*, OCR RapidOCR, lista, escritorio,
A4: agregar/editar/eliminar comprobantes, PDF, cerrar/reabrir carga, admin de detalles).
A6: Qué ya está cubierto (marcados Hecho/Parcial en Hoja1 col. K):
A7: - Inicio de rendición + lista + escritorio con datos en BD
A8: - Detalle de gastos desde imagen (OCR) + corrección manual
A9: - Adjuntos, sumas, presentación/cierre, PDF
A11: Qué falta para cerrar el módulo operacional completo:
A12: - Catálogos (categorías) y UI de responsables
A13: - Entregas de fondo + liquidación (cuadrada / devolución / reembolso)
A14: - Revisión/aprobación formal y observaciones por gasto
A15: - Excel; alertas y dashboard (Fase 2)
... A19: (dependencias, libGL/headless) concentró esfuerzo que el tabulador original no desglosaba.
