Workbook

Sheet Ingresos
B2: PANEL DE INGRESOS
D5: =#REF! & " " & TEXT(SUM(tbl_ingresos[Ingreso Total]),"#,##0.00") -> #REF! | F5: =#REF! & " " & TEXT(SUM(tbl_ingresos[Valor Impuesto]),"#,##0.00") -> #REF! | H5: =#REF! & " " & TEXT(SUM(tbl_ingresos[Total Neto]),"#,##0.00") -> #REF!
D6: Ingresos Brutos | F6: Monto de Impuestos | H6: Ingresos Netos
B8: ID | C8: Fecha | D8: Categoría | E8: Descripción | F8: Mét. De Pago | G8: Ingreso Total | H8: Impuesto | I8: Valor Impuesto | J8: Total Neto | K8: Notas | L8: M | M8: Y | N8: D
B9: 301 | C9: 46105 | D9: 301 Ventas factura/Clientes | E9: Fac 621 | F9: Transferencias | G9: 1288412 | H9: 0.19 | I9: =G9 - (G9 / (1 + H9)) -> 205712.84 | J9: =G9 / (1 + H9) -> 1082699.2 | K9: I. Municipalidad de Temuco. | L9: =IF(C9="","",MONTH(C9)) -> 3 | M9: =IF(C9="","",YEAR(C9)) -> 2026 | N9: =IF(C9="","",DAY(C9)) -> 24
C10: 46084 | D10: 302 Fingo/ Flujo | E10: F.616 | F10: TRANSFERENCIA FINGO | G10: 874949 | K10: MONTO FACTURA 969.882 COMISION DE 94.933 | L10: 94933
C11: 46084 | D11: 302 Fingo/ Flujo | E11: F618 | F11: TRANSFERENCIA FINGO | G11: 518767 | H11: 0.19 | I11: =G11 - (G11 / (1 + H11)) -> 82828.345 | J11: =G11 / (1 + H11) -> 435938.66 | K11: MONTO FACTURA 545.273 COMISION 26.506 | L11: =IF(C11="","",MONTH(C11)) -> 3 | M11: =IF(C11="","",YEAR(C11)) -> 2026 | N11: =IF(C11="","",DAY(C11)) -> 3
C12: 46090 | D12: 302 Fingo/ Flujo | E12: 617 Y 622 | F12: TRANSFERENCIA FINGO | G12: 1349393 | H12: 0.19 | I12: =G12 - (G12 / (1 + H12)) -> 215449.3 | J12: =G12 / (1 + H12) -> 1133943.7 | K12: MONTO FACATURAS 2.103.773 SE PAGO FACTURA TALCA POR 594.952 | L12: =IF(C12="","",MONTH(C12)) -> 3 | M12: =IF(C12="","",YEAR(C12)) -> 2026 | N12: =IF(C12="","",DAY(C12)) -> 9
C13: 46091 | D13: 302 Fingo/ Flujo | E13: F | F13: TRANSFERENCIA FINGO | G13: 1005305 | H13: 0.19 | I13: =G13 - (G13 / (1 + H13)) -> 160510.88 | J13: =G13 / (1 + H13) -> 844794.12 | K13: MONTO FACTURA 1.105.009 COMISION 99.704 | L13: =IF(C13="","",MONTH(C13)) -> 3 | M13: =IF(C13="","",YEAR(C13)) -> 2026 | N13: =IF(C13="","",DAY(C13)) -> 10
C14: 46097 | D14: 302 Fingo/ Flujo | E14: F 631 | F14: TRANSFERENCIA FINGO | G14: 852599 | H14: 0.19 | I14: =G14 - (G14 / (1 + H14)) -> 136129.25 | J14: =G14 / (1 + H14) -> 716469.75 | K14: MONTO FACTURA 949.506 COMISION 96.907 | L14: =IF(C14="","",MONTH(C14)) -> 3 | M14: =IF(C14="","",YEAR(C14)) -> 2026 | N14: =IF(C14="","",DAY(C14)) -> 16
C15: 46100 | D15: 302 Fingo/ Flujo | E15: F.632 | F15: TRANSFERENCIA FINGO | G15: 269948 | H15: 0.19 | I15: =G15 - (G15 / (1 + H15)) -> 43100.941 | J15: =G15 / (1 + H15) -> 226847.06 | K15: MONTO FACTURA 326.404 COMISION 56.456 | L15: =IF(C15="","",MONTH(C15)) -> 3 | M15: =IF(C15="","",YEAR(C15)) -> 2026 | N15: =IF(C15="","",DAY(C15)) -> 19
C16: 46104 | D16: 302 Fingo/ Flujo | E16: F.635 | F16: TRANSFERENCIA FINGO | G16: 397891 | H16: 0.19 | I16: =G16 - (G16 / (1 + H16)) -> 63528.815 | J16: =G16 / (1 + H16) -> 334362.18 | K16: MONTO FACTURA 615.140 PAGO FACTURA RETIRO POR 238.964 | L16: =IF(C16="","",MONTH(C16)) -> 3 | M16: =IF(C16="","",YEAR(C16)) -> 2026 | N16: =IF(C16="","",DAY(C16)) -> 23
C17: 46104 | D17: 302 Fingo/ Flujo | E17: EXCEDENTES | F17: TRANSFERENCIA FINGO | G17: 277250 | H17: 0.19 | I17: =G17 - (G17 / (1 + H17)) -> 44266.807 | J17: =G17 / (1 + H17) -> 232983.19 | K17: EXCEDENTES | L17: =IF(C17="","",MONTH(C17)) -> 3 | M17: =IF(C17="","",YEAR(C17)) -> 2026 | N17: =IF(C17="","",DAY(C17)) -> 23
C18: 46087 | D18: 301 Ventas factura/Clientes | E18: F 604 | F18: TRANSFERENCIA CLIENTES | G18: 128225 | H18: 0.19 | I18: =G18 - (G18 / (1 + H18)) -> 20472.899 | J18: =G18 / (1 + H18) -> 107752.1 | K18: TESORERIA PROVINCIAL DE MALLECO ANGOL | L18: =IF(C18="","",MONTH(C18)) -> 3 | M18: =IF(C18="","",YEAR(C18)) -> 2026 | N18: =IF(C18="","",DAY(C18)) -> 6
C19: 46090 | D19: 301 Ventas factura/Clientes | E19: F 589 | F19: TRANSFERENCIA CLIENTES | G19: 371542 | H19: 0.19 | I19: =G19 - (G19 / (1 + H19)) -> 59321.832 | J19: =G19 / (1 + H19) -> 312220.17 | K19: MODULOS WEWFE LIMITADA | L19: =IF(C19="","",MONTH(C19)) -> 3 | M19: =IF(C19="","",YEAR(C19)) -> 2026 | N19: =IF(C19="","",DAY(C19)) -> 9
C20: 46092 | D20: 301 Ventas factura/Clientes | E20: 598 | F20: TRANSFERENCIA CLIENTES | G20: 128484 | H20: 0.19 | I20: =G20 - (G20 / (1 + H20)) -> 20514.252 | J20: =G20 / (1 + H20) -> 107969.75 | K20: ILUSTRE MUNICIPALIDAD DE NINHUE DEPARTAMENTO DE SALUD | L20: =IF(C20="","",MONTH(C20)) -> 3 | M20: =IF(C20="","",YEAR(C20)) -> 2026 | N20: =IF(C20="","",DAY(C20)) -> 11
C21: 46094 | D21: 301 Ventas factura/Clientes | F21: TRANSFERENCIA CLIENTES | G21: 96271 | H21: 0.19 | I21: =G21 - (G21 / (1 + H21)) -> 15371 | J21: =G21 / (1 + H21) -> 80900 | K21: PAGO CLIENTES | L21: =IF(C21="","",MONTH(C21)) -> 3 | M21: =IF(C21="","",YEAR(C21)) -> 2026 | N21: =IF(C21="","",DAY(C21)) -> 13
C22: 46100 | D22: 301 Ventas factura/Clientes | F22: TRANSFERENCIA CLIENTES | G22: 333855 | H22: 0.19 | I22: =G22 - (G22 / (1 + H22)) -> 53304.58 | J22: =G22 / (1 + H22) -> 280550.42 | K22: PAGO CLIENTES | L22: =IF(C22="","",MONTH(C22)) -> 3 | M22: =IF(C22="","",YEAR(C22)) -> 2026 | N22: =IF(C22="","",DAY(C22)) -> 19
C23: 46101 | D23: 301 Ventas factura/Clientes | E23: 626 | F23: TRANSFERENCIA CLIENTES | G23: 22872 | H23: 0.19 | I23: =G23 - (G23 / (1 + H23)) -> 3651.8319 | J23: =G23 / (1 + H23) -> 19220.168 | K23: MUNICIPLAIDAD LAGO RANCO | L23: =IF(C23="","",MONTH(C23)) -> 3 | M23: =IF(C23="","",YEAR(C23)) -> 2026 | N23: =IF(C23="","",DAY(C23)) -> 20
C24: 46101 | D24: 301 Ventas factura/Clientes | E24: 625 | F24: TRANSFERENCIA CLIENTES | G24: 20635 | H24: 0.19 | I24: =G24 - (G24 / (1 + H24)) -> 3294.6639 | J24: =G24 / (1 + H24) -> 17340.336 | K24: MUNICIPLAIDAD LAGO RANCO | L24: =IF(C24="","",MONTH(C24)) -> 3 | M24: =IF(C24="","",YEAR(C24)) -> 2026 | N24: =IF(C24="","",DAY(C24)) -> 20
C25: 46101 | D25: 301 Ventas factura/Clientes | E25: 624 | F25: TRANSFERENCIA CLIENTES | G25: 88607 | H25: 0.19 | I25: =G25 - (G25 / (1 + H25)) -> 14147.336 | J25: =G25 / (1 + H25) -> 74459.664 | K25: MUNICIPLAIDAD LAGO RANCO | L25: =IF(C25="","",MONTH(C25)) -> 3 | M25: =IF(C25="","",YEAR(C25)) -> 2026 | N25: =IF(C25="","",DAY(C25)) -> 20
C26: 24-3-206 | D26: 301 Ventas factura/Clientes | E26: 621 | F26: TRANSFERENCIA CLIENTES | G26: 1288412 | H26: 0.19 | I26: =G26 - (G26 / (1 + H26)) -> 205712.84 | J26: =G26 / (1 + H26) -> 1082699.2 | K26: MUNICIPALIDAD DE TEMUCO | L26: =IF(C26="","",MONTH(C26)) -> #VALUE! | M26: =IF(C26="","",YEAR(C26)) -> #VALUE! | N26: =IF(C26="","",DAY(C26)) -> #VALUE!
H27: 0.19 | I27: =G27 - (G27 / (1 + H27)) -> 0 | J27: =G27 / (1 + H27) -> 0 | L27: =IF(C27="","",MONTH(C27)) | M27: =IF(C27="","",YEAR(C27)) | N27: =IF(C27="","",DAY(C27))
H28: 0.19 | I28: =G28 - (G28 / (1 + H28)) -> 0 | J28: =G28 / (1 + H28) -> 0 | L28: =IF(C28="","",MONTH(C28)) | M28: =IF(C28="","",YEAR(C28)) | N28: =IF(C28="","",DAY(C28))
H29: 0.19 | I29: =G29 - (G29 / (1 + H29)) -> 0 | J29: =G29 / (1 + H29) -> 0 | L29: =IF(C29="","",MONTH(C29)) | M29: =IF(C29="","",YEAR(C29)) | N29: =IF(C29="","",DAY(C29))
H30: 0.19 | I30: =G30 - (G30 / (1 + H30)) -> 0 | J30: =G30 / (1 + H30) -> 0 | L30: =IF(C30="","",MONTH(C30)) | M30: =IF(C30="","",YEAR(C30)) | N30: =IF(C30="","",DAY(C30))
H31: 0.19 | I31: =G31 - (G31 / (1 + H31)) -> 0 | J31: =G31 / (1 + H31) -> 0 | L31: =IF(C31="","",MONTH(C31)) | M31: =IF(C31="","",YEAR(C31)) | N31: =IF(C31="","",DAY(C31))
H32: 0.19 | I32: =G32 - (G32 / (1 + H32)) -> 0 | J32: =G32 / (1 + H32) -> 0 | L32: =IF(C32="","",MONTH(C32)) | M32: =IF(C32="","",YEAR(C32)) | N32: =IF(C32="","",DAY(C32))
H33: 0.19 | I33: =G33 - (G33 / (1 + H33)) -> 0 | J33: =G33 / (1 + H33) -> 0 | L33: =IF(C33="","",MONTH(C33)) | M33: =IF(C33="","",YEAR(C33)) | N33: =IF(C33="","",DAY(C33))
H34: 0.19 | I34: =G34 - (G34 / (1 + H34)) -> 0 | J34: =G34 / (1 + H34) -> 0 | L34: =IF(C34="","",MONTH(C34)) | M34: =IF(C34="","",YEAR(C34)) | N34: =IF(C34="","",DAY(C34))
H35: 0.19 | I35: =G35 - (G35 / (1 + H35)) -> 0 | J35: =G35 / (1 + H35) -> 0 | L35: =IF(C35="","",MONTH(C35)) | M35: =IF(C35="","",YEAR(C35)) | N35: =IF(C35="","",DAY(C35))
H36: 0.19 | I36: =G36 - (G36 / (1 + H36)) -> 0 | J36: =G36 / (1 + H36) -> 0 | L36: =IF(C36="","",MONTH(C36)) | M36: =IF(C36="","",YEAR(C36)) | N36: =IF(C36="","",DAY(C36))
H37: 0.19 | I37: =G37 - (G37 / (1 + H37)) -> 0 | J37: =G37 / (1 + H37) -> 0 | L37: =IF(C37="","",MONTH(C37)) | M37: =IF(C37="","",YEAR(C37)) | N37: =IF(C37="","",DAY(C37))
H38: 0.19 | I38: =G38 - (G38 / (1 + H38)) -> 0 | J38: =G38 / (1 + H38) -> 0 | L38: =IF(C38="","",MONTH(C38)) | M38: =IF(C38="","",YEAR(C38)) | N38: =IF(C38="","",DAY(C38))
... H97: 0.19 | I97: =G97 - (G97 / (1 + H97)) -> 0 | J97: =G97 / (1 + H97) -> 0 | L97: =IF(C97="","",MONTH(C97)) | M97: =IF(C97="","",YEAR(C97)) | N97: =IF(C97="","",DAY(C97))
I98: =G98 - (G98 / (1 + H98)) -> 0 | J98: =G98 / (1 + H98) -> 0 | L98: =IF(C98="","",MONTH(C98)) | M98: =IF(C98="","",YEAR(C98)) | N98: =IF(C98="","",DAY(C98))
I99: =G99 - (G99 / (1 + H99)) -> 0 | J99: =G99 / (1 + H99) -> 0 | L99: =IF(C99="","",MONTH(C99)) | M99: =IF(C99="","",YEAR(C99)) | N99: =IF(C99="","",DAY(C99))

Sheet Gastos
B2: PANEL DE GASTOS
D5: =#REF! & " " & TEXT(SUM(tbl_ingresos3[Gasto Total]),"#,##0.00") -> #REF! | F5: =#REF! & " " & TEXT(SUM(tbl_ingresos3[Valor Impuesto]),"#,##0.00") -> #REF! | H5: =#REF! & " " & TEXT(SUM(tbl_ingresos3[Total Neto]),"#,##0.00") -> #REF!
D6: Gastos Brutos | F6: Monto de Impuestos | H6: Gastos Netos
B8: ID | C8: Fecha | D8: Categoría | E8: Descripción | F8: Mét. De Pago | G8: Gasto Total | H8: Impuesto | I8: Valor Impuesto | J8: Total Neto | K8: Notas | L8: M | M8: Y | N8: D
B9: 415 | C9: 45740 | D9: 415 Devolucion Capital | E9: Ingreso del 6-08-25 | F9: Transferencias | G9: 1200000 | H9: 0 | I9: =G9 - (G9 / (1 + H9)) -> 0 | J9: =G9 / (1 + H9) -> 1200000 | K9: Prestamo de V. R a EXT.Real | L9: =IF(C9="","",MONTH(C9)) -> 3 | M9: =IF(C9="","",YEAR(C9)) -> 2025 | N9: =IF(C9="","",DAY(C9)) -> 24
B10: 408 | C10: 46112 | D10: 408 Sueldo administrativos/oficina | E10: pendiente 406.309 | F10: Transferencias B. Santader | G10: 594952 | H10: 0 | I10: =G10 - (G10 / (1 + H10)) -> 0 | J10: =G10 / (1 + H10) -> 594952 | K10: pendiente 406.309 | L10: =IF(C10="","",MONTH(C10)) -> 3 | M10: =IF(C10="","",YEAR(C10)) -> 2026 | N10: =IF(C10="","",DAY(C10)) -> 31
B11: 404 | C11: 46097 | D11: 404 Arriendo | E11: Oficina | F11: Transferencias B. Santader | G11: 673240 | H11: 0 | I11: =G11 - (G11 / (1 + H11)) -> 0 | J11: =G11 / (1 + H11) -> 673240 | K11: pago a Gabriel Lopez | L11: =IF(C11="","",MONTH(C11)) -> 3 | M11: =IF(C11="","",YEAR(C11)) -> 2026 | N11: =IF(C11="","",DAY(C11)) -> 16
C12: 46086 | D12: 416 Oficina | E12: Alimento | F12: Debito B. Santander 2405 | G12: 8800 | H12: 0 | I12: =G12 - (G12 / (1 + H12)) -> 0 | J12: =G12 / (1 + H12) -> 8800 | L12: =IF(C12="","",MONTH(C12)) -> 3 | M12: =IF(C12="","",YEAR(C12)) -> 2026 | N12: =IF(C12="","",DAY(C12)) -> 5
C13: 46100 | D13: 416 Oficina | E13: Gastos oficina varios | F13: Transferencias B. Santader | G13: 100000 | H13: 0 | I13: =G13 - (G13 / (1 + H13)) -> 0 | J13: =G13 / (1 + H13) -> 100000 | K13: varios oficina | L13: =IF(C13="","",MONTH(C13)) -> 3 | M13: =IF(C13="","",YEAR(C13)) -> 2026 | N13: =IF(C13="","",DAY(C13)) -> 19
C14: 46104 | D14: 407 Reunión clientes-personal | E14: personal | F14: Transferencias B. Santader | G14: 20000 | H14: 0 | I14: =G14 - (G14 / (1 + H14)) -> 0 | J14: =G14 / (1 + H14) -> 20000 | K14: reunion personal | L14: =IF(C14="","",MONTH(C14)) -> 3 | M14: =IF(C14="","",YEAR(C14)) -> 2026 | N14: =IF(C14="","",DAY(C14)) -> 23
C15: 46085 | D15: 407 Reunión clientes-personal | E15: CLIENTE | F15: Debito B. Santander 2405 | G15: 9800 | H15: 0 | I15: =G15 - (G15 / (1 + H15)) -> 0 | J15: =G15 / (1 + H15) -> 9800 | K15: REUNION CLIENTE | L15: =IF(C15="","",MONTH(C15)) -> 3 | M15: =IF(C15="","",YEAR(C15)) -> 2026 | N15: =IF(C15="","",DAY(C15)) -> 4
C16: 46084 | D16: 407 Reunión clientes-personal | E16: personal | F16: Debito B. Santander 2405 | G16: 8140 | H16: 0 | I16: =G16 - (G16 / (1 + H16)) -> 0 | J16: =G16 / (1 + H16) -> 8140 | K16: reunion personal | L16: =IF(C16="","",MONTH(C16)) -> 3 | M16: =IF(C16="","",YEAR(C16)) -> 2026 | N16: =IF(C16="","",DAY(C16)) -> 3
C17: 46126 | D17: 410 Telefonía | E17: CLARO | F17: Debito B. Santander 2405 | G17: 8125 | H17: 0.19 | I17: =G17 - (G17 / (1 + H17)) -> 1297.2689 | J17: =G17 / (1 + H17) -> 6827.7311 | L17: =IF(C17="","",MONTH(C17)) -> 4 | M17: =IF(C17="","",YEAR(C17)) -> 2026 | N17: =IF(C17="","",DAY(C17)) -> 14
C18: 46126 | D18: 410 Telefonía | E18: ENTEL EMPRESA | F18: Debito B. Santander 2405 | G18: 43228 | H18: 0.19 | I18: =G18 - (G18 / (1 + H18)) -> 6901.9496 | J18: =G18 / (1 + H18) -> 36326.05 | L18: =IF(C18="","",MONTH(C18)) -> 4 | M18: =IF(C18="","",YEAR(C18)) -> 2026 | N18: =IF(C18="","",DAY(C18)) -> 14
C19: 46126 | D19: 408 Sueldo administrativos/oficina | E19: DIFERENCIA SUELDO MARZO | F19: Debito B. Santander 2405 | G19: 470000 | H19: 0.19 | I19: =G19 - (G19 / (1 + H19)) -> 75042.017 | J19: =G19 / (1 + H19) -> 394957.98 | K19: 63691 DIFERENCIA A FAVOR DE V.R | L19: =IF(C19="","",MONTH(C19)) -> 4 | M19: =IF(C19="","",YEAR(C19)) -> 2026 | N19: =IF(C19="","",DAY(C19)) -> 14
C20: 46126 | D20: 404 Arriendo | E20: ARRIENDO OFICINA | F20: Debito B. Santander 2405 | G20: 673240 | H20: 0.19 | I20: =G20 - (G20 / (1 + H20)) -> 107492.1 | J20: =G20 / (1 + H20) -> 565747.9 | K20: GABRIEL LOPEZ | L20: =IF(C20="","",MONTH(C20)) -> 4 | M20: =IF(C20="","",YEAR(C20)) -> 2026 | N20: =IF(C20="","",DAY(C20)) -> 14
C21: 46127 | D21: 409 Imposiciones administrativo | E21: OCTUBRE-NOVIEMBRE SALDO A CONTADOR | F21: Transferencias B. Santader | G21: 737351 | H21: 0.19 | I21: =G21 - (G21 / (1 + H21)) -> 117728.31 | J21: =G21 / (1 + H21) -> 619622.69 | K21: PREVIRED PEDIR REMMBOLSO AFP CAPITAL | L21: =IF(C21="","",MONTH(C21)) -> 4 | M21: =IF(C21="","",YEAR(C21)) -> 2026 | N21: =IF(C21="","",DAY(C21)) -> 15
C22: 46127 | D22: 409 Imposiciones administrativo | E22: AFC OCTUBRE | F22: Transferencias B. Santader | G22: 156027 | H22: 0.19 | I22: =G22 - (G22 / (1 + H22)) -> 24911.874 | J22: =G22 / (1 + H22) -> 131115.13 | K22: MARICEL | L22: =IF(C22="","",MONTH(C22)) -> 4 | M22: =IF(C22="","",YEAR(C22)) -> 2026 | N22: =IF(C22="","",DAY(C22)) -> 15
C23: 46126 | H23: 0.19 | I23: =G23 - (G23 / (1 + H23)) -> 0 | J23: =G23 / (1 + H23) -> 0 | L23: =IF(C23="","",MONTH(C23)) -> 4 | M23: =IF(C23="","",YEAR(C23)) -> 2026 | N23: =IF(C23="","",DAY(C23)) -> 14
H24: 0.19 | I24: =G24 - (G24 / (1 + H24)) -> 0 | J24: =G24 / (1 + H24) -> 0 | L24: =IF(C24="","",MONTH(C24)) | M24: =IF(C24="","",YEAR(C24)) | N24: =IF(C24="","",DAY(C24))
C25: 3 MARZO 2026 | H25: 0.19 | I25: =G25 - (G25 / (1 + H25)) -> 0 | J25: =G25 / (1 + H25) -> 0 | L25: =IF(C25="","",MONTH(C25)) -> 3 | M25: =IF(C25="","",YEAR(C25)) -> 2026 | N25: =IF(C25="","",DAY(C25)) -> 3
H26: 0.19 | I26: =G26 - (G26 / (1 + H26)) -> 0 | J26: =G26 / (1 + H26) -> 0 | L26: =IF(C26="","",MONTH(C26)) | M26: =IF(C26="","",YEAR(C26)) | N26: =IF(C26="","",DAY(C26))
H27: 0.19 | I27: =G27 - (G27 / (1 + H27)) -> 0 | J27: =G27 / (1 + H27) -> 0 | L27: =IF(C27="","",MONTH(C27)) | M27: =IF(C27="","",YEAR(C27)) | N27: =IF(C27="","",DAY(C27))
H28: 0.19 | I28: =G28 - (G28 / (1 + H28)) -> 0 | J28: =G28 / (1 + H28) -> 0 | L28: =IF(C28="","",MONTH(C28)) | M28: =IF(C28="","",YEAR(C28)) | N28: =IF(C28="","",DAY(C28))
H29: 0.19 | I29: =G29 - (G29 / (1 + H29)) -> 0 | J29: =G29 / (1 + H29) -> 0 | L29: =IF(C29="","",MONTH(C29)) | M29: =IF(C29="","",YEAR(C29)) | N29: =IF(C29="","",DAY(C29))
H30: 0.19 | I30: =G30 - (G30 / (1 + H30)) -> 0 | J30: =G30 / (1 + H30) -> 0 | L30: =IF(C30="","",MONTH(C30)) | M30: =IF(C30="","",YEAR(C30)) | N30: =IF(C30="","",DAY(C30))
H31: 0.19 | I31: =G31 - (G31 / (1 + H31)) -> 0 | J31: =G31 / (1 + H31) -> 0 | L31: =IF(C31="","",MONTH(C31)) | M31: =IF(C31="","",YEAR(C31)) | N31: =IF(C31="","",DAY(C31))
H32: 0.19 | I32: =G32 - (G32 / (1 + H32)) -> 0 | J32: =G32 / (1 + H32) -> 0 | L32: =IF(C32="","",MONTH(C32)) | M32: =IF(C32="","",YEAR(C32)) | N32: =IF(C32="","",DAY(C32))
H33: 0.19 | I33: =G33 - (G33 / (1 + H33)) -> 0 | J33: =G33 / (1 + H33) -> 0 | L33: =IF(C33="","",MONTH(C33)) | M33: =IF(C33="","",YEAR(C33)) | N33: =IF(C33="","",DAY(C33))
H34: 0.19 | I34: =G34 - (G34 / (1 + H34)) -> 0 | J34: =G34 / (1 + H34) -> 0 | L34: =IF(C34="","",MONTH(C34)) | M34: =IF(C34="","",YEAR(C34)) | N34: =IF(C34="","",DAY(C34))
H35: 0.19 | I35: =G35 - (G35 / (1 + H35)) -> 0 | J35: =G35 / (1 + H35) -> 0 | L35: =IF(C35="","",MONTH(C35)) | M35: =IF(C35="","",YEAR(C35)) | N35: =IF(C35="","",DAY(C35))
H36: 0.19 | I36: =G36 - (G36 / (1 + H36)) -> 0 | J36: =G36 / (1 + H36) -> 0 | L36: =IF(C36="","",MONTH(C36)) | M36: =IF(C36="","",YEAR(C36)) | N36: =IF(C36="","",DAY(C36))
H37: 0.19 | I37: =G37 - (G37 / (1 + H37)) -> 0 | J37: =G37 / (1 + H37) -> 0 | L37: =IF(C37="","",MONTH(C37)) | M37: =IF(C37="","",YEAR(C37)) | N37: =IF(C37="","",DAY(C37))
... H133: 0.19 | I133: =G133 - (G133 / (1 + H133)) -> 0 | J133: =G133 / (1 + H133) -> 0 | L133: =IF(C133="","",MONTH(C133)) | M133: =IF(C133="","",YEAR(C133)) | N133: =IF(C133="","",DAY(C133))

Sheet Costos
B2: PANEL DE COSTOS
D5: =#REF! & " " & TEXT(SUM(tbl_ingresos314[Costo Total]),"#,##0.00") -> #REF! | F5: =#REF! & " " & TEXT(SUM(tbl_ingresos314[Valor Impuesto]),"#,##0.00") -> #REF! | H5: =#REF! & " " & TEXT(SUM(tbl_ingresos314[Total Neto]),"#,##0.00") -> #REF!
D6: Costos Brutos | F6: Monto de Impuestos | H6: Costos Netos
B8: ID | C8: Fecha | D8: Categoría | E8: Descripción | F8: Mét. De Pago | G8: Costo Total | H8: Impuesto | I8: Valor Impuesto | J8: Total Neto | K8: Notas | L8: M | M8: Y | N8: D
C9: MARZO 2026 | I9: =G9 - (G9 / (1 + H9)) -> 0 | J9: =G9 / (1 + H9) -> 0 | L9: =IF(C9="","",MONTH(C9)) -> #VALUE! | M9: =IF(C9="","",YEAR(C9)) -> #VALUE! | N9: =IF(C9="","",DAY(C9)) -> #VALUE!
B10: 514 | C10: 46105 | D10: 514materiales/varios | E10: Motobomba | F10: Debito | G10: 242240 | H10: 0.19 | I10: =G10 - (G10 / (1 + H10)) -> 38676.975 | J10: =G10 / (1 + H10) -> 203563.03 | K10: mantención Red Seca | L10: =IF(C10="","",MONTH(C10)) -> 3 | M10: =IF(C10="","",YEAR(C10)) -> 2026 | N10: =IF(C10="","",DAY(C10)) -> 24
B11: 502 | C11: 46106 | D11: 502 Fire Master-Ossa-Startfire | E11: Ext. Soporte, Piton | F11: Debito | G11: 157865 | H11: 0.19 | I11: =G11 - (G11 / (1 + H11)) -> 25205.336 | J11: =G11 / (1 + H11) -> 132659.66 | K11: Fac 33276/FireMaster | L11: =IF(C11="","",MONTH(C11)) -> 3 | M11: =IF(C11="","",YEAR(C11)) -> 2026 | N11: =IF(C11="","",DAY(C11)) -> 25
B12: 505 | C12: 46106 | D12: 505 Ecoex / Transporte insumo | E12: O.T 010-23-379753 | F12: Efectivo | G12: 17000 | H12: 0.19 | I12: =G12 - (G12 / (1 + H12)) -> 2714.2857 | J12: =G12 / (1 + H12) -> 14285.714 | K12: Retiro pedido fireMaster-Fac 33276 | L12: =IF(C12="","",MONTH(C12)) -> 3 | M12: =IF(C12="","",YEAR(C12)) -> 2026 | N12: =IF(C12="","",DAY(C12)) -> 25
B13: 515 | C13: 46106 | D13: 515 Transporte/Combustible | E13: DYFX20 | F13: Debito | G13: 20000 | H13: 0.19 | I13: =G13 - (G13 / (1 + H13)) -> 3193.2773 | J13: =G13 / (1 + H13) -> 16806.723 | K13: camioneta transporte de herramientas | L13: =IF(C13="","",MONTH(C13)) -> 3 | M13: =IF(C13="","",YEAR(C13)) -> 2026 | N13: =IF(C13="","",DAY(C13)) -> 25
L14: =IF(C14="","",MONTH(C14)) | M14: =IF(C14="","",YEAR(C14)) | N14: =IF(C14="","",DAY(C14))
L15: =IF(C15="","",MONTH(C15)) | M15: =IF(C15="","",YEAR(C15)) | N15: =IF(C15="","",DAY(C15))
L16: =IF(C16="","",MONTH(C16)) | M16: =IF(C16="","",YEAR(C16)) | N16: =IF(C16="","",DAY(C16))
L17: =IF(C17="","",MONTH(C17)) | M17: =IF(C17="","",YEAR(C17)) | N17: =IF(C17="","",DAY(C17))
L18: =IF(C18="","",MONTH(C18)) | M18: =IF(C18="","",YEAR(C18)) | N18: =IF(C18="","",DAY(C18))
L19: =IF(C19="","",MONTH(C19)) | M19: =IF(C19="","",YEAR(C19)) | N19: =IF(C19="","",DAY(C19))
L20: =IF(C20="","",MONTH(C20)) | M20: =IF(C20="","",YEAR(C20)) | N20: =IF(C20="","",DAY(C20))
L21: =IF(C21="","",MONTH(C21)) | M21: =IF(C21="","",YEAR(C21)) | N21: =IF(C21="","",DAY(C21))
L22: =IF(C22="","",MONTH(C22)) | M22: =IF(C22="","",YEAR(C22)) | N22: =IF(C22="","",DAY(C22))
L23: =IF(C23="","",MONTH(C23)) | M23: =IF(C23="","",YEAR(C23)) | N23: =IF(C23="","",DAY(C23))
L24: =IF(C24="","",MONTH(C24)) | M24: =IF(C24="","",YEAR(C24)) | N24: =IF(C24="","",DAY(C24))
L25: =IF(C25="","",MONTH(C25)) | M25: =IF(C25="","",YEAR(C25)) | N25: =IF(C25="","",DAY(C25))
... L76: =IF(C76="","",MONTH(C76)) | M76: =IF(C76="","",YEAR(C76)) | N76: =IF(C76="","",DAY(C76))
L77: =IF(#REF!="","",MONTH(#REF!)) -> #REF! | M77: =IF(#REF!="","",YEAR(#REF!)) -> #REF! | N77: =IF(#REF!="","",DAY(#REF!)) -> #REF!
L78: =IF(C78="","",MONTH(C78)) | M78: =IF(C78="","",YEAR(C78)) | N78: =IF(C78="","",DAY(C78))
L79: =IF(C79="","",MONTH(C79)) | M79: =IF(C79="","",YEAR(C79)) | N79: =IF(C79="","",DAY(C79))
L80: =IF(C80="","",MONTH(C80)) | M80: =IF(C80="","",YEAR(C80)) | N80: =IF(C80="","",DAY(C80))
L81: =IF(C81="","",MONTH(C81)) | M81: =IF(C81="","",YEAR(C81)) | N81: =IF(C81="","",DAY(C81))
L82: =IF(C82="","",MONTH(C82)) | M82: =IF(C82="","",YEAR(C82)) | N82: =IF(C82="","",DAY(C82))
L83: =IF(C83="","",MONTH(C83)) | M83: =IF(C83="","",YEAR(C83)) | N83: =IF(C83="","",DAY(C83))
L84: =IF(C84="","",MONTH(C84)) | M84: =IF(C84="","",YEAR(C84)) | N84: =IF(C84="","",DAY(C84))
L85: =IF(C85="","",MONTH(C85)) | M85: =IF(C85="","",YEAR(C85)) | N85: =IF(C85="","",DAY(C85))
L86: =IF(C86="","",MONTH(C86)) | M86: =IF(C86="","",YEAR(C86)) | N86: =IF(C86="","",DAY(C86))
L87: =IF(C87="","",MONTH(C87)) | M87: =IF(C87="","",YEAR(C87)) | N87: =IF(C87="","",DAY(C87))
L88: =IF(C88="","",MONTH(C88)) | M88: =IF(C88="","",YEAR(C88)) | N88: =IF(C88="","",DAY(C88))
L89: =IF(C89="","",MONTH(C89)) | M89: =IF(C89="","",YEAR(C89)) | N89: =IF(C89="","",DAY(C89))
... L144: =IF(C144="","",MONTH(C144)) | M144: =IF(C144="","",YEAR(C144)) | N144: =IF(C144="","",DAY(C144))
I145: =G145 - (G145 / (1 + H145)) -> 0 | J145: =G145 / (1 + H145) -> 0 | L145: =IF(C145="","",MONTH(C145)) | M145: =IF(C145="","",YEAR(C145)) | N145: =IF(C145="","",DAY(C145))
I146: =G146 - (G146 / (1 + H146)) -> 0 | J146: =G146 / (1 + H146) -> 0 | L146: =IF(C146="","",MONTH(C146)) | M146: =IF(C146="","",YEAR(C146)) | N146: =IF(C146="","",DAY(C146))
I147: =G147 - (G147 / (1 + H147)) -> 0 | J147: =G147 / (1 + H147) -> 0 | L147: =IF(C147="","",MONTH(C147)) | M147: =IF(C147="","",YEAR(C147)) | N147: =IF(C147="","",DAY(C147))
I148: =G148 - (G148 / (1 + H148)) -> 0 | J148: =G148 / (1 + H148) -> 0 | L148: =IF(C148="","",MONTH(C148)) | M148: =IF(C148="","",YEAR(C148)) | N148: =IF(C148="","",DAY(C148))
I149: =G149 - (G149 / (1 + H149)) -> 0 | J149: =G149 / (1 + H149) -> 0 | L149: =IF(C149="","",MONTH(C149)) | M149: =IF(C149="","",YEAR(C149)) | N149: =IF(C149="","",DAY(C149))
I150: =G150 - (G150 / (1 + H150)) -> 0 | J150: =G150 / (1 + H150) -> 0 | L150: =IF(C150="","",MONTH(C150)) | M150: =IF(C150="","",YEAR(C150)) | N150: =IF(C150="","",DAY(C150))
I151: =G151 - (G151 / (1 + H151)) -> 0 | J151: =G151 / (1 + H151) -> 0 | L151: =IF(C151="","",MONTH(C151)) | M151: =IF(C151="","",YEAR(C151)) | N151: =IF(C151="","",DAY(C151))
I152: =G152 - (G152 / (1 + H152)) -> 0 | J152: =G152 / (1 + H152) -> 0 | L152: =IF(C152="","",MONTH(C152)) | M152: =IF(C152="","",YEAR(C152)) | N152: =IF(C152="","",DAY(C152))
I153: =G153 - (G153 / (1 + H153)) -> 0 | J153: =G153 / (1 + H153) -> 0 | L153: =IF(C153="","",MONTH(C153)) | M153: =IF(C153="","",YEAR(C153)) | N153: =IF(C153="","",DAY(C153))
I154: =G154 - (G154 / (1 + H154)) -> 0 | J154: =G154 / (1 + H154) -> 0 | L154: =IF(C154="","",MONTH(C154)) | M154: =IF(C154="","",YEAR(C154)) | N154: =IF(C154="","",DAY(C154))
I155: =G155 - (G155 / (1 + H155)) -> 0 | J155: =G155 / (1 + H155) -> 0 | L155: =IF(C155="","",MONTH(C155)) | M155: =IF(C155="","",YEAR(C155)) | N155: =IF(C155="","",DAY(C155))
I156: =G156 - (G156 / (1 + H156)) -> 0 | J156: =G156 / (1 + H156) -> 0 | L156: =IF(C156="","",MONTH(C156)) | M156: =IF(C156="","",YEAR(C156)) | N156: =IF(C156="","",DAY(C156))
... I189: =G189 - (G189 / (1 + H189)) -> 0 | J189: =G189 / (1 + H189) -> 0 | L189: =IF(C189="","",MONTH(C189)) | M189: =IF(C189="","",YEAR(C189)) | N189: =IF(C189="","",DAY(C189))

Sheet Datos
B2: Ingresos | C2: =#REF! -> #REF! | D2: =#REF! -> #REF! | E2: =#REF! -> #REF! | F2: =#REF! -> #REF! | G2: =#REF! -> #REF! | H2: =#REF! -> #REF! | I2: =#REF! -> #REF! | J2: =#REF! -> #REF! | ... N2: =#REF! -> #REF! | O2: TOTAL | Q2: GASTOS | R2: =#REF! -> #REF! | S2: =#REF! -> #REF! | T2: =#REF! -> #REF! | U2: =#REF! -> #REF! | V2: =#REF! -> #REF! | W2: =#REF! -> #REF! | X2: =#REF! -> #REF! | Y2: =#REF! -> #REF! | ... AC2: =#REF! -> #REF! | AD2: TOTAL | AF2: Resumen anual: Ingresos vs Gastos
B3: M | C3: =IF(C2="","",MONTH(C2)) -> #REF! | D3: =IF(D2="","",MONTH(D2)) -> #REF! | E3: =IF(E2="","",MONTH(E2)) -> #REF! | F3: =IF(F2="","",MONTH(F2)) -> #REF! | G3: =IF(G2="","",MONTH(G2)) -> #REF! | H3: =IF(H2="","",MONTH(H2)) -> #REF! | I3: =IF(I2="","",MONTH(I2)) -> #REF! | J3: =IF(J2="","",MONTH(J2)) -> #REF! | ... N3: =IF(N2="","",MONTH(N2)) -> #REF! | Q3: M | R3: =IF(R2="","",MONTH(R2)) -> #REF! | S3: =IF(S2="","",MONTH(S2)) -> #REF! | T3: =IF(T2="","",MONTH(T2)) -> #REF! | U3: =IF(U2="","",MONTH(U2)) -> #REF! | V3: =IF(V2="","",MONTH(V2)) -> #REF! | W3: =IF(W2="","",MONTH(W2)) -> #REF! | X3: =IF(X2="","",MONTH(X2)) -> #REF! | Y3: =IF(Y2="","",MONTH(Y2)) -> #REF! | ... AC3: =IF(AC2="","",MONTH(AC2)) -> #REF! | AG3: Ingresos | AH3: Gastos | AI3: Costos | AM3: =#REF! -> #REF! | AN3: =#REF! -> #REF! | AO3: =#REF! -> #REF! | AP3: =#REF! -> #REF! | AQ3: =#REF! -> #REF! | AR3: =#REF! -> #REF! | AS3: =#REF! -> #REF! | AT3: =#REF! -> #REF! | ... AX3: =#REF! -> #REF!
B4: Y | C4: =IF(C2="","",YEAR(C2)) -> #REF! | D4: =IF(D2="","",YEAR(D2)) -> #REF! | E4: =IF(E2="","",YEAR(E2)) -> #REF! | F4: =IF(F2="","",YEAR(F2)) -> #REF! | G4: =IF(G2="","",YEAR(G2)) -> #REF! | H4: =IF(H2="","",YEAR(H2)) -> #REF! | I4: =IF(I2="","",YEAR(I2)) -> #REF! | J4: =IF(J2="","",YEAR(J2)) -> #REF! | ... N4: =IF(N2="","",YEAR(N2)) -> #REF! | Q4: Y | R4: =IF(R2="","",YEAR(R2)) -> #REF! | S4: =IF(S2="","",YEAR(S2)) -> #REF! | T4: =IF(T2="","",YEAR(T2)) -> #REF! | U4: =IF(U2="","",YEAR(U2)) -> #REF! | V4: =IF(V2="","",YEAR(V2)) -> #REF! | W4: =IF(W2="","",YEAR(W2)) -> #REF! | X4: =IF(X2="","",YEAR(X2)) -> #REF! | Y4: =IF(Y2="","",YEAR(Y2)) -> #REF! | ... AC4: =IF(AC2="","",YEAR(AC2)) -> #REF! | AF4: =#REF! -> #REF! | AG4: =#REF! -> #REF! | AH4: =#REF! -> #REF! | AI4: =#REF! -> #REF! | AM4: =IF(AM3="","",MONTH(AM3)) -> #REF! | AN4: =IF(AN3="","",MONTH(AN3)) -> #REF! | AO4: =IF(AO3="","",MONTH(AO3)) -> #REF! | AP4: =IF(AP3="","",MONTH(AP3)) -> #REF! | AQ4: =IF(AQ3="","",MONTH(AQ3)) -> #REF! | AR4: =IF(AR3="","",MONTH(AR3)) -> #REF! | AS4: =IF(AS3="","",MONTH(AS3)) -> #REF! | AT4: =IF(AT3="","",MONTH(AT3)) -> #REF! | ... AX4: =IF(AX3="","",MONTH(AX3)) -> #REF!
AF5: =#REF! -> #REF! | AG5: =#REF! -> #REF! | AH5: =#REF! -> #REF! | AI5: =#REF! -> #REF! | AM5: =IF(AM3="","",YEAR(AM3)) -> #REF! | AN5: =IF(AN3="","",YEAR(AN3)) -> #REF! | AO5: =IF(AO3="","",YEAR(AO3)) -> #REF! | AP5: =IF(AP3="","",YEAR(AP3)) -> #REF! | AQ5: =IF(AQ3="","",YEAR(AQ3)) -> #REF! | AR5: =IF(AR3="","",YEAR(AR3)) -> #REF! | AS5: =IF(AS3="","",YEAR(AS3)) -> #REF! | AT5: =IF(AT3="","",YEAR(AT3)) -> #REF! | ... AX5: =IF(AX3="","",YEAR(AX3)) -> #REF!
B6: CATEGORÍAS DE INGRESOS | Q6: CATEGORÍAS DE GASTOS | AF6: =#REF! -> #REF! | AG6: =#REF! -> #REF! | AH6: =#REF! -> #REF! | AI6: =#REF! -> #REF! | AK6: Ingresos Netos | AM6: =SUMIFS(Ingresos!$J$9:$J$3900,Ingresos!$L$9:$L$3900,$AM$4,Ingresos!$M$9:$M$3900,$AM$5) -> 0 | AN6: =SUMIFS(Ingresos!$J$9:$J$3900,Ingresos!$L$9:$L$3900,$AN$4,Ingresos!$M$9:$M$3900,$AN$5) -> 0 | AO6: =SUMIFS(Ingresos!$J$9:$J$3900,Ingresos!$L$9:$L$3900,$AO$4,Ingresos!$M$9:$M$3900,$AO$5) -> 0 | AP6: =SUMIFS(Ingresos!$J$9:$J$3900,Ingresos!$L$9:$L$3900,$AP$4,Ingresos!$M$9:$M$3900,$AP$5) -> 0 | AQ6: =SUMIFS(Ingresos!$J$9:$J$3900,Ingresos!$L$9:$L$3900,$AQ$4,Ingresos!$M$9:$M$3900,$AQ$5) -> 0 | AR6: =SUMIFS(Ingresos!$J$9:$J$3900,Ingresos!$L$9:$L$3900,$AR$4,Ingresos!$M$9:$M$3900,$AR$5) -> 0 | AS6: =SUMIFS(Ingresos!$J$9:$J$3900,Ingresos!$L$9:$L$3900,$AS$4,Ingresos!$M$9:$M$3900,$AS$5) -> 0 | AT6: =SUMIFS(Ingresos!$J$9:$J$3900,Ingresos!$L$9:$L$3900,$AT$4,Ingresos!$M$9:$M$3900,$AT$5) -> 0 | AU6: =SUMIFS(Ingresos!$J$9:$J$3900,Ingresos!$L$9:$L$3900,$AU$4,Ingresos!$M$9:$M$3900,$AU$5) -> 0 | AV6: =SUMIFS(Ingresos!$J$9:$J$3900,Ingresos!$L$9:$L$3900,$AV$4,Ingresos!$M$9:$M$3900,$AV$5) -> 0 | AW6: =SUMIFS(Ingresos!$J$9:$J$3900,Ingresos!$L$9:$L$3900,$AW$4,Ingresos!$M$9:$M$3900,$AW$5) -> 0 | AX6: =SUMIFS(Ingresos!$J$9:$J$3900,Ingresos!$L$9:$L$3900,$AX$4,Ingresos!$M$9:$M$3900,$AX$5) -> 0
B7: =#REF! -> #REF! | C7: =SUMIFS(Ingresos!$J$9:$J$3900, Ingresos!$L$9:$L$3900, $C$3, Ingresos!$M$9:$M$3900, $C$4, Ingresos!$D$9:$D$3900, B7) -> 0 | D7: =SUMIFS(Ingresos!$J$9:$J$3900, Ingresos!$L$9:$L$3900, $D$3, Ingresos!$M$9:$M$3900, $D$4, Ingresos!$D$9:$D$3900, B7) -> 0 | E7: =SUMIFS(Ingresos!$J$9:$J$3900, Ingresos!$L$9:$L$3900, $E$3, Ingresos!$M$9:$M$3900, $E$4, Ingresos!$D$9:$D$3900, B7) -> 0 | F7: =SUMIFS(Ingresos!$J$9:$J$3900, Ingresos!$L$9:$L$3900, $F$3, Ingresos!$M$9:$M$3900, $F$4, Ingresos!$D$9:$D$3900, B7) -> 0 | G7: =SUMIFS(Ingresos!$J$9:$J$3900, Ingresos!$L$9:$L$3900, $G$3, Ingresos!$M$9:$M$3900, $G$4, Ingresos!$D$9:$D$3900, B7) -> 0 | H7: =SUMIFS(Ingresos!$J$9:$J$3900, Ingresos!$L$9:$L$3900, $H$3, Ingresos!$M$9:$M$3900, $H$4, Ingresos!$D$9:$D$3900, B7) -> 0 | I7: =SUMIFS(Ingresos!$J$9:$J$3900, Ingresos!$L$9:$L$3900, $I$3, Ingresos!$M$9:$M$3900, $I$4, Ingresos!$D$9:$D$3900, B7) -> 0 | J7: =SUMIFS(Ingresos!$J$9:$J$3900, Ingresos!$L$9:$L$3900, $J$3, Ingresos!$M$9:$M$3900, $J$4, Ingresos!$D$9:$D$3900, B7) -> 0 | K7: =SUMIFS(Ingresos!$J$9:$J$3900, Ingresos!$L$9:$L$3900, $K$3, Ingresos!$M$9:$M$3900, $K$4, Ingresos!$D$9:$D$3900, B7) -> 0 | L7: =SUMIFS(Ingresos!$J$9:$J$3900, Ingresos!$L$9:$L$3900, $L$3, Ingresos!$M$9:$M$3900, $L$4, Ingresos!$D$9:$D$3900, B7) -> 0 | M7: =SUMIFS(Ingresos!$J$9:$J$3900, Ingresos!$L$9:$L$3900, $M$3, Ingresos!$M$9:$M$3900, $M$4, Ingresos!$D$9:$D$3900, B7) -> 0 | N7: =SUMIFS(Ingresos!$J$9:$J$3900, Ingresos!$L$9:$L$3900, $N$3, Ingresos!$M$9:$M$3900, $N$4, Ingresos!$D$9:$D$3900, B7) -> 0 | O7: =SUM(C7:N7) -> 0 | Q7: =#REF! -> #REF! | R7: =SUMIFS(Gastos!$J$9:$J$4091, Gastos!$L$9:$L$4091, $R$3, Gastos!$M$9:$M$4091, $R$4, Gastos!$D$9:$D$4091, Q7) -> 0 | S7: =SUMIFS(Gastos!$J$9:$J$4091, Gastos!$L$9:$L$4091, $S$3, Gastos!$M$9:$M$4091, $S$4, Gastos!$D$9:$D$4091, Q7) -> 0 | T7: =SUMIFS(Gastos!$J$9:$J$4091, Gastos!$L$9:$L$4091, $T$3, Gastos!$M$9:$M$4091, $T$4, Gastos!$D$9:$D$4091, Q7) -> 0 | U7: =SUMIFS(Gastos!$J$9:$J$4091, Gastos!$L$9:$L$4091, $U$3, Gastos!$M$9:$M$4091, $U$4, Gastos!$D$9:$D$4091, Q7) -> 0 | V7: =SUMIFS(Gastos!$J$9:$J$4091, Gastos!$L$9:$L$4091, $V$3, Gastos!$M$9:$M$4091, $V$4, Gastos!$D$9:$D$4091, Q7) -> 0 | W7: =SUMIFS(Gastos!$J$9:$J$4091, Gastos!$L$9:$L$4091, $W$3, Gastos!$M$9:$M$4091, $W$4, Gastos!$D$9:$D$4091, Q7) -> 0 | X7: =SUMIFS(Gastos!$J$9:$J$4091, Gastos!$L$9:$L$4091, $X$3, Gastos!$M$9:$M$4091, $X$4, Gastos!$D$9:$D$4091, Q7) -> 0 | Y7: =SUMIFS(Gastos!$J$9:$J$4091, Gastos!$L$9:$L$4091, $Y$3, Gastos!$M$9:$M$4091, $Y$4, Gastos!$D$9:$D$4091, Q7) -> 0 | Z7: =SUMIFS(Gastos!$J$9:$J$4091, Gastos!$L$9:$L$4091, $Z$3, Gastos!$M$9:$M$4091, $Z$4, Gastos!$D$9:$D$4091, Q7) -> 0 | AA7: =SUMIFS(Gastos!$J$9:$J$4091, Gastos!$L$9:$L$4091, $AA$3, Gastos!$M$9:$M$4091, $AA$4, Gastos!$D$9:$D$4091, Q7) -> 0 | AB7: =SUMIFS(Gastos!$J$9:$J$4091, Gastos!$L$9:$L$4091, $AB$3, Gastos!$M$9:$M$4091, $AB$4, Gastos!$D$9:$D$4091, Q7) -> 0 | AC7: =SUMIFS(Gastos!$J$9:$J$4091, Gastos!$L$9:$L$4091, $AC$3, Gastos!$M$9:$M$4091, $AC$4, Gastos!$D$9:$D$4091, Q7) -> 0 | AD7: =SUM(R7:AC7) -> 0 | AF7: =#REF! -> #REF! | AG7: =#REF! -> #REF! | AH7: =#REF! -> #REF! | AI7: =#REF! -> #REF! | AK7: Gastos y Costos Totales | AM7: =#REF!+#REF! -> #REF! | AN7: =#REF!+#REF! -> #REF! | AO7: =#REF!+#REF! -> #REF! | AP7: =#REF!+#REF! -> #REF! | AQ7: =#REF!+#REF! -> #REF! | AR7: =#REF!+#REF! -> #REF! | AS7: =#REF!+#REF! -> #REF! | AT7: =#REF!+#REF! -> #REF! | ... AX7: =#REF!+#REF! -> #REF!
B8: =#REF! -> #REF! | C8: =SUMIFS(Ingresos!$J$9:$J$3900, Ingresos!$L$9:$L$3900, $C$3, Ingresos!$M$9:$M$3900, $C$4, Ingresos!$D$9:$D$3900, B8) -> 0 | D8: =SUMIFS(Ingresos!$J$9:$J$3900, Ingresos!$L$9:$L$3900, $D$3, Ingresos!$M$9:$M$3900, $D$4, Ingresos!$D$9:$D$3900, B8) -> 0 | E8: =SUMIFS(Ingresos!$J$9:$J$3900, Ingresos!$L$9:$L$3900, $E$3, Ingresos!$M$9:$M$3900, $E$4, Ingresos!$D$9:$D$3900, B8) -> 0 | F8: =SUMIFS(Ingresos!$J$9:$J$3900, Ingresos!$L$9:$L$3900, $F$3, Ingresos!$M$9:$M$3900, $F$4, Ingresos!$D$9:$D$3900, B8) -> 0 | G8: =SUMIFS(Ingresos!$J$9:$J$3900, Ingresos!$L$9:$L$3900, $G$3, Ingresos!$M$9:$M$3900, $G$4, Ingresos!$D$9:$D$3900, B8) -> 0 | H8: =SUMIFS(Ingresos!$J$9:$J$3900, Ingresos!$L$9:$L$3900, $H$3, Ingresos!$M$9:$M$3900, $H$4, Ingresos!$D$9:$D$3900, B8) -> 0 | I8: =SUMIFS(Ingresos!$J$9:$J$3900, Ingresos!$L$9:$L$3900, $I$3, Ingresos!$M$9:$M$3900, $I$4, Ingresos!$D$9:$D$3900, B8) -> 0 | J8: =SUMIFS(Ingresos!$J$9:$J$3900, Ingresos!$L$9:$L$3900, $J$3, Ingresos!$M$9:$M$3900, $J$4, Ingresos!$D$9:$D$3900, B8) -> 0 | K8: =SUMIFS(Ingresos!$J$9:$J$3900, Ingresos!$L$9:$L$3900, $K$3, Ingresos!$M$9:$M$3900, $K$4, Ingresos!$D$9:$D$3900, B8) -> 0 | L8: =SUMIFS(Ingresos!$J$9:$J$3900, Ingresos!$L$9:$L$3900, $L$3, Ingresos!$M$9:$M$3900, $L$4, Ingresos!$D$9:$D$3900, B8) -> 0 | M8: =SUMIFS(Ingresos!$J$9:$J$3900, Ingresos!$L$9:$L$3900, $M$3, Ingresos!$M$9:$M$3900, $M$4, Ingresos!$D$9:$D$3900, B8) -> 0 | N8: =SUMIFS(Ingresos!$J$9:$J$3900, Ingresos!$L$9:$L$3900, $N$3, Ingresos!$M$9:$M$3900, $N$4, Ingresos!$D$9:$D$3900, B8) -> 0 | O8: =SUM(C8:N8) -> 0 | Q8: =#REF! -> #REF! | R8: =SUMIFS(Gastos!$J$9:$J$4091, Gastos!$L$9:$L$4091, $R$3, Gastos!$M$9:$M$4091, $R$4, Gastos!$D$9:$D$4091, Q8) -> 0 | S8: =SUMIFS(Gastos!$J$9:$J$4091, Gastos!$L$9:$L$4091, $S$3, Gastos!$M$9:$M$4091, $S$4, Gastos!$D$9:$D$4091, Q8) -> 0 | T8: =SUMIFS(Gastos!$J$9:$J$4091, Gastos!$L$9:$L$4091, $T$3, Gastos!$M$9:$M$4091, $T$4, Gastos!$D$9:$D$4091, Q8) -> 0 | U8: =SUMIFS(Gastos!$J$9:$J$4091, Gastos!$L$9:$L$4091, $U$3, Gastos!$M$9:$M$4091, $U$4, Gastos!$D$9:$D$4091, Q8) -> 0 | V8: =SUMIFS(Gastos!$J$9:$J$4091, Gastos!$L$9:$L$4091, $V$3, Gastos!$M$9:$M$4091, $V$4, Gastos!$D$9:$D$4091, Q8) -> 0 | W8: =SUMIFS(Gastos!$J$9:$J$4091, Gastos!$L$9:$L$4091, $W$3, Gastos!$M$9:$M$4091, $W$4, Gastos!$D$9:$D$4091, Q8) -> 0 | X8: =SUMIFS(Gastos!$J$9:$J$4091, Gastos!$L$9:$L$4091, $X$3, Gastos!$M$9:$M$4091, $X$4, Gastos!$D$9:$D$4091, Q8) -> 0 | Y8: =SUMIFS(Gastos!$J$9:$J$4091, Gastos!$L$9:$L$4091, $Y$3, Gastos!$M$9:$M$4091, $Y$4, Gastos!$D$9:$D$4091, Q8) -> 0 | Z8: =SUMIFS(Gastos!$J$9:$J$4091, Gastos!$L$9:$L$4091, $Z$3, Gastos!$M$9:$M$4091, $Z$4, Gastos!$D$9:$D$4091, Q8) -> 0 | AA8: =SUMIFS(Gastos!$J$9:$J$4091, Gastos!$L$9:$L$4091, $AA$3, Gastos!$M$9:$M$4091, $AA$4, Gastos!$D$9:$D$4091, Q8) -> 0 | AB8: =SUMIFS(Gastos!$J$9:$J$4091, Gastos!$L$9:$L$4091, $AB$3, Gastos!$M$9:$M$4091, $AB$4, Gastos!$D$9:$D$4091, Q8) -> 0 | AC8: =SUMIFS(Gastos!$J$9:$J$4091, Gastos!$L$9:$L$4091, $AC$3, Gastos!$M$9:$M$4091, $AC$4, Gastos!$D$9:$D$4091, Q8) -> 0 | AD8: =SUM(R8:AC8) -> 0 | AF8: =#REF! -> #REF! | AG8: =#REF! -> #REF! | AH8: =#REF! -> #REF! | AI8: =#REF! -> #REF!
B9: =#REF! -> #REF! | C9: =SUMIFS(Ingresos!$J$9:$J$3900, Ingresos!$L$9:$L$3900, $C$3, Ingresos!$M$9:$M$3900, $C$4, Ingresos!$D$9:$D$3900, B9) -> 0 | D9: =SUMIFS(Ingresos!$J$9:$J$3900, Ingresos!$L$9:$L$3900, $D$3, Ingresos!$M$9:$M$3900, $D$4, Ingresos!$D$9:$D$3900, B9) -> 0 | E9: =SUMIFS(Ingresos!$J$9:$J$3900, Ingresos!$L$9:$L$3900, $E$3, Ingresos!$M$9:$M$3900, $E$4, Ingresos!$D$9:$D$3900, B9) -> 0 | F9: =SUMIFS(Ingresos!$J$9:$J$3900, Ingresos!$L$9:$L$3900, $F$3, Ingresos!$M$9:$M$3900, $F$4, Ingresos!$D$9:$D$3900, B9) -> 0 | G9: =SUMIFS(Ingresos!$J$9:$J$3900, Ingresos!$L$9:$L$3900, $G$3, Ingresos!$M$9:$M$3900, $G$4, Ingresos!$D$9:$D$3900, B9) -> 0 | H9: =SUMIFS(Ingresos!$J$9:$J$3900, Ingresos!$L$9:$L$3900, $H$3, Ingresos!$M$9:$M$3900, $H$4, Ingresos!$D$9:$D$3900, B9) -> 0 | I9: =SUMIFS(Ingresos!$J$9:$J$3900, Ingresos!$L$9:$L$3900, $I$3, Ingresos!$M$9:$M$3900, $I$4, Ingresos!$D$9:$D$3900, B9) -> 0 | J9: =SUMIFS(Ingresos!$J$9:$J$3900, Ingresos!$L$9:$L$3900, $J$3, Ingresos!$M$9:$M$3900, $J$4, Ingresos!$D$9:$D$3900, B9) -> 0 | K9: =SUMIFS(Ingresos!$J$9:$J$3900, Ingresos!$L$9:$L$3900, $K$3, Ingresos!$M$9:$M$3900, $K$4, Ingresos!$D$9:$D$3900, B9) -> 0 | L9: =SUMIFS(Ingresos!$J$9:$J$3900, Ingresos!$L$9:$L$3900, $L$3, Ingresos!$M$9:$M$3900, $L$4, Ingresos!$D$9:$D$3900, B9) -> 0 | M9: =SUMIFS(Ingresos!$J$9:$J$3900, Ingresos!$L$9:$L$3900, $M$3, Ingresos!$M$9:$M$3900, $M$4, Ingresos!$D$9:$D$3900, B9) -> 0 | N9: =SUMIFS(Ingresos!$J$9:$J$3900, Ingresos!$L$9:$L$3900, $N$3, Ingresos!$M$9:$M$3900, $N$4, Ingresos!$D$9:$D$3900, B9) -> 0 | O9: =SUM(C9:N9) -> 0 | Q9: =#REF! -> #REF! | R9: =SUMIFS(Gastos!$J$9:$J$4091, Gastos!$L$9:$L$4091, $R$3, Gastos!$M$9:$M$4091, $R$4, Gastos!$D$9:$D$4091, Q9) -> 0 | S9: =SUMIFS(Gastos!$J$9:$J$4091, Gastos!$L$9:$L$4091, $S$3, Gastos!$M$9:$M$4091, $S$4, Gastos!$D$9:$D$4091, Q9) -> 0 | T9: =SUMIFS(Gastos!$J$9:$J$4091, Gastos!$L$9:$L$4091, $T$3, Gastos!$M$9:$M$4091, $T$4, Gastos!$D$9:$D$4091, Q9) -> 0 | U9: =SUMIFS(Gastos!$J$9:$J$4091, Gastos!$L$9:$L$4091, $U$3, Gastos!$M$9:$M$4091, $U$4, Gastos!$D$9:$D$4091, Q9) -> 0 | V9: =SUMIFS(Gastos!$J$9:$J$4091, Gastos!$L$9:$L$4091, $V$3, Gastos!$M$9:$M$4091, $V$4, Gastos!$D$9:$D$4091, Q9) -> 0 | W9: =SUMIFS(Gastos!$J$9:$J$4091, Gastos!$L$9:$L$4091, $W$3, Gastos!$M$9:$M$4091, $W$4, Gastos!$D$9:$D$4091, Q9) -> 0 | X9: =SUMIFS(Gastos!$J$9:$J$4091, Gastos!$L$9:$L$4091, $X$3, Gastos!$M$9:$M$4091, $X$4, Gastos!$D$9:$D$4091, Q9) -> 0 | Y9: =SUMIFS(Gastos!$J$9:$J$4091, Gastos!$L$9:$L$4091, $Y$3, Gastos!$M$9:$M$4091, $Y$4, Gastos!$D$9:$D$4091, Q9) -> 0 | Z9: =SUMIFS(Gastos!$J$9:$J$4091, Gastos!$L$9:$L$4091, $Z$3, Gastos!$M$9:$M$4091, $Z$4, Gastos!$D$9:$D$4091, Q9) -> 0 | AA9: =SUMIFS(Gastos!$J$9:$J$4091, Gastos!$L$9:$L$4091, $AA$3, Gastos!$M$9:$M$4091, $AA$4, Gastos!$D$9:$D$4091, Q9) -> 0 | AB9: =SUMIFS(Gastos!$J$9:$J$4091, Gastos!$L$9:$L$4091, $AB$3, Gastos!$M$9:$M$4091, $AB$4, Gastos!$D$9:$D$4091, Q9) -> 0 | AC9: =SUMIFS(Gastos!$J$9:$J$4091, Gastos!$L$9:$L$4091, $AC$3, Gastos!$M$9:$M$4091, $AC$4, Gastos!$D$9:$D$4091, Q9) -> 0 | AD9: =SUM(R9:AC9) -> 0 | AF9: =#REF! -> #REF! | AG9: =#REF! -> #REF! | AH9: =#REF! -> #REF! | AI9: =#REF! -> #REF! | AK9: Reaultado por Mes | AM9: =AM6-AM7 -> #REF! | AN9: =AN6-AN7 -> #REF! | AO9: =AO6-AO7 -> #REF! | AP9: =AP6-AP7 -> #REF! | AQ9: =AQ6-AQ7 -> #REF! | AR9: =AR6-AR7 -> #REF! | AS9: =AS6-AS7 -> #REF! | AT9: =AT6-AT7 -> #REF! | ... AX9: =AX6-AX7 -> #REF!
B10: =#REF! -> #REF! | C10: =SUMIFS(Ingresos!$J$9:$J$3900, Ingresos!$L$9:$L$3900, $C$3, Ingresos!$M$9:$M$3900, $C$4, Ingresos!$D$9:$D$3900, B10) -> 0 | D10: =SUMIFS(Ingresos!$J$9:$J$3900, Ingresos!$L$9:$L$3900, $D$3, Ingresos!$M$9:$M$3900, $D$4, Ingresos!$D$9:$D$3900, B10) -> 0 | E10: =SUMIFS(Ingresos!$J$9:$J$3900, Ingresos!$L$9:$L$3900, $E$3, Ingresos!$M$9:$M$3900, $E$4, Ingresos!$D$9:$D$3900, B10) -> 0 | F10: =SUMIFS(Ingresos!$J$9:$J$3900, Ingresos!$L$9:$L$3900, $F$3, Ingresos!$M$9:$M$3900, $F$4, Ingresos!$D$9:$D$3900, B10) -> 0 | G10: =SUMIFS(Ingresos!$J$9:$J$3900, Ingresos!$L$9:$L$3900, $G$3, Ingresos!$M$9:$M$3900, $G$4, Ingresos!$D$9:$D$3900, B10) -> 0 | H10: =SUMIFS(Ingresos!$J$9:$J$3900, Ingresos!$L$9:$L$3900, $H$3, Ingresos!$M$9:$M$3900, $H$4, Ingresos!$D$9:$D$3900, B10) -> 0 | I10: =SUMIFS(Ingresos!$J$9:$J$3900, Ingresos!$L$9:$L$3900, $I$3, Ingresos!$M$9:$M$3900, $I$4, Ingresos!$D$9:$D$3900, B10) -> 0 | J10: =SUMIFS(Ingresos!$J$9:$J$3900, Ingresos!$L$9:$L$3900, $J$3, Ingresos!$M$9:$M$3900, $J$4, Ingresos!$D$9:$D$3900, B10) -> 0 | K10: =SUMIFS(Ingresos!$J$9:$J$3900, Ingresos!$L$9:$L$3900, $K$3, Ingresos!$M$9:$M$3900, $K$4, Ingresos!$D$9:$D$3900, B10) -> 0 | L10: =SUMIFS(Ingresos!$J$9:$J$3900, Ingresos!$L$9:$L$3900, $L$3, Ingresos!$M$9:$M$3900, $L$4, Ingresos!$D$9:$D$3900, B10) -> 0 | M10: =SUMIFS(Ingresos!$J$9:$J$3900, Ingresos!$L$9:$L$3900, $M$3, Ingresos!$M$9:$M$3900, $M$4, Ingresos!$D$9:$D$3900, B10) -> 0 | N10: =SUMIFS(Ingresos!$J$9:$J$3900, Ingresos!$L$9:$L$3900, $N$3, Ingresos!$M$9:$M$3900, $N$4, Ingresos!$D$9:$D$3900, B10) -> 0 | O10: =SUM(C10:N10) -> 0 | Q10: =#REF! -> #REF! | R10: =SUMIFS(Gastos!$J$9:$J$4091, Gastos!$L$9:$L$4091, $R$3, Gastos!$M$9:$M$4091, $R$4, Gastos!$D$9:$D$4091, Q10) -> 0 | S10: =SUMIFS(Gastos!$J$9:$J$4091, Gastos!$L$9:$L$4091, $S$3, Gastos!$M$9:$M$4091, $S$4, Gastos!$D$9:$D$4091, Q10) -> 0 | T10: =SUMIFS(Gastos!$J$9:$J$4091, Gastos!$L$9:$L$4091, $T$3, Gastos!$M$9:$M$4091, $T$4, Gastos!$D$9:$D$4091, Q10) -> 0 | U10: =SUMIFS(Gastos!$J$9:$J$4091, Gastos!$L$9:$L$4091, $U$3, Gastos!$M$9:$M$4091, $U$4, Gastos!$D$9:$D$4091, Q10) -> 0 | V10: =SUMIFS(Gastos!$J$9:$J$4091, Gastos!$L$9:$L$4091, $V$3, Gastos!$M$9:$M$4091, $V$4, Gastos!$D$9:$D$4091, Q10) -> 0 | W10: =SUMIFS(Gastos!$J$9:$J$4091, Gastos!$L$9:$L$4091, $W$3, Gastos!$M$9:$M$4091, $W$4, Gastos!$D$9:$D$4091, Q10) -> 0 | X10: =SUMIFS(Gastos!$J$9:$J$4091, Gastos!$L$9:$L$4091, $X$3, Gastos!$M$9:$M$4091, $X$4, Gastos!$D$9:$D$4091, Q10) -> 0 | Y10: =SUMIFS(Gastos!$J$9:$J$4091, Gastos!$L$9:$L$4091, $Y$3, Gastos!$M$9:$M$4091, $Y$4, Gastos!$D$9:$D$4091, Q10) -> 0 | Z10: =SUMIFS(Gastos!$J$9:$J$4091, Gastos!$L$9:$L$4091, $Z$3, Gastos!$M$9:$M$4091, $Z$4, Gastos!$D$9:$D$4091, Q10) -> 0 | AA10: =SUMIFS(Gastos!$J$9:$J$4091, Gastos!$L$9:$L$4091, $AA$3, Gastos!$M$9:$M$4091, $AA$4, Gastos!$D$9:$D$4091, Q10) -> 0 | AB10: =SUMIFS(Gastos!$J$9:$J$4091, Gastos!$L$9:$L$4091, $AB$3, Gastos!$M$9:$M$4091, $AB$4, Gastos!$D$9:$D$4091, Q10) -> 0 | AC10: =SUMIFS(Gastos!$J$9:$J$4091, Gastos!$L$9:$L$4091, $AC$3, Gastos!$M$9:$M$4091, $AC$4, Gastos!$D$9:$D$4091, Q10) -> 0 | AD10: =SUM(R10:AC10) -> 0 | AF10: =#REF! -> #REF! | AG10: =#REF! -> #REF! | AH10: =#REF! -> #REF! | AI10: =#REF! -> #REF!
B11: =#REF! -> #REF! | C11: =SUMIFS(Ingresos!$J$9:$J$3900, Ingresos!$L$9:$L$3900, $C$3, Ingresos!$M$9:$M$3900, $C$4, Ingresos!$D$9:$D$3900, B11) -> 0 | D11: =SUMIFS(Ingresos!$J$9:$J$3900, Ingresos!$L$9:$L$3900, $D$3, Ingresos!$M$9:$M$3900, $D$4, Ingresos!$D$9:$D$3900, B11) -> 0 | E11: =SUMIFS(Ingresos!$J$9:$J$3900, Ingresos!$L$9:$L$3900, $E$3, Ingresos!$M$9:$M$3900, $E$4, Ingresos!$D$9:$D$3900, B11) -> 0 | F11: =SUMIFS(Ingresos!$J$9:$J$3900, Ingresos!$L$9:$L$3900, $F$3, Ingresos!$M$9:$M$3900, $F$4, Ingresos!$D$9:$D$3900, B11) -> 0 | G11: =SUMIFS(Ingresos!$J$9:$J$3900, Ingresos!$L$9:$L$3900, $G$3, Ingresos!$M$9:$M$3900, $G$4, Ingresos!$D$9:$D$3900, B11) -> 0 | H11: =SUMIFS(Ingresos!$J$9:$J$3900, Ingresos!$L$9:$L$3900, $H$3, Ingresos!$M$9:$M$3900, $H$4, Ingresos!$D$9:$D$3900, B11) -> 0 | I11: =SUMIFS(Ingresos!$J$9:$J$3900, Ingresos!$L$9:$L$3900, $I$3, Ingresos!$M$9:$M$3900, $I$4, Ingresos!$D$9:$D$3900, B11) -> 0 | J11: =SUMIFS(Ingresos!$J$9:$J$3900, Ingresos!$L$9:$L$3900, $J$3, Ingresos!$M$9:$M$3900, $J$4, Ingresos!$D$9:$D$3900, B11) -> 0 | K11: =SUMIFS(Ingresos!$J$9:$J$3900, Ingresos!$L$9:$L$3900, $K$3, Ingresos!$M$9:$M$3900, $K$4, Ingresos!$D$9:$D$3900, B11) -> 0 | L11: =SUMIFS(Ingresos!$J$9:$J$3900, Ingresos!$L$9:$L$3900, $L$3, Ingresos!$M$9:$M$3900, $L$4, Ingresos!$D$9:$D$3900, B11) -> 0 | M11: =SUMIFS(Ingresos!$J$9:$J$3900, Ingresos!$L$9:$L$3900, $M$3, Ingresos!$M$9:$M$3900, $M$4, Ingresos!$D$9:$D$3900, B11) -> 0 | N11: =SUMIFS(Ingresos!$J$9:$J$3900, Ingresos!$L$9:$L$3900, $N$3, Ingresos!$M$9:$M$3900, $N$4, Ingresos!$D$9:$D$3900, B11) -> 0 | O11: =SUM(C11:N11) -> 0 | Q11: =#REF! -> #REF! | R11: =SUMIFS(Gastos!$J$9:$J$4091, Gastos!$L$9:$L$4091, $R$3, Gastos!$M$9:$M$4091, $R$4, Gastos!$D$9:$D$4091, Q11) -> 0 | S11: =SUMIFS(Gastos!$J$9:$J$4091, Gastos!$L$9:$L$4091, $S$3, Gastos!$M$9:$M$4091, $S$4, Gastos!$D$9:$D$4091, Q11) -> 0 | T11: =SUMIFS(Gastos!$J$9:$J$4091, Gastos!$L$9:$L$4091, $T$3, Gastos!$M$9:$M$4091, $T$4, Gastos!$D$9:$D$4091, Q11) -> 0 | U11: =SUMIFS(Gastos!$J$9:$J$4091, Gastos!$L$9:$L$4091, $U$3, Gastos!$M$9:$M$4091, $U$4, Gastos!$D$9:$D$4091, Q11) -> 0 | V11: =SUMIFS(Gastos!$J$9:$J$4091, Gastos!$L$9:$L$4091, $V$3, Gastos!$M$9:$M$4091, $V$4, Gastos!$D$9:$D$4091, Q11) -> 0 | W11: =SUMIFS(Gastos!$J$9:$J$4091, Gastos!$L$9:$L$4091, $W$3, Gastos!$M$9:$M$4091, $W$4, Gastos!$D$9:$D$4091, Q11) -> 0 | X11: =SUMIFS(Gastos!$J$9:$J$4091, Gastos!$L$9:$L$4091, $X$3, Gastos!$M$9:$M$4091, $X$4, Gastos!$D$9:$D$4091, Q11) -> 0 | Y11: =SUMIFS(Gastos!$J$9:$J$4091, Gastos!$L$9:$L$4091, $Y$3, Gastos!$M$9:$M$4091, $Y$4, Gastos!$D$9:$D$4091, Q11) -> 0 | Z11: =SUMIFS(Gastos!$J$9:$J$4091, Gastos!$L$9:$L$4091, $Z$3, Gastos!$M$9:$M$4091, $Z$4, Gastos!$D$9:$D$4091, Q11) -> 0 | AA11: =SUMIFS(Gastos!$J$9:$J$4091, Gastos!$L$9:$L$4091, $AA$3, Gastos!$M$9:$M$4091, $AA$4, Gastos!$D$9:$D$4091, Q11) -> 0 | AB11: =SUMIFS(Gastos!$J$9:$J$4091, Gastos!$L$9:$L$4091, $AB$3, Gastos!$M$9:$M$4091, $AB$4, Gastos!$D$9:$D$4091, Q11) -> 0 | AC11: =SUMIFS(Gastos!$J$9:$J$4091, Gastos!$L$9:$L$4091, $AC$3, Gastos!$M$9:$M$4091, $AC$4, Gastos!$D$9:$D$4091, Q11) -> 0 | AD11: =SUM(R11:AC11) -> 0 | AF11: =#REF! -> #REF! | AG11: =#REF! -> #REF! | AH11: =#REF! -> #REF! | AI11: =#REF! -> #REF! | AK11: Saldo Acumulado | AM11: =AM9 -> #REF! | AN11: =AM11+AN9 -> #REF! | AO11: =AN11+AO9 -> #REF! | AP11: =AO11+AP9 -> #REF! | AQ11: =AP11+AQ9 -> #REF! | AR11: =AQ11+AR9 -> #REF! | AS11: =AR11+AS9 -> #REF! | AT11: =AS11+AT9 -> #REF! | AU11: =AT11+AU9 -> #REF! | ... AX11: =AW11+AX9 -> #REF!
B12: =#REF! -> #REF! | C12: =SUMIFS(Ingresos!$J$9:$J$3900, Ingresos!$L$9:$L$3900, $C$3, Ingresos!$M$9:$M$3900, $C$4, Ingresos!$D$9:$D$3900, B12) -> 0 | D12: =SUMIFS(Ingresos!$J$9:$J$3900, Ingresos!$L$9:$L$3900, $D$3, Ingresos!$M$9:$M$3900, $D$4, Ingresos!$D$9:$D$3900, B12) -> 0 | E12: =SUMIFS(Ingresos!$J$9:$J$3900, Ingresos!$L$9:$L$3900, $E$3, Ingresos!$M$9:$M$3900, $E$4, Ingresos!$D$9:$D$3900, B12) -> 0 | F12: =SUMIFS(Ingresos!$J$9:$J$3900, Ingresos!$L$9:$L$3900, $F$3, Ingresos!$M$9:$M$3900, $F$4, Ingresos!$D$9:$D$3900, B12) -> 0 | G12: =SUMIFS(Ingresos!$J$9:$J$3900, Ingresos!$L$9:$L$3900, $G$3, Ingresos!$M$9:$M$3900, $G$4, Ingresos!$D$9:$D$3900, B12) -> 0 | H12: =SUMIFS(Ingresos!$J$9:$J$3900, Ingresos!$L$9:$L$3900, $H$3, Ingresos!$M$9:$M$3900, $H$4, Ingresos!$D$9:$D$3900, B12) -> 0 | I12: =SUMIFS(Ingresos!$J$9:$J$3900, Ingresos!$L$9:$L$3900, $I$3, Ingresos!$M$9:$M$3900, $I$4, Ingresos!$D$9:$D$3900, B12) -> 0 | J12: =SUMIFS(Ingresos!$J$9:$J$3900, Ingresos!$L$9:$L$3900, $J$3, Ingresos!$M$9:$M$3900, $J$4, Ingresos!$D$9:$D$3900, B12) -> 0 | K12: =SUMIFS(Ingresos!$J$9:$J$3900, Ingresos!$L$9:$L$3900, $K$3, Ingresos!$M$9:$M$3900, $K$4, Ingresos!$D$9:$D$3900, B12) -> 0 | L12: =SUMIFS(Ingresos!$J$9:$J$3900, Ingresos!$L$9:$L$3900, $L$3, Ingresos!$M$9:$M$3900, $L$4, Ingresos!$D$9:$D$3900, B12) -> 0 | M12: =SUMIFS(Ingresos!$J$9:$J$3900, Ingresos!$L$9:$L$3900, $M$3, Ingresos!$M$9:$M$3900, $M$4, Ingresos!$D$9:$D$3900, B12) -> 0 | N12: =SUMIFS(Ingresos!$J$9:$J$3900, Ingresos!$L$9:$L$3900, $N$3, Ingresos!$M$9:$M$3900, $N$4, Ingresos!$D$9:$D$3900, B12) -> 0 | O12: =SUM(C12:N12) -> 0 | Q12: =#REF! -> #REF! | R12: =SUMIFS(Gastos!$J$9:$J$4091, Gastos!$L$9:$L$4091, $R$3, Gastos!$M$9:$M$4091, $R$4, Gastos!$D$9:$D$4091, Q12) -> 0 | S12: =SUMIFS(Gastos!$J$9:$J$4091, Gastos!$L$9:$L$4091, $S$3, Gastos!$M$9:$M$4091, $S$4, Gastos!$D$9:$D$4091, Q12) -> 0 | T12: =SUMIFS(Gastos!$J$9:$J$4091, Gastos!$L$9:$L$4091, $T$3, Gastos!$M$9:$M$4091, $T$4, Gastos!$D$9:$D$4091, Q12) -> 0 | U12: =SUMIFS(Gastos!$J$9:$J$4091, Gastos!$L$9:$L$4091, $U$3, Gastos!$M$9:$M$4091, $U$4, Gastos!$D$9:$D$4091, Q12) -> 0 | V12: =SUMIFS(Gastos!$J$9:$J$4091, Gastos!$L$9:$L$4091, $V$3, Gastos!$M$9:$M$4091, $V$4, Gastos!$D$9:$D$4091, Q12) -> 0 | W12: =SUMIFS(Gastos!$J$9:$J$4091, Gastos!$L$9:$L$4091, $W$3, Gastos!$M$9:$M$4091, $W$4, Gastos!$D$9:$D$4091, Q12) -> 0 | X12: =SUMIFS(Gastos!$J$9:$J$4091, Gastos!$L$9:$L$4091, $X$3, Gastos!$M$9:$M$4091, $X$4, Gastos!$D$9:$D$4091, Q12) -> 0 | Y12: =SUMIFS(Gastos!$J$9:$J$4091, Gastos!$L$9:$L$4091, $Y$3, Gastos!$M$9:$M$4091, $Y$4, Gastos!$D$9:$D$4091, Q12) -> 0 | Z12: =SUMIFS(Gastos!$J$9:$J$4091, Gastos!$L$9:$L$4091, $Z$3, Gastos!$M$9:$M$4091, $Z$4, Gastos!$D$9:$D$4091, Q12) -> 0 | AA12: =SUMIFS(Gastos!$J$9:$J$4091, Gastos!$L$9:$L$4091, $AA$3, Gastos!$M$9:$M$4091, $AA$4, Gastos!$D$9:$D$4091, Q12) -> 0 | AB12: =SUMIFS(Gastos!$J$9:$J$4091, Gastos!$L$9:$L$4091, $AB$3, Gastos!$M$9:$M$4091, $AB$4, Gastos!$D$9:$D$4091, Q12) -> 0 | AC12: =SUMIFS(Gastos!$J$9:$J$4091, Gastos!$L$9:$L$4091, $AC$3, Gastos!$M$9:$M$4091, $AC$4, Gastos!$D$9:$D$4091, Q12) -> 0 | AD12: =SUM(R12:AC12) -> 0 | AF12: =#REF! -> #REF! | AG12: =#REF! -> #REF! | AH12: =#REF! -> #REF! | AI12: =#REF! -> #REF!
B13: =#REF! -> #REF! | C13: =SUMIFS(Ingresos!$J$9:$J$3900, Ingresos!$L$9:$L$3900, $C$3, Ingresos!$M$9:$M$3900, $C$4, Ingresos!$D$9:$D$3900, B13) -> 0 | D13: =SUMIFS(Ingresos!$J$9:$J$3900, Ingresos!$L$9:$L$3900, $D$3, Ingresos!$M$9:$M$3900, $D$4, Ingresos!$D$9:$D$3900, B13) -> 0 | E13: =SUMIFS(Ingresos!$J$9:$J$3900, Ingresos!$L$9:$L$3900, $E$3, Ingresos!$M$9:$M$3900, $E$4, Ingresos!$D$9:$D$3900, B13) -> 0 | F13: =SUMIFS(Ingresos!$J$9:$J$3900, Ingresos!$L$9:$L$3900, $F$3, Ingresos!$M$9:$M$3900, $F$4, Ingresos!$D$9:$D$3900, B13) -> 0 | G13: =SUMIFS(Ingresos!$J$9:$J$3900, Ingresos!$L$9:$L$3900, $G$3, Ingresos!$M$9:$M$3900, $G$4, Ingresos!$D$9:$D$3900, B13) -> 0 | H13: =SUMIFS(Ingresos!$J$9:$J$3900, Ingresos!$L$9:$L$3900, $H$3, Ingresos!$M$9:$M$3900, $H$4, Ingresos!$D$9:$D$3900, B13) -> 0 | I13: =SUMIFS(Ingresos!$J$9:$J$3900, Ingresos!$L$9:$L$3900, $I$3, Ingresos!$M$9:$M$3900, $I$4, Ingresos!$D$9:$D$3900, B13) -> 0 | J13: =SUMIFS(Ingresos!$J$9:$J$3900, Ingresos!$L$9:$L$3900, $J$3, Ingresos!$M$9:$M$3900, $J$4, Ingresos!$D$9:$D$3900, B13) -> 0 | K13: =SUMIFS(Ingresos!$J$9:$J$3900, Ingresos!$L$9:$L$3900, $K$3, Ingresos!$M$9:$M$3900, $K$4, Ingresos!$D$9:$D$3900, B13) -> 0 | L13: =SUMIFS(Ingresos!$J$9:$J$3900, Ingresos!$L$9:$L$3900, $L$3, Ingresos!$M$9:$M$3900, $L$4, Ingresos!$D$9:$D$3900, B13) -> 0 | M13: =SUMIFS(Ingresos!$J$9:$J$3900, Ingresos!$L$9:$L$3900, $M$3, Ingresos!$M$9:$M$3900, $M$4, Ingresos!$D$9:$D$3900, B13) -> 0 | N13: =SUMIFS(Ingresos!$J$9:$J$3900, Ingresos!$L$9:$L$3900, $N$3, Ingresos!$M$9:$M$3900, $N$4, Ingresos!$D$9:$D$3900, B13) -> 0 | O13: =SUM(C13:N13) -> 0 | Q13: =#REF! -> #REF! | R13: =SUMIFS(Gastos!$J$9:$J$4091, Gastos!$L$9:$L$4091, $R$3, Gastos!$M$9:$M$4091, $R$4, Gastos!$D$9:$D$4091, Q13) -> 0 | S13: =SUMIFS(Gastos!$J$9:$J$4091, Gastos!$L$9:$L$4091, $S$3, Gastos!$M$9:$M$4091, $S$4, Gastos!$D$9:$D$4091, Q13) -> 0 | T13: =SUMIFS(Gastos!$J$9:$J$4091, Gastos!$L$9:$L$4091, $T$3, Gastos!$M$9:$M$4091, $T$4, Gastos!$D$9:$D$4091, Q13) -> 0 | U13: =SUMIFS(Gastos!$J$9:$J$4091, Gastos!$L$9:$L$4091, $U$3, Gastos!$M$9:$M$4091, $U$4, Gastos!$D$9:$D$4091, Q13) -> 0 | V13: =SUMIFS(Gastos!$J$9:$J$4091, Gastos!$L$9:$L$4091, $V$3, Gastos!$M$9:$M$4091, $V$4, Gastos!$D$9:$D$4091, Q13) -> 0 | W13: =SUMIFS(Gastos!$J$9:$J$4091, Gastos!$L$9:$L$4091, $W$3, Gastos!$M$9:$M$4091, $W$4, Gastos!$D$9:$D$4091, Q13) -> 0 | X13: =SUMIFS(Gastos!$J$9:$J$4091, Gastos!$L$9:$L$4091, $X$3, Gastos!$M$9:$M$4091, $X$4, Gastos!$D$9:$D$4091, Q13) -> 0 | Y13: =SUMIFS(Gastos!$J$9:$J$4091, Gastos!$L$9:$L$4091, $Y$3, Gastos!$M$9:$M$4091, $Y$4, Gastos!$D$9:$D$4091, Q13) -> 0 | Z13: =SUMIFS(Gastos!$J$9:$J$4091, Gastos!$L$9:$L$4091, $Z$3, Gastos!$M$9:$M$4091, $Z$4, Gastos!$D$9:$D$4091, Q13) -> 0 | AA13: =SUMIFS(Gastos!$J$9:$J$4091, Gastos!$L$9:$L$4091, $AA$3, Gastos!$M$9:$M$4091, $AA$4, Gastos!$D$9:$D$4091, Q13) -> 0 | AB13: =SUMIFS(Gastos!$J$9:$J$4091, Gastos!$L$9:$L$4091, $AB$3, Gastos!$M$9:$M$4091, $AB$4, Gastos!$D$9:$D$4091, Q13) -> 0 | AC13: =SUMIFS(Gastos!$J$9:$J$4091, Gastos!$L$9:$L$4091, $AC$3, Gastos!$M$9:$M$4091, $AC$4, Gastos!$D$9:$D$4091, Q13) -> 0 | AD13: =SUM(R13:AC13) -> 0 | AF13: =#REF! -> #REF! | AG13: =#REF! -> #REF! | AH13: =#REF! -> #REF! | AI13: =#REF! -> #REF!
B14: =#REF! -> #REF! | C14: =SUMIFS(Ingresos!$J$9:$J$3900, Ingresos!$L$9:$L$3900, $C$3, Ingresos!$M$9:$M$3900, $C$4, Ingresos!$D$9:$D$3900, B14) -> 0 | D14: =SUMIFS(Ingresos!$J$9:$J$3900, Ingresos!$L$9:$L$3900, $D$3, Ingresos!$M$9:$M$3900, $D$4, Ingresos!$D$9:$D$3900, B14) -> 0 | E14: =SUMIFS(Ingresos!$J$9:$J$3900, Ingresos!$L$9:$L$3900, $E$3, Ingresos!$M$9:$M$3900, $E$4, Ingresos!$D$9:$D$3900, B14) -> 0 | F14: =SUMIFS(Ingresos!$J$9:$J$3900, Ingresos!$L$9:$L$3900, $F$3, Ingresos!$M$9:$M$3900, $F$4, Ingresos!$D$9:$D$3900, B14) -> 0 | G14: =SUMIFS(Ingresos!$J$9:$J$3900, Ingresos!$L$9:$L$3900, $G$3, Ingresos!$M$9:$M$3900, $G$4, Ingresos!$D$9:$D$3900, B14) -> 0 | H14: =SUMIFS(Ingresos!$J$9:$J$3900, Ingresos!$L$9:$L$3900, $H$3, Ingresos!$M$9:$M$3900, $H$4, Ingresos!$D$9:$D$3900, B14) -> 0 | I14: =SUMIFS(Ingresos!$J$9:$J$3900, Ingresos!$L$9:$L$3900, $I$3, Ingresos!$M$9:$M$3900, $I$4, Ingresos!$D$9:$D$3900, B14) -> 0 | J14: =SUMIFS(Ingresos!$J$9:$J$3900, Ingresos!$L$9:$L$3900, $J$3, Ingresos!$M$9:$M$3900, $J$4, Ingresos!$D$9:$D$3900, B14) -> 0 | K14: =SUMIFS(Ingresos!$J$9:$J$3900, Ingresos!$L$9:$L$3900, $K$3, Ingresos!$M$9:$M$3900, $K$4, Ingresos!$D$9:$D$3900, B14) -> 0 | L14: =SUMIFS(Ingresos!$J$9:$J$3900, Ingresos!$L$9:$L$3900, $L$3, Ingresos!$M$9:$M$3900, $L$4, Ingresos!$D$9:$D$3900, B14) -> 0 | M14: =SUMIFS(Ingresos!$J$9:$J$3900, Ingresos!$L$9:$L$3900, $M$3, Ingresos!$M$9:$M$3900, $M$4, Ingresos!$D$9:$D$3900, B14) -> 0 | N14: =SUMIFS(Ingresos!$J$9:$J$3900, Ingresos!$L$9:$L$3900, $N$3, Ingresos!$M$9:$M$3900, $N$4, Ingresos!$D$9:$D$3900, B14) -> 0 | O14: =SUM(C14:N14) -> 0 | Q14: =#REF! -> #REF! | R14: =SUMIFS(Gastos!$J$9:$J$4091, Gastos!$L$9:$L$4091, $R$3, Gastos!$M$9:$M$4091, $R$4, Gastos!$D$9:$D$4091, Q14) -> 0 | S14: =SUMIFS(Gastos!$J$9:$J$4091, Gastos!$L$9:$L$4091, $S$3, Gastos!$M$9:$M$4091, $S$4, Gastos!$D$9:$D$4091, Q14) -> 0 | T14: =SUMIFS(Gastos!$J$9:$J$4091, Gastos!$L$9:$L$4091, $T$3, Gastos!$M$9:$M$4091, $T$4, Gastos!$D$9:$D$4091, Q14) -> 0 | U14: =SUMIFS(Gastos!$J$9:$J$4091, Gastos!$L$9:$L$4091, $U$3, Gastos!$M$9:$M$4091, $U$4, Gastos!$D$9:$D$4091, Q14) -> 0 | V14: =SUMIFS(Gastos!$J$9:$J$4091, Gastos!$L$9:$L$4091, $V$3, Gastos!$M$9:$M$4091, $V$4, Gastos!$D$9:$D$4091, Q14) -> 0 | W14: =SUMIFS(Gastos!$J$9:$J$4091, Gastos!$L$9:$L$4091, $W$3, Gastos!$M$9:$M$4091, $W$4, Gastos!$D$9:$D$4091, Q14) -> 0 | X14: =SUMIFS(Gastos!$J$9:$J$4091, Gastos!$L$9:$L$4091, $X$3, Gastos!$M$9:$M$4091, $X$4, Gastos!$D$9:$D$4091, Q14) -> 0 | Y14: =SUMIFS(Gastos!$J$9:$J$4091, Gastos!$L$9:$L$4091, $Y$3, Gastos!$M$9:$M$4091, $Y$4, Gastos!$D$9:$D$4091, Q14) -> 0 | Z14: =SUMIFS(Gastos!$J$9:$J$4091, Gastos!$L$9:$L$4091, $Z$3, Gastos!$M$9:$M$4091, $Z$4, Gastos!$D$9:$D$4091, Q14) -> 0 | AA14: =SUMIFS(Gastos!$J$9:$J$4091, Gastos!$L$9:$L$4091, $AA$3, Gastos!$M$9:$M$4091, $AA$4, Gastos!$D$9:$D$4091, Q14) -> 0 | AB14: =SUMIFS(Gastos!$J$9:$J$4091, Gastos!$L$9:$L$4091, $AB$3, Gastos!$M$9:$M$4091, $AB$4, Gastos!$D$9:$D$4091, Q14) -> 0 | AC14: =SUMIFS(Gastos!$J$9:$J$4091, Gastos!$L$9:$L$4091, $AC$3, Gastos!$M$9:$M$4091, $AC$4, Gastos!$D$9:$D$4091, Q14) -> 0 | AD14: =SUM(R14:AC14) -> 0 | AF14: =#REF! -> #REF! | AG14: =#REF! -> #REF! | AH14: =#REF! -> #REF! | AI14: =#REF! -> #REF! | AK14: INGRESOS | AL14: Presupuesto | AM14: Actual | AN14: Variación | AO14: Pre. Acumulativo | AP14: Ingreso Acumulativo
B15: =#REF! -> #REF! | C15: =SUMIFS(Ingresos!$J$9:$J$3900, Ingresos!$L$9:$L$3900, $C$3, Ingresos!$M$9:$M$3900, $C$4, Ingresos!$D$9:$D$3900, B15) -> 0 | D15: =SUMIFS(Ingresos!$J$9:$J$3900, Ingresos!$L$9:$L$3900, $D$3, Ingresos!$M$9:$M$3900, $D$4, Ingresos!$D$9:$D$3900, B15) -> 0 | E15: =SUMIFS(Ingresos!$J$9:$J$3900, Ingresos!$L$9:$L$3900, $E$3, Ingresos!$M$9:$M$3900, $E$4, Ingresos!$D$9:$D$3900, B15) -> 0 | F15: =SUMIFS(Ingresos!$J$9:$J$3900, Ingresos!$L$9:$L$3900, $F$3, Ingresos!$M$9:$M$3900, $F$4, Ingresos!$D$9:$D$3900, B15) -> 0 | G15: =SUMIFS(Ingresos!$J$9:$J$3900, Ingresos!$L$9:$L$3900, $G$3, Ingresos!$M$9:$M$3900, $G$4, Ingresos!$D$9:$D$3900, B15) -> 0 | H15: =SUMIFS(Ingresos!$J$9:$J$3900, Ingresos!$L$9:$L$3900, $H$3, Ingresos!$M$9:$M$3900, $H$4, Ingresos!$D$9:$D$3900, B15) -> 0 | I15: =SUMIFS(Ingresos!$J$9:$J$3900, Ingresos!$L$9:$L$3900, $I$3, Ingresos!$M$9:$M$3900, $I$4, Ingresos!$D$9:$D$3900, B15) -> 0 | J15: =SUMIFS(Ingresos!$J$9:$J$3900, Ingresos!$L$9:$L$3900, $J$3, Ingresos!$M$9:$M$3900, $J$4, Ingresos!$D$9:$D$3900, B15) -> 0 | K15: =SUMIFS(Ingresos!$J$9:$J$3900, Ingresos!$L$9:$L$3900, $K$3, Ingresos!$M$9:$M$3900, $K$4, Ingresos!$D$9:$D$3900, B15) -> 0 | L15: =SUMIFS(Ingresos!$J$9:$J$3900, Ingresos!$L$9:$L$3900, $L$3, Ingresos!$M$9:$M$3900, $L$4, Ingresos!$D$9:$D$3900, B15) -> 0 | M15: =SUMIFS(Ingresos!$J$9:$J$3900, Ingresos!$L$9:$L$3900, $M$3, Ingresos!$M$9:$M$3900, $M$4, Ingresos!$D$9:$D$3900, B15) -> 0 | N15: =SUMIFS(Ingresos!$J$9:$J$3900, Ingresos!$L$9:$L$3900, $N$3, Ingresos!$M$9:$M$3900, $N$4, Ingresos!$D$9:$D$3900, B15) -> 0 | O15: =SUM(C15:N15) -> 0 | Q15: =#REF! -> #REF! | R15: =SUMIFS(Gastos!$J$9:$J$4091, Gastos!$L$9:$L$4091, $R$3, Gastos!$M$9:$M$4091, $R$4, Gastos!$D$9:$D$4091, Q15) -> 0 | S15: =SUMIFS(Gastos!$J$9:$J$4091, Gastos!$L$9:$L$4091, $S$3, Gastos!$M$9:$M$4091, $S$4, Gastos!$D$9:$D$4091, Q15) -> 0 | T15: =SUMIFS(Gastos!$J$9:$J$4091, Gastos!$L$9:$L$4091, $T$3, Gastos!$M$9:$M$4091, $T$4, Gastos!$D$9:$D$4091, Q15) -> 0 | U15: =SUMIFS(Gastos!$J$9:$J$4091, Gastos!$L$9:$L$4091, $U$3, Gastos!$M$9:$M$4091, $U$4, Gastos!$D$9:$D$4091, Q15) -> 0 | V15: =SUMIFS(Gastos!$J$9:$J$4091, Gastos!$L$9:$L$4091, $V$3, Gastos!$M$9:$M$4091, $V$4, Gastos!$D$9:$D$4091, Q15) -> 0 | W15: =SUMIFS(Gastos!$J$9:$J$4091, Gastos!$L$9:$L$4091, $W$3, Gastos!$M$9:$M$4091, $W$4, Gastos!$D$9:$D$4091, Q15) -> 0 | X15: =SUMIFS(Gastos!$J$9:$J$4091, Gastos!$L$9:$L$4091, $X$3, Gastos!$M$9:$M$4091, $X$4, Gastos!$D$9:$D$4091, Q15) -> 0 | Y15: =SUMIFS(Gastos!$J$9:$J$4091, Gastos!$L$9:$L$4091, $Y$3, Gastos!$M$9:$M$4091, $Y$4, Gastos!$D$9:$D$4091, Q15) -> 0 | Z15: =SUMIFS(Gastos!$J$9:$J$4091, Gastos!$L$9:$L$4091, $Z$3, Gastos!$M$9:$M$4091, $Z$4, Gastos!$D$9:$D$4091, Q15) -> 0 | AA15: =SUMIFS(Gastos!$J$9:$J$4091, Gastos!$L$9:$L$4091, $AA$3, Gastos!$M$9:$M$4091, $AA$4, Gastos!$D$9:$D$4091, Q15) -> 0 | AB15: =SUMIFS(Gastos!$J$9:$J$4091, Gastos!$L$9:$L$4091, $AB$3, Gastos!$M$9:$M$4091, $AB$4, Gastos!$D$9:$D$4091, Q15) -> 0 | AC15: =SUMIFS(Gastos!$J$9:$J$4091, Gastos!$L$9:$L$4091, $AC$3, Gastos!$M$9:$M$4091, $AC$4, Gastos!$D$9:$D$4091, Q15) -> 0 | AD15: =SUM(R15:AC15) -> 0 | AF15: =#REF! -> #REF! | AG15: =#REF! -> #REF! | AH15: =#REF! -> #REF! | AI15: =#REF! -> #REF! | AK15: =#REF! -> #REF! | AL15: =#REF! -> #REF! | AM15: =#REF! -> #REF! | AN15: =AL15-AM15 -> #REF! | AO15: =AL15 -> #REF! | AP15: =AM15 -> #REF!
B16: =#REF! -> #REF! | C16: =SUMIFS(Ingresos!$J$9:$J$3900, Ingresos!$L$9:$L$3900, $C$3, Ingresos!$M$9:$M$3900, $C$4, Ingresos!$D$9:$D$3900, B16) -> 0 | D16: =SUMIFS(Ingresos!$J$9:$J$3900, Ingresos!$L$9:$L$3900, $D$3, Ingresos!$M$9:$M$3900, $D$4, Ingresos!$D$9:$D$3900, B16) -> 0 | E16: =SUMIFS(Ingresos!$J$9:$J$3900, Ingresos!$L$9:$L$3900, $E$3, Ingresos!$M$9:$M$3900, $E$4, Ingresos!$D$9:$D$3900, B16) -> 0 | F16: =SUMIFS(Ingresos!$J$9:$J$3900, Ingresos!$L$9:$L$3900, $F$3, Ingresos!$M$9:$M$3900, $F$4, Ingresos!$D$9:$D$3900, B16) -> 0 | G16: =SUMIFS(Ingresos!$J$9:$J$3900, Ingresos!$L$9:$L$3900, $G$3, Ingresos!$M$9:$M$3900, $G$4, Ingresos!$D$9:$D$3900, B16) -> 0 | H16: =SUMIFS(Ingresos!$J$9:$J$3900, Ingresos!$L$9:$L$3900, $H$3, Ingresos!$M$9:$M$3900, $H$4, Ingresos!$D$9:$D$3900, B16) -> 0 | I16: =SUMIFS(Ingresos!$J$9:$J$3900, Ingresos!$L$9:$L$3900, $I$3, Ingresos!$M$9:$M$3900, $I$4, Ingresos!$D$9:$D$3900, B16) -> 0 | J16: =SUMIFS(Ingresos!$J$9:$J$3900, Ingresos!$L$9:$L$3900, $J$3, Ingresos!$M$9:$M$3900, $J$4, Ingresos!$D$9:$D$3900, B16) -> 0 | K16: =SUMIFS(Ingresos!$J$9:$J$3900, Ingresos!$L$9:$L$3900, $K$3, Ingresos!$M$9:$M$3900, $K$4, Ingresos!$D$9:$D$3900, B16) -> 0 | L16: =SUMIFS(Ingresos!$J$9:$J$3900, Ingresos!$L$9:$L$3900, $L$3, Ingresos!$M$9:$M$3900, $L$4, Ingresos!$D$9:$D$3900, B16) -> 0 | M16: =SUMIFS(Ingresos!$J$9:$J$3900, Ingresos!$L$9:$L$3900, $M$3, Ingresos!$M$9:$M$3900, $M$4, Ingresos!$D$9:$D$3900, B16) -> 0 | N16: =SUMIFS(Ingresos!$J$9:$J$3900, Ingresos!$L$9:$L$3900, $N$3, Ingresos!$M$9:$M$3900, $N$4, Ingresos!$D$9:$D$3900, B16) -> 0 | O16: =SUM(C16:N16) -> 0 | Q16: =#REF! -> #REF! | R16: =SUMIFS(Gastos!$J$9:$J$4091, Gastos!$L$9:$L$4091, $R$3, Gastos!$M$9:$M$4091, $R$4, Gastos!$D$9:$D$4091, Q16) -> 0 | S16: =SUMIFS(Gastos!$J$9:$J$4091, Gastos!$L$9:$L$4091, $S$3, Gastos!$M$9:$M$4091, $S$4, Gastos!$D$9:$D$4091, Q16) -> 0 | T16: =SUMIFS(Gastos!$J$9:$J$4091, Gastos!$L$9:$L$4091, $T$3, Gastos!$M$9:$M$4091, $T$4, Gastos!$D$9:$D$4091, Q16) -> 0 | U16: =SUMIFS(Gastos!$J$9:$J$4091, Gastos!$L$9:$L$4091, $U$3, Gastos!$M$9:$M$4091, $U$4, Gastos!$D$9:$D$4091, Q16) -> 0 | V16: =SUMIFS(Gastos!$J$9:$J$4091, Gastos!$L$9:$L$4091, $V$3, Gastos!$M$9:$M$4091, $V$4, Gastos!$D$9:$D$4091, Q16) -> 0 | W16: =SUMIFS(Gastos!$J$9:$J$4091, Gastos!$L$9:$L$4091, $W$3, Gastos!$M$9:$M$4091, $W$4, Gastos!$D$9:$D$4091, Q16) -> 0 | X16: =SUMIFS(Gastos!$J$9:$J$4091, Gastos!$L$9:$L$4091, $X$3, Gastos!$M$9:$M$4091, $X$4, Gastos!$D$9:$D$4091, Q16) -> 0 | Y16: =SUMIFS(Gastos!$J$9:$J$4091, Gastos!$L$9:$L$4091, $Y$3, Gastos!$M$9:$M$4091, $Y$4, Gastos!$D$9:$D$4091, Q16) -> 0 | Z16: =SUMIFS(Gastos!$J$9:$J$4091, Gastos!$L$9:$L$4091, $Z$3, Gastos!$M$9:$M$4091, $Z$4, Gastos!$D$9:$D$4091, Q16) -> 0 | AA16: =SUMIFS(Gastos!$J$9:$J$4091, Gastos!$L$9:$L$4091, $AA$3, Gastos!$M$9:$M$4091, $AA$4, Gastos!$D$9:$D$4091, Q16) -> 0 | AB16: =SUMIFS(Gastos!$J$9:$J$4091, Gastos!$L$9:$L$4091, $AB$3, Gastos!$M$9:$M$4091, $AB$4, Gastos!$D$9:$D$4091, Q16) -> 0 | AC16: =SUMIFS(Gastos!$J$9:$J$4091, Gastos!$L$9:$L$4091, $AC$3, Gastos!$M$9:$M$4091, $AC$4, Gastos!$D$9:$D$4091, Q16) -> 0 | AD16: =SUM(R16:AC16) -> 0 | AK16: =#REF! -> #REF! | AL16: =#REF! -> #REF! | AM16: =#REF! -> #REF! | AN16: =AL16-AM16 -> #REF! | AO16: =AO15+AL16 -> #REF! | AP16: =AP15+AM16 -> #REF!
B17: =#REF! -> #REF! | C17: =SUMIFS(Ingresos!$J$9:$J$3900, Ingresos!$L$9:$L$3900, $C$3, Ingresos!$M$9:$M$3900, $C$4, Ingresos!$D$9:$D$3900, B17) -> 0 | D17: =SUMIFS(Ingresos!$J$9:$J$3900, Ingresos!$L$9:$L$3900, $D$3, Ingresos!$M$9:$M$3900, $D$4, Ingresos!$D$9:$D$3900, B17) -> 0 | E17: =SUMIFS(Ingresos!$J$9:$J$3900, Ingresos!$L$9:$L$3900, $E$3, Ingresos!$M$9:$M$3900, $E$4, Ingresos!$D$9:$D$3900, B17) -> 0 | F17: =SUMIFS(Ingresos!$J$9:$J$3900, Ingresos!$L$9:$L$3900, $F$3, Ingresos!$M$9:$M$3900, $F$4, Ingresos!$D$9:$D$3900, B17) -> 0 | G17: =SUMIFS(Ingresos!$J$9:$J$3900, Ingresos!$L$9:$L$3900, $G$3, Ingresos!$M$9:$M$3900, $G$4, Ingresos!$D$9:$D$3900, B17) -> 0 | H17: =SUMIFS(Ingresos!$J$9:$J$3900, Ingresos!$L$9:$L$3900, $H$3, Ingresos!$M$9:$M$3900, $H$4, Ingresos!$D$9:$D$3900, B17) -> 0 | I17: =SUMIFS(Ingresos!$J$9:$J$3900, Ingresos!$L$9:$L$3900, $I$3, Ingresos!$M$9:$M$3900, $I$4, Ingresos!$D$9:$D$3900, B17) -> 0 | J17: =SUMIFS(Ingresos!$J$9:$J$3900, Ingresos!$L$9:$L$3900, $J$3, Ingresos!$M$9:$M$3900, $J$4, Ingresos!$D$9:$D$3900, B17) -> 0 | K17: =SUMIFS(Ingresos!$J$9:$J$3900, Ingresos!$L$9:$L$3900, $K$3, Ingresos!$M$9:$M$3900, $K$4, Ingresos!$D$9:$D$3900, B17) -> 0 | L17: =SUMIFS(Ingresos!$J$9:$J$3900, Ingresos!$L$9:$L$3900, $L$3, Ingresos!$M$9:$M$3900, $L$4, Ingresos!$D$9:$D$3900, B17) -> 0 | M17: =SUMIFS(Ingresos!$J$9:$J$3900, Ingresos!$L$9:$L$3900, $M$3, Ingresos!$M$9:$M$3900, $M$4, Ingresos!$D$9:$D$3900, B17) -> 0 | N17: =SUMIFS(Ingresos!$J$9:$J$3900, Ingresos!$L$9:$L$3900, $N$3, Ingresos!$M$9:$M$3900, $N$4, Ingresos!$D$9:$D$3900, B17) -> 0 | O17: =SUM(C17:N17) -> 0 | Q17: =#REF! -> #REF! | R17: =SUMIFS(Gastos!$J$9:$J$4091, Gastos!$L$9:$L$4091, $R$3, Gastos!$M$9:$M$4091, $R$4, Gastos!$D$9:$D$4091, Q17) -> 0 | S17: =SUMIFS(Gastos!$J$9:$J$4091, Gastos!$L$9:$L$4091, $S$3, Gastos!$M$9:$M$4091, $S$4, Gastos!$D$9:$D$4091, Q17) -> 0 | T17: =SUMIFS(Gastos!$J$9:$J$4091, Gastos!$L$9:$L$4091, $T$3, Gastos!$M$9:$M$4091, $T$4, Gastos!$D$9:$D$4091, Q17) -> 0 | U17: =SUMIFS(Gastos!$J$9:$J$4091, Gastos!$L$9:$L$4091, $U$3, Gastos!$M$9:$M$4091, $U$4, Gastos!$D$9:$D$4091, Q17) -> 0 | V17: =SUMIFS(Gastos!$J$9:$J$4091, Gastos!$L$9:$L$4091, $V$3, Gastos!$M$9:$M$4091, $V$4, Gastos!$D$9:$D$4091, Q17) -> 0 | W17: =SUMIFS(Gastos!$J$9:$J$4091, Gastos!$L$9:$L$4091, $W$3, Gastos!$M$9:$M$4091, $W$4, Gastos!$D$9:$D$4091, Q17) -> 0 | X17: =SUMIFS(Gastos!$J$9:$J$4091, Gastos!$L$9:$L$4091, $X$3, Gastos!$M$9:$M$4091, $X$4, Gastos!$D$9:$D$4091, Q17) -> 0 | Y17: =SUMIFS(Gastos!$J$9:$J$4091, Gastos!$L$9:$L$4091, $Y$3, Gastos!$M$9:$M$4091, $Y$4, Gastos!$D$9:$D$4091, Q17) -> 0 | Z17: =SUMIFS(Gastos!$J$9:$J$4091, Gastos!$L$9:$L$4091, $Z$3, Gastos!$M$9:$M$4091, $Z$4, Gastos!$D$9:$D$4091, Q17) -> 0 | AA17: =SUMIFS(Gastos!$J$9:$J$4091, Gastos!$L$9:$L$4091, $AA$3, Gastos!$M$9:$M$4091, $AA$4, Gastos!$D$9:$D$4091, Q17) -> 0 | AB17: =SUMIFS(Gastos!$J$9:$J$4091, Gastos!$L$9:$L$4091, $AB$3, Gastos!$M$9:$M$4091, $AB$4, Gastos!$D$9:$D$4091, Q17) -> 0 | AC17: =SUMIFS(Gastos!$J$9:$J$4091, Gastos!$L$9:$L$4091, $AC$3, Gastos!$M$9:$M$4091, $AC$4, Gastos!$D$9:$D$4091, Q17) -> 0 | AD17: =SUM(R17:AC17) -> 0 | AK17: =#REF! -> #REF! | AL17: =#REF! -> #REF! | AM17: =#REF! -> #REF! | AN17: =AL17-AM17 -> #REF! | AO17: =AO16+AL17 -> #REF! | AP17: =AP16+AM17 -> #REF!
B18: =#REF! -> #REF! | C18: =SUMIFS(Ingresos!$J$9:$J$3900, Ingresos!$L$9:$L$3900, $C$3, Ingresos!$M$9:$M$3900, $C$4, Ingresos!$D$9:$D$3900, B18) -> 0 | D18: =SUMIFS(Ingresos!$J$9:$J$3900, Ingresos!$L$9:$L$3900, $D$3, Ingresos!$M$9:$M$3900, $D$4, Ingresos!$D$9:$D$3900, B18) -> 0 | E18: =SUMIFS(Ingresos!$J$9:$J$3900, Ingresos!$L$9:$L$3900, $E$3, Ingresos!$M$9:$M$3900, $E$4, Ingresos!$D$9:$D$3900, B18) -> 0 | F18: =SUMIFS(Ingresos!$J$9:$J$3900, Ingresos!$L$9:$L$3900, $F$3, Ingresos!$M$9:$M$3900, $F$4, Ingresos!$D$9:$D$3900, B18) -> 0 | G18: =SUMIFS(Ingresos!$J$9:$J$3900, Ingresos!$L$9:$L$3900, $G$3, Ingresos!$M$9:$M$3900, $G$4, Ingresos!$D$9:$D$3900, B18) -> 0 | H18: =SUMIFS(Ingresos!$J$9:$J$3900, Ingresos!$L$9:$L$3900, $H$3, Ingresos!$M$9:$M$3900, $H$4, Ingresos!$D$9:$D$3900, B18) -> 0 | I18: =SUMIFS(Ingresos!$J$9:$J$3900, Ingresos!$L$9:$L$3900, $I$3, Ingresos!$M$9:$M$3900, $I$4, Ingresos!$D$9:$D$3900, B18) -> 0 | J18: =SUMIFS(Ingresos!$J$9:$J$3900, Ingresos!$L$9:$L$3900, $J$3, Ingresos!$M$9:$M$3900, $J$4, Ingresos!$D$9:$D$3900, B18) -> 0 | K18: =SUMIFS(Ingresos!$J$9:$J$3900, Ingresos!$L$9:$L$3900, $K$3, Ingresos!$M$9:$M$3900, $K$4, Ingresos!$D$9:$D$3900, B18) -> 0 | L18: =SUMIFS(Ingresos!$J$9:$J$3900, Ingresos!$L$9:$L$3900, $L$3, Ingresos!$M$9:$M$3900, $L$4, Ingresos!$D$9:$D$3900, B18) -> 0 | M18: =SUMIFS(Ingresos!$J$9:$J$3900, Ingresos!$L$9:$L$3900, $M$3, Ingresos!$M$9:$M$3900, $M$4, Ingresos!$D$9:$D$3900, B18) -> 0 | N18: =SUMIFS(Ingresos!$J$9:$J$3900, Ingresos!$L$9:$L$3900, $N$3, Ingresos!$M$9:$M$3900, $N$4, Ingresos!$D$9:$D$3900, B18) -> 0 | O18: =SUM(C18:N18) -> 0 | Q18: =#REF! -> #REF! | R18: =SUMIFS(Gastos!$J$9:$J$4091, Gastos!$L$9:$L$4091, $R$3, Gastos!$M$9:$M$4091, $R$4, Gastos!$D$9:$D$4091, Q18) -> 0 | S18: =SUMIFS(Gastos!$J$9:$J$4091, Gastos!$L$9:$L$4091, $S$3, Gastos!$M$9:$M$4091, $S$4, Gastos!$D$9:$D$4091, Q18) -> 0 | T18: =SUMIFS(Gastos!$J$9:$J$4091, Gastos!$L$9:$L$4091, $T$3, Gastos!$M$9:$M$4091, $T$4, Gastos!$D$9:$D$4091, Q18) -> 0 | U18: =SUMIFS(Gastos!$J$9:$J$4091, Gastos!$L$9:$L$4091, $U$3, Gastos!$M$9:$M$4091, $U$4, Gastos!$D$9:$D$4091, Q18) -> 0 | V18: =SUMIFS(Gastos!$J$9:$J$4091, Gastos!$L$9:$L$4091, $V$3, Gastos!$M$9:$M$4091, $V$4, Gastos!$D$9:$D$4091, Q18) -> 0 | W18: =SUMIFS(Gastos!$J$9:$J$4091, Gastos!$L$9:$L$4091, $W$3, Gastos!$M$9:$M$4091, $W$4, Gastos!$D$9:$D$4091, Q18) -> 0 | X18: =SUMIFS(Gastos!$J$9:$J$4091, Gastos!$L$9:$L$4091, $X$3, Gastos!$M$9:$M$4091, $X$4, Gastos!$D$9:$D$4091, Q18) -> 0 | Y18: =SUMIFS(Gastos!$J$9:$J$4091, Gastos!$L$9:$L$4091, $Y$3, Gastos!$M$9:$M$4091, $Y$4, Gastos!$D$9:$D$4091, Q18) -> 0 | Z18: =SUMIFS(Gastos!$J$9:$J$4091, Gastos!$L$9:$L$4091, $Z$3, Gastos!$M$9:$M$4091, $Z$4, Gastos!$D$9:$D$4091, Q18) -> 0 | AA18: =SUMIFS(Gastos!$J$9:$J$4091, Gastos!$L$9:$L$4091, $AA$3, Gastos!$M$9:$M$4091, $AA$4, Gastos!$D$9:$D$4091, Q18) -> 0 | AB18: =SUMIFS(Gastos!$J$9:$J$4091, Gastos!$L$9:$L$4091, $AB$3, Gastos!$M$9:$M$4091, $AB$4, Gastos!$D$9:$D$4091, Q18) -> 0 | AC18: =SUMIFS(Gastos!$J$9:$J$4091, Gastos!$L$9:$L$4091, $AC$3, Gastos!$M$9:$M$4091, $AC$4, Gastos!$D$9:$D$4091, Q18) -> 0 | AD18: =SUM(R18:AC18) -> 0 | AK18: =#REF! -> #REF! | AL18: =#REF! -> #REF! | AM18: =#REF! -> #REF! | AN18: =AL18-AM18 -> #REF! | AO18: =AO17+AL18 -> #REF! | AP18: =AP17+AM18 -> #REF!
B19: =#REF! -> #REF! | C19: =SUMIFS(Ingresos!$J$9:$J$3900, Ingresos!$L$9:$L$3900, $C$3, Ingresos!$M$9:$M$3900, $C$4, Ingresos!$D$9:$D$3900, B19) -> 0 | D19: =SUMIFS(Ingresos!$J$9:$J$3900, Ingresos!$L$9:$L$3900, $D$3, Ingresos!$M$9:$M$3900, $D$4, Ingresos!$D$9:$D$3900, B19) -> 0 | E19: =SUMIFS(Ingresos!$J$9:$J$3900, Ingresos!$L$9:$L$3900, $E$3, Ingresos!$M$9:$M$3900, $E$4, Ingresos!$D$9:$D$3900, B19) -> 0 | F19: =SUMIFS(Ingresos!$J$9:$J$3900, Ingresos!$L$9:$L$3900, $F$3, Ingresos!$M$9:$M$3900, $F$4, Ingresos!$D$9:$D$3900, B19) -> 0 | G19: =SUMIFS(Ingresos!$J$9:$J$3900, Ingresos!$L$9:$L$3900, $G$3, Ingresos!$M$9:$M$3900, $G$4, Ingresos!$D$9:$D$3900, B19) -> 0 | H19: =SUMIFS(Ingresos!$J$9:$J$3900, Ingresos!$L$9:$L$3900, $H$3, Ingresos!$M$9:$M$3900, $H$4, Ingresos!$D$9:$D$3900, B19) -> 0 | I19: =SUMIFS(Ingresos!$J$9:$J$3900, Ingresos!$L$9:$L$3900, $I$3, Ingresos!$M$9:$M$3900, $I$4, Ingresos!$D$9:$D$3900, B19) -> 0 | J19: =SUMIFS(Ingresos!$J$9:$J$3900, Ingresos!$L$9:$L$3900, $J$3, Ingresos!$M$9:$M$3900, $J$4, Ingresos!$D$9:$D$3900, B19) -> 0 | K19: =SUMIFS(Ingresos!$J$9:$J$3900, Ingresos!$L$9:$L$3900, $K$3, Ingresos!$M$9:$M$3900, $K$4, Ingresos!$D$9:$D$3900, B19) -> 0 | L19: =SUMIFS(Ingresos!$J$9:$J$3900, Ingresos!$L$9:$L$3900, $L$3, Ingresos!$M$9:$M$3900, $L$4, Ingresos!$D$9:$D$3900, B19) -> 0 | M19: =SUMIFS(Ingresos!$J$9:$J$3900, Ingresos!$L$9:$L$3900, $M$3, Ingresos!$M$9:$M$3900, $M$4, Ingresos!$D$9:$D$3900, B19) -> 0 | N19: =SUMIFS(Ingresos!$J$9:$J$3900, Ingresos!$L$9:$L$3900, $N$3, Ingresos!$M$9:$M$3900, $N$4, Ingresos!$D$9:$D$3900, B19) -> 0 | O19: =SUM(C19:N19) -> 0 | Q19: =#REF! -> #REF! | R19: =SUMIFS(Gastos!$J$9:$J$4091, Gastos!$L$9:$L$4091, $R$3, Gastos!$M$9:$M$4091, $R$4, Gastos!$D$9:$D$4091, Q19) -> 0 | S19: =SUMIFS(Gastos!$J$9:$J$4091, Gastos!$L$9:$L$4091, $S$3, Gastos!$M$9:$M$4091, $S$4, Gastos!$D$9:$D$4091, Q19) -> 0 | T19: =SUMIFS(Gastos!$J$9:$J$4091, Gastos!$L$9:$L$4091, $T$3, Gastos!$M$9:$M$4091, $T$4, Gastos!$D$9:$D$4091, Q19) -> 0 | U19: =SUMIFS(Gastos!$J$9:$J$4091, Gastos!$L$9:$L$4091, $U$3, Gastos!$M$9:$M$4091, $U$4, Gastos!$D$9:$D$4091, Q19) -> 0 | V19: =SUMIFS(Gastos!$J$9:$J$4091, Gastos!$L$9:$L$4091, $V$3, Gastos!$M$9:$M$4091, $V$4, Gastos!$D$9:$D$4091, Q19) -> 0 | W19: =SUMIFS(Gastos!$J$9:$J$4091, Gastos!$L$9:$L$4091, $W$3, Gastos!$M$9:$M$4091, $W$4, Gastos!$D$9:$D$4091, Q19) -> 0 | X19: =SUMIFS(Gastos!$J$9:$J$4091, Gastos!$L$9:$L$4091, $X$3, Gastos!$M$9:$M$4091, $X$4, Gastos!$D$9:$D$4091, Q19) -> 0 | Y19: =SUMIFS(Gastos!$J$9:$J$4091, Gastos!$L$9:$L$4091, $Y$3, Gastos!$M$9:$M$4091, $Y$4, Gastos!$D$9:$D$4091, Q19) -> 0 | Z19: =SUMIFS(Gastos!$J$9:$J$4091, Gastos!$L$9:$L$4091, $Z$3, Gastos!$M$9:$M$4091, $Z$4, Gastos!$D$9:$D$4091, Q19) -> 0 | AA19: =SUMIFS(Gastos!$J$9:$J$4091, Gastos!$L$9:$L$4091, $AA$3, Gastos!$M$9:$M$4091, $AA$4, Gastos!$D$9:$D$4091, Q19) -> 0 | AB19: =SUMIFS(Gastos!$J$9:$J$4091, Gastos!$L$9:$L$4091, $AB$3, Gastos!$M$9:$M$4091, $AB$4, Gastos!$D$9:$D$4091, Q19) -> 0 | AC19: =SUMIFS(Gastos!$J$9:$J$4091, Gastos!$L$9:$L$4091, $AC$3, Gastos!$M$9:$M$4091, $AC$4, Gastos!$D$9:$D$4091, Q19) -> 0 | AD19: =SUM(R19:AC19) -> 0 | AK19: =#REF! -> #REF! | AL19: =#REF! -> #REF! | AM19: =#REF! -> #REF! | AN19: =AL19-AM19 -> #REF! | AO19: =AO18+AL19 -> #REF! | AP19: =AP18+AM19 -> #REF!
B20: =#REF! -> #REF! | C20: =SUMIFS(Ingresos!$J$9:$J$3900, Ingresos!$L$9:$L$3900, $C$3, Ingresos!$M$9:$M$3900, $C$4, Ingresos!$D$9:$D$3900, B20) -> 0 | D20: =SUMIFS(Ingresos!$J$9:$J$3900, Ingresos!$L$9:$L$3900, $D$3, Ingresos!$M$9:$M$3900, $D$4, Ingresos!$D$9:$D$3900, B20) -> 0 | E20: =SUMIFS(Ingresos!$J$9:$J$3900, Ingresos!$L$9:$L$3900, $E$3, Ingresos!$M$9:$M$3900, $E$4, Ingresos!$D$9:$D$3900, B20) -> 0 | F20: =SUMIFS(Ingresos!$J$9:$J$3900, Ingresos!$L$9:$L$3900, $F$3, Ingresos!$M$9:$M$3900, $F$4, Ingresos!$D$9:$D$3900, B20) -> 0 | G20: =SUMIFS(Ingresos!$J$9:$J$3900, Ingresos!$L$9:$L$3900, $G$3, Ingresos!$M$9:$M$3900, $G$4, Ingresos!$D$9:$D$3900, B20) -> 0 | H20: =SUMIFS(Ingresos!$J$9:$J$3900, Ingresos!$L$9:$L$3900, $H$3, Ingresos!$M$9:$M$3900, $H$4, Ingresos!$D$9:$D$3900, B20) -> 0 | I20: =SUMIFS(Ingresos!$J$9:$J$3900, Ingresos!$L$9:$L$3900, $I$3, Ingresos!$M$9:$M$3900, $I$4, Ingresos!$D$9:$D$3900, B20) -> 0 | J20: =SUMIFS(Ingresos!$J$9:$J$3900, Ingresos!$L$9:$L$3900, $J$3, Ingresos!$M$9:$M$3900, $J$4, Ingresos!$D$9:$D$3900, B20) -> 0 | K20: =SUMIFS(Ingresos!$J$9:$J$3900, Ingresos!$L$9:$L$3900, $K$3, Ingresos!$M$9:$M$3900, $K$4, Ingresos!$D$9:$D$3900, B20) -> 0 | L20: =SUMIFS(Ingresos!$J$9:$J$3900, Ingresos!$L$9:$L$3900, $L$3, Ingresos!$M$9:$M$3900, $L$4, Ingresos!$D$9:$D$3900, B20) -> 0 | M20: =SUMIFS(Ingresos!$J$9:$J$3900, Ingresos!$L$9:$L$3900, $M$3, Ingresos!$M$9:$M$3900, $M$4, Ingresos!$D$9:$D$3900, B20) -> 0 | N20: =SUMIFS(Ingresos!$J$9:$J$3900, Ingresos!$L$9:$L$3900, $N$3, Ingresos!$M$9:$M$3900, $N$4, Ingresos!$D$9:$D$3900, B20) -> 0 | O20: =SUM(C20:N20) -> 0 | Q20: =#REF! -> #REF! | R20: =SUMIFS(Gastos!$J$9:$J$4091, Gastos!$L$9:$L$4091, $R$3, Gastos!$M$9:$M$4091, $R$4, Gastos!$D$9:$D$4091, Q20) -> 0 | S20: =SUMIFS(Gastos!$J$9:$J$4091, Gastos!$L$9:$L$4091, $S$3, Gastos!$M$9:$M$4091, $S$4, Gastos!$D$9:$D$4091, Q20) -> 0 | T20: =SUMIFS(Gastos!$J$9:$J$4091, Gastos!$L$9:$L$4091, $T$3, Gastos!$M$9:$M$4091, $T$4, Gastos!$D$9:$D$4091, Q20) -> 0 | U20: =SUMIFS(Gastos!$J$9:$J$4091, Gastos!$L$9:$L$4091, $U$3, Gastos!$M$9:$M$4091, $U$4, Gastos!$D$9:$D$4091, Q20) -> 0 | V20: =SUMIFS(Gastos!$J$9:$J$4091, Gastos!$L$9:$L$4091, $V$3, Gastos!$M$9:$M$4091, $V$4, Gastos!$D$9:$D$4091, Q20) -> 0 | W20: =SUMIFS(Gastos!$J$9:$J$4091, Gastos!$L$9:$L$4091, $W$3, Gastos!$M$9:$M$4091, $W$4, Gastos!$D$9:$D$4091, Q20) -> 0 | X20: =SUMIFS(Gastos!$J$9:$J$4091, Gastos!$L$9:$L$4091, $X$3, Gastos!$M$9:$M$4091, $X$4, Gastos!$D$9:$D$4091, Q20) -> 0 | Y20: =SUMIFS(Gastos!$J$9:$J$4091, Gastos!$L$9:$L$4091, $Y$3, Gastos!$M$9:$M$4091, $Y$4, Gastos!$D$9:$D$4091, Q20) -> 0 | Z20: =SUMIFS(Gastos!$J$9:$J$4091, Gastos!$L$9:$L$4091, $Z$3, Gastos!$M$9:$M$4091, $Z$4, Gastos!$D$9:$D$4091, Q20) -> 0 | AA20: =SUMIFS(Gastos!$J$9:$J$4091, Gastos!$L$9:$L$4091, $AA$3, Gastos!$M$9:$M$4091, $AA$4, Gastos!$D$9:$D$4091, Q20) -> 0 | AB20: =SUMIFS(Gastos!$J$9:$J$4091, Gastos!$L$9:$L$4091, $AB$3, Gastos!$M$9:$M$4091, $AB$4, Gastos!$D$9:$D$4091, Q20) -> 0 | AC20: =SUMIFS(Gastos!$J$9:$J$4091, Gastos!$L$9:$L$4091, $AC$3, Gastos!$M$9:$M$4091, $AC$4, Gastos!$D$9:$D$4091, Q20) -> 0 | AD20: =SUM(R20:AC20) -> 0 | AK20: =#REF! -> #REF! | AL20: =#REF! -> #REF! | AM20: =#REF! -> #REF! | AN20: =AL20-AM20 -> #REF! | AO20: =AO19+AL20 -> #REF! | AP20: =AP19+AM20 -> #REF!
B21: =#REF! -> #REF! | C21: =SUMIFS(Ingresos!$J$9:$J$3900, Ingresos!$L$9:$L$3900, $C$3, Ingresos!$M$9:$M$3900, $C$4, Ingresos!$D$9:$D$3900, B21) -> 0 | D21: =SUMIFS(Ingresos!$J$9:$J$3900, Ingresos!$L$9:$L$3900, $D$3, Ingresos!$M$9:$M$3900, $D$4, Ingresos!$D$9:$D$3900, B21) -> 0 | E21: =SUMIFS(Ingresos!$J$9:$J$3900, Ingresos!$L$9:$L$3900, $E$3, Ingresos!$M$9:$M$3900, $E$4, Ingresos!$D$9:$D$3900, B21) -> 0 | F21: =SUMIFS(Ingresos!$J$9:$J$3900, Ingresos!$L$9:$L$3900, $F$3, Ingresos!$M$9:$M$3900, $F$4, Ingresos!$D$9:$D$3900, B21) -> 0 | G21: =SUMIFS(Ingresos!$J$9:$J$3900, Ingresos!$L$9:$L$3900, $G$3, Ingresos!$M$9:$M$3900, $G$4, Ingresos!$D$9:$D$3900, B21) -> 0 | H21: =SUMIFS(Ingresos!$J$9:$J$3900, Ingresos!$L$9:$L$3900, $H$3, Ingresos!$M$9:$M$3900, $H$4, Ingresos!$D$9:$D$3900, B21) -> 0 | I21: =SUMIFS(Ingresos!$J$9:$J$3900, Ingresos!$L$9:$L$3900, $I$3, Ingresos!$M$9:$M$3900, $I$4, Ingresos!$D$9:$D$3900, B21) -> 0 | J21: =SUMIFS(Ingresos!$J$9:$J$3900, Ingresos!$L$9:$L$3900, $J$3, Ingresos!$M$9:$M$3900, $J$4, Ingresos!$D$9:$D$3900, B21) -> 0 | K21: =SUMIFS(Ingresos!$J$9:$J$3900, Ingresos!$L$9:$L$3900, $K$3, Ingresos!$M$9:$M$3900, $K$4, Ingresos!$D$9:$D$3900, B21) -> 0 | L21: =SUMIFS(Ingresos!$J$9:$J$3900, Ingresos!$L$9:$L$3900, $L$3, Ingresos!$M$9:$M$3900, $L$4, Ingresos!$D$9:$D$3900, B21) -> 0 | M21: =SUMIFS(Ingresos!$J$9:$J$3900, Ingresos!$L$9:$L$3900, $M$3, Ingresos!$M$9:$M$3900, $M$4, Ingresos!$D$9:$D$3900, B21) -> 0 | N21: =SUMIFS(Ingresos!$J$9:$J$3900, Ingresos!$L$9:$L$3900, $N$3, Ingresos!$M$9:$M$3900, $N$4, Ingresos!$D$9:$D$3900, B21) -> 0 | O21: =SUM(C21:N21) -> 0 | Q21: =#REF! -> #REF! | R21: =SUMIFS(Gastos!$J$9:$J$4091, Gastos!$L$9:$L$4091, $R$3, Gastos!$M$9:$M$4091, $R$4, Gastos!$D$9:$D$4091, Q21) -> 0 | S21: =SUMIFS(Gastos!$J$9:$J$4091, Gastos!$L$9:$L$4091, $S$3, Gastos!$M$9:$M$4091, $S$4, Gastos!$D$9:$D$4091, Q21) -> 0 | T21: =SUMIFS(Gastos!$J$9:$J$4091, Gastos!$L$9:$L$4091, $T$3, Gastos!$M$9:$M$4091, $T$4, Gastos!$D$9:$D$4091, Q21) -> 0 | U21: =SUMIFS(Gastos!$J$9:$J$4091, Gastos!$L$9:$L$4091, $U$3, Gastos!$M$9:$M$4091, $U$4, Gastos!$D$9:$D$4091, Q21) -> 0 | V21: =SUMIFS(Gastos!$J$9:$J$4091, Gastos!$L$9:$L$4091, $V$3, Gastos!$M$9:$M$4091, $V$4, Gastos!$D$9:$D$4091, Q21) -> 0 | W21: =SUMIFS(Gastos!$J$9:$J$4091, Gastos!$L$9:$L$4091, $W$3, Gastos!$M$9:$M$4091, $W$4, Gastos!$D$9:$D$4091, Q21) -> 0 | X21: =SUMIFS(Gastos!$J$9:$J$4091, Gastos!$L$9:$L$4091, $X$3, Gastos!$M$9:$M$4091, $X$4, Gastos!$D$9:$D$4091, Q21) -> 0 | Y21: =SUMIFS(Gastos!$J$9:$J$4091, Gastos!$L$9:$L$4091, $Y$3, Gastos!$M$9:$M$4091, $Y$4, Gastos!$D$9:$D$4091, Q21) -> 0 | Z21: =SUMIFS(Gastos!$J$9:$J$4091, Gastos!$L$9:$L$4091, $Z$3, Gastos!$M$9:$M$4091, $Z$4, Gastos!$D$9:$D$4091, Q21) -> 0 | AA21: =SUMIFS(Gastos!$J$9:$J$4091, Gastos!$L$9:$L$4091, $AA$3, Gastos!$M$9:$M$4091, $AA$4, Gastos!$D$9:$D$4091, Q21) -> 0 | AB21: =SUMIFS(Gastos!$J$9:$J$4091, Gastos!$L$9:$L$4091, $AB$3, Gastos!$M$9:$M$4091, $AB$4, Gastos!$D$9:$D$4091, Q21) -> 0 | AC21: =SUMIFS(Gastos!$J$9:$J$4091, Gastos!$L$9:$L$4091, $AC$3, Gastos!$M$9:$M$4091, $AC$4, Gastos!$D$9:$D$4091, Q21) -> 0 | AD21: =SUM(R21:AC21) -> 0 | AK21: =#REF! -> #REF! | AL21: =#REF! -> #REF! | AM21: =#REF! -> #REF! | AN21: =AL21-AM21 -> #REF! | AO21: =AO20+AL21 -> #REF! | AP21: =AP20+AM21 -> #REF!
B22: =#REF! -> #REF! | C22: =SUMIFS(Ingresos!$J$9:$J$3900, Ingresos!$L$9:$L$3900, $C$3, Ingresos!$M$9:$M$3900, $C$4, Ingresos!$D$9:$D$3900, B22) -> 0 | D22: =SUMIFS(Ingresos!$J$9:$J$3900, Ingresos!$L$9:$L$3900, $D$3, Ingresos!$M$9:$M$3900, $D$4, Ingresos!$D$9:$D$3900, B22) -> 0 | E22: =SUMIFS(Ingresos!$J$9:$J$3900, Ingresos!$L$9:$L$3900, $E$3, Ingresos!$M$9:$M$3900, $E$4, Ingresos!$D$9:$D$3900, B22) -> 0 | F22: =SUMIFS(Ingresos!$J$9:$J$3900, Ingresos!$L$9:$L$3900, $F$3, Ingresos!$M$9:$M$3900, $F$4, Ingresos!$D$9:$D$3900, B22) -> 0 | G22: =SUMIFS(Ingresos!$J$9:$J$3900, Ingresos!$L$9:$L$3900, $G$3, Ingresos!$M$9:$M$3900, $G$4, Ingresos!$D$9:$D$3900, B22) -> 0 | H22: =SUMIFS(Ingresos!$J$9:$J$3900, Ingresos!$L$9:$L$3900, $H$3, Ingresos!$M$9:$M$3900, $H$4, Ingresos!$D$9:$D$3900, B22) -> 0 | I22: =SUMIFS(Ingresos!$J$9:$J$3900, Ingresos!$L$9:$L$3900, $I$3, Ingresos!$M$9:$M$3900, $I$4, Ingresos!$D$9:$D$3900, B22) -> 0 | J22: =SUMIFS(Ingresos!$J$9:$J$3900, Ingresos!$L$9:$L$3900, $J$3, Ingresos!$M$9:$M$3900, $J$4, Ingresos!$D$9:$D$3900, B22) -> 0 | K22: =SUMIFS(Ingresos!$J$9:$J$3900, Ingresos!$L$9:$L$3900, $K$3, Ingresos!$M$9:$M$3900, $K$4, Ingresos!$D$9:$D$3900, B22) -> 0 | L22: =SUMIFS(Ingresos!$J$9:$J$3900, Ingresos!$L$9:$L$3900, $L$3, Ingresos!$M$9:$M$3900, $L$4, Ingresos!$D$9:$D$3900, B22) -> 0 | M22: =SUMIFS(Ingresos!$J$9:$J$3900, Ingresos!$L$9:$L$3900, $M$3, Ingresos!$M$9:$M$3900, $M$4, Ingresos!$D$9:$D$3900, B22) -> 0 | N22: =SUMIFS(Ingresos!$J$9:$J$3900, Ingresos!$L$9:$L$3900, $N$3, Ingresos!$M$9:$M$3900, $N$4, Ingresos!$D$9:$D$3900, B22) -> 0 | O22: =SUM(C22:N22) -> 0 | Q22: =#REF! -> #REF! | R22: =SUMIFS(Gastos!$J$9:$J$4091, Gastos!$L$9:$L$4091, $R$3, Gastos!$M$9:$M$4091, $R$4, Gastos!$D$9:$D$4091, Q22) -> 0 | S22: =SUMIFS(Gastos!$J$9:$J$4091, Gastos!$L$9:$L$4091, $S$3, Gastos!$M$9:$M$4091, $S$4, Gastos!$D$9:$D$4091, Q22) -> 0 | T22: =SUMIFS(Gastos!$J$9:$J$4091, Gastos!$L$9:$L$4091, $T$3, Gastos!$M$9:$M$4091, $T$4, Gastos!$D$9:$D$4091, Q22) -> 0 | U22: =SUMIFS(Gastos!$J$9:$J$4091, Gastos!$L$9:$L$4091, $U$3, Gastos!$M$9:$M$4091, $U$4, Gastos!$D$9:$D$4091, Q22) -> 0 | V22: =SUMIFS(Gastos!$J$9:$J$4091, Gastos!$L$9:$L$4091, $V$3, Gastos!$M$9:$M$4091, $V$4, Gastos!$D$9:$D$4091, Q22) -> 0 | W22: =SUMIFS(Gastos!$J$9:$J$4091, Gastos!$L$9:$L$4091, $W$3, Gastos!$M$9:$M$4091, $W$4, Gastos!$D$9:$D$4091, Q22) -> 0 | X22: =SUMIFS(Gastos!$J$9:$J$4091, Gastos!$L$9:$L$4091, $X$3, Gastos!$M$9:$M$4091, $X$4, Gastos!$D$9:$D$4091, Q22) -> 0 | Y22: =SUMIFS(Gastos!$J$9:$J$4091, Gastos!$L$9:$L$4091, $Y$3, Gastos!$M$9:$M$4091, $Y$4, Gastos!$D$9:$D$4091, Q22) -> 0 | Z22: =SUMIFS(Gastos!$J$9:$J$4091, Gastos!$L$9:$L$4091, $Z$3, Gastos!$M$9:$M$4091, $Z$4, Gastos!$D$9:$D$4091, Q22) -> 0 | AA22: =SUMIFS(Gastos!$J$9:$J$4091, Gastos!$L$9:$L$4091, $AA$3, Gastos!$M$9:$M$4091, $AA$4, Gastos!$D$9:$D$4091, Q22) -> 0 | AB22: =SUMIFS(Gastos!$J$9:$J$4091, Gastos!$L$9:$L$4091, $AB$3, Gastos!$M$9:$M$4091, $AB$4, Gastos!$D$9:$D$4091, Q22) -> 0 | AC22: =SUMIFS(Gastos!$J$9:$J$4091, Gastos!$L$9:$L$4091, $AC$3, Gastos!$M$9:$M$4091, $AC$4, Gastos!$D$9:$D$4091, Q22) -> 0 | AD22: =SUM(R22:AC22) -> 0 | AK22: =#REF! -> #REF! | AL22: =#REF! -> #REF! | AM22: =#REF! -> #REF! | AN22: =AL22-AM22 -> #REF! | AO22: =AO21+AL22 -> #REF! | AP22: =AP21+AM22 -> #REF!
B23: =#REF! -> #REF! | C23: =SUMIFS(Ingresos!$J$9:$J$3900, Ingresos!$L$9:$L$3900, $C$3, Ingresos!$M$9:$M$3900, $C$4, Ingresos!$D$9:$D$3900, B23) -> 0 | D23: =SUMIFS(Ingresos!$J$9:$J$3900, Ingresos!$L$9:$L$3900, $D$3, Ingresos!$M$9:$M$3900, $D$4, Ingresos!$D$9:$D$3900, B23) -> 0 | E23: =SUMIFS(Ingresos!$J$9:$J$3900, Ingresos!$L$9:$L$3900, $E$3, Ingresos!$M$9:$M$3900, $E$4, Ingresos!$D$9:$D$3900, B23) -> 0 | F23: =SUMIFS(Ingresos!$J$9:$J$3900, Ingresos!$L$9:$L$3900, $F$3, Ingresos!$M$9:$M$3900, $F$4, Ingresos!$D$9:$D$3900, B23) -> 0 | G23: =SUMIFS(Ingresos!$J$9:$J$3900, Ingresos!$L$9:$L$3900, $G$3, Ingresos!$M$9:$M$3900, $G$4, Ingresos!$D$9:$D$3900, B23) -> 0 | H23: =SUMIFS(Ingresos!$J$9:$J$3900, Ingresos!$L$9:$L$3900, $H$3, Ingresos!$M$9:$M$3900, $H$4, Ingresos!$D$9:$D$3900, B23) -> 0 | I23: =SUMIFS(Ingresos!$J$9:$J$3900, Ingresos!$L$9:$L$3900, $I$3, Ingresos!$M$9:$M$3900, $I$4, Ingresos!$D$9:$D$3900, B23) -> 0 | J23: =SUMIFS(Ingresos!$J$9:$J$3900, Ingresos!$L$9:$L$3900, $J$3, Ingresos!$M$9:$M$3900, $J$4, Ingresos!$D$9:$D$3900, B23) -> 0 | K23: =SUMIFS(Ingresos!$J$9:$J$3900, Ingresos!$L$9:$L$3900, $K$3, Ingresos!$M$9:$M$3900, $K$4, Ingresos!$D$9:$D$3900, B23) -> 0 | L23: =SUMIFS(Ingresos!$J$9:$J$3900, Ingresos!$L$9:$L$3900, $L$3, Ingresos!$M$9:$M$3900, $L$4, Ingresos!$D$9:$D$3900, B23) -> 0 | M23: =SUMIFS(Ingresos!$J$9:$J$3900, Ingresos!$L$9:$L$3900, $M$3, Ingresos!$M$9:$M$3900, $M$4, Ingresos!$D$9:$D$3900, B23) -> 0 | N23: =SUMIFS(Ingresos!$J$9:$J$3900, Ingresos!$L$9:$L$3900, $N$3, Ingresos!$M$9:$M$3900, $N$4, Ingresos!$D$9:$D$3900, B23) -> 0 | O23: =SUM(C23:N23) -> 0 | Q23: =#REF! -> #REF! | R23: =SUMIFS(Gastos!$J$9:$J$4091, Gastos!$L$9:$L$4091, $R$3, Gastos!$M$9:$M$4091, $R$4, Gastos!$D$9:$D$4091, Q23) -> 0 | S23: =SUMIFS(Gastos!$J$9:$J$4091, Gastos!$L$9:$L$4091, $S$3, Gastos!$M$9:$M$4091, $S$4, Gastos!$D$9:$D$4091, Q23) -> 0 | T23: =SUMIFS(Gastos!$J$9:$J$4091, Gastos!$L$9:$L$4091, $T$3, Gastos!$M$9:$M$4091, $T$4, Gastos!$D$9:$D$4091, Q23) -> 0 | U23: =SUMIFS(Gastos!$J$9:$J$4091, Gastos!$L$9:$L$4091, $U$3, Gastos!$M$9:$M$4091, $U$4, Gastos!$D$9:$D$4091, Q23) -> 0 | V23: =SUMIFS(Gastos!$J$9:$J$4091, Gastos!$L$9:$L$4091, $V$3, Gastos!$M$9:$M$4091, $V$4, Gastos!$D$9:$D$4091, Q23) -> 0 | W23: =SUMIFS(Gastos!$J$9:$J$4091, Gastos!$L$9:$L$4091, $W$3, Gastos!$M$9:$M$4091, $W$4, Gastos!$D$9:$D$4091, Q23) -> 0 | X23: =SUMIFS(Gastos!$J$9:$J$4091, Gastos!$L$9:$L$4091, $X$3, Gastos!$M$9:$M$4091, $X$4, Gastos!$D$9:$D$4091, Q23) -> 0 | Y23: =SUMIFS(Gastos!$J$9:$J$4091, Gastos!$L$9:$L$4091, $Y$3, Gastos!$M$9:$M$4091, $Y$4, Gastos!$D$9:$D$4091, Q23) -> 0 | Z23: =SUMIFS(Gastos!$J$9:$J$4091, Gastos!$L$9:$L$4091, $Z$3, Gastos!$M$9:$M$4091, $Z$4, Gastos!$D$9:$D$4091, Q23) -> 0 | AA23: =SUMIFS(Gastos!$J$9:$J$4091, Gastos!$L$9:$L$4091, $AA$3, Gastos!$M$9:$M$4091, $AA$4, Gastos!$D$9:$D$4091, Q23) -> 0 | AB23: =SUMIFS(Gastos!$J$9:$J$4091, Gastos!$L$9:$L$4091, $AB$3, Gastos!$M$9:$M$4091, $AB$4, Gastos!$D$9:$D$4091, Q23) -> 0 | AC23: =SUMIFS(Gastos!$J$9:$J$4091, Gastos!$L$9:$L$4091, $AC$3, Gastos!$M$9:$M$4091, $AC$4, Gastos!$D$9:$D$4091, Q23) -> 0 | AD23: =SUM(R23:AC23) -> 0 | AK23: =#REF! -> #REF! | AL23: =#REF! -> #REF! | AM23: =#REF! -> #REF! | AN23: =AL23-AM23 -> #REF! | AO23: =AO22+AL23 -> #REF! | AP23: =AP22+AM23 -> #REF!
B24: =#REF! -> #REF! | C24: =SUMIFS(Ingresos!$J$9:$J$3900, Ingresos!$L$9:$L$3900, $C$3, Ingresos!$M$9:$M$3900, $C$4, Ingresos!$D$9:$D$3900, B24) -> 0 | D24: =SUMIFS(Ingresos!$J$9:$J$3900, Ingresos!$L$9:$L$3900, $D$3, Ingresos!$M$9:$M$3900, $D$4, Ingresos!$D$9:$D$3900, B24) -> 0 | E24: =SUMIFS(Ingresos!$J$9:$J$3900, Ingresos!$L$9:$L$3900, $E$3, Ingresos!$M$9:$M$3900, $E$4, Ingresos!$D$9:$D$3900, B24) -> 0 | F24: =SUMIFS(Ingresos!$J$9:$J$3900, Ingresos!$L$9:$L$3900, $F$3, Ingresos!$M$9:$M$3900, $F$4, Ingresos!$D$9:$D$3900, B24) -> 0 | G24: =SUMIFS(Ingresos!$J$9:$J$3900, Ingresos!$L$9:$L$3900, $G$3, Ingresos!$M$9:$M$3900, $G$4, Ingresos!$D$9:$D$3900, B24) -> 0 | H24: =SUMIFS(Ingresos!$J$9:$J$3900, Ingresos!$L$9:$L$3900, $H$3, Ingresos!$M$9:$M$3900, $H$4, Ingresos!$D$9:$D$3900, B24) -> 0 | I24: =SUMIFS(Ingresos!$J$9:$J$3900, Ingresos!$L$9:$L$3900, $I$3, Ingresos!$M$9:$M$3900, $I$4, Ingresos!$D$9:$D$3900, B24) -> 0 | J24: =SUMIFS(Ingresos!$J$9:$J$3900, Ingresos!$L$9:$L$3900, $J$3, Ingresos!$M$9:$M$3900, $J$4, Ingresos!$D$9:$D$3900, B24) -> 0 | K24: =SUMIFS(Ingresos!$J$9:$J$3900, Ingresos!$L$9:$L$3900, $K$3, Ingresos!$M$9:$M$3900, $K$4, Ingresos!$D$9:$D$3900, B24) -> 0 | L24: =SUMIFS(Ingresos!$J$9:$J$3900, Ingresos!$L$9:$L$3900, $L$3, Ingresos!$M$9:$M$3900, $L$4, Ingresos!$D$9:$D$3900, B24) -> 0 | M24: =SUMIFS(Ingresos!$J$9:$J$3900, Ingresos!$L$9:$L$3900, $M$3, Ingresos!$M$9:$M$3900, $M$4, Ingresos!$D$9:$D$3900, B24) -> 0 | N24: =SUMIFS(Ingresos!$J$9:$J$3900, Ingresos!$L$9:$L$3900, $N$3, Ingresos!$M$9:$M$3900, $N$4, Ingresos!$D$9:$D$3900, B24) -> 0 | O24: =SUM(C24:N24) -> 0 | Q24: =#REF! -> #REF! | R24: =SUMIFS(Gastos!$J$9:$J$4091, Gastos!$L$9:$L$4091, $R$3, Gastos!$M$9:$M$4091, $R$4, Gastos!$D$9:$D$4091, Q24) -> 0 | S24: =SUMIFS(Gastos!$J$9:$J$4091, Gastos!$L$9:$L$4091, $S$3, Gastos!$M$9:$M$4091, $S$4, Gastos!$D$9:$D$4091, Q24) -> 0 | T24: =SUMIFS(Gastos!$J$9:$J$4091, Gastos!$L$9:$L$4091, $T$3, Gastos!$M$9:$M$4091, $T$4, Gastos!$D$9:$D$4091, Q24) -> 0 | U24: =SUMIFS(Gastos!$J$9:$J$4091, Gastos!$L$9:$L$4091, $U$3, Gastos!$M$9:$M$4091, $U$4, Gastos!$D$9:$D$4091, Q24) -> 0 | V24: =SUMIFS(Gastos!$J$9:$J$4091, Gastos!$L$9:$L$4091, $V$3, Gastos!$M$9:$M$4091, $V$4, Gastos!$D$9:$D$4091, Q24) -> 0 | W24: =SUMIFS(Gastos!$J$9:$J$4091, Gastos!$L$9:$L$4091, $W$3, Gastos!$M$9:$M$4091, $W$4, Gastos!$D$9:$D$4091, Q24) -> 0 | X24: =SUMIFS(Gastos!$J$9:$J$4091, Gastos!$L$9:$L$4091, $X$3, Gastos!$M$9:$M$4091, $X$4, Gastos!$D$9:$D$4091, Q24) -> 0 | Y24: =SUMIFS(Gastos!$J$9:$J$4091, Gastos!$L$9:$L$4091, $Y$3, Gastos!$M$9:$M$4091, $Y$4, Gastos!$D$9:$D$4091, Q24) -> 0 | Z24: =SUMIFS(Gastos!$J$9:$J$4091, Gastos!$L$9:$L$4091, $Z$3, Gastos!$M$9:$M$4091, $Z$4, Gastos!$D$9:$D$4091, Q24) -> 0 | AA24: =SUMIFS(Gastos!$J$9:$J$4091, Gastos!$L$9:$L$4091, $AA$3, Gastos!$M$9:$M$4091, $AA$4, Gastos!$D$9:$D$4091, Q24) -> 0 | AB24: =SUMIFS(Gastos!$J$9:$J$4091, Gastos!$L$9:$L$4091, $AB$3, Gastos!$M$9:$M$4091, $AB$4, Gastos!$D$9:$D$4091, Q24) -> 0 | AC24: =SUMIFS(Gastos!$J$9:$J$4091, Gastos!$L$9:$L$4091, $AC$3, Gastos!$M$9:$M$4091, $AC$4, Gastos!$D$9:$D$4091, Q24) -> 0 | AD24: =SUM(R24:AC24) -> 0 | AK24: =#REF! -> #REF! | AL24: =#REF! -> #REF! | AM24: =#REF! -> #REF! | AN24: =AL24-AM24 -> #REF! | AO24: =AO23+AL24 -> #REF! | AP24: =AP23+AM24 -> #REF!
B25: =#REF! -> #REF! | C25: =SUMIFS(Ingresos!$J$9:$J$3900, Ingresos!$L$9:$L$3900, $C$3, Ingresos!$M$9:$M$3900, $C$4, Ingresos!$D$9:$D$3900, B25) -> 0 | D25: =SUMIFS(Ingresos!$J$9:$J$3900, Ingresos!$L$9:$L$3900, $D$3, Ingresos!$M$9:$M$3900, $D$4, Ingresos!$D$9:$D$3900, B25) -> 0 | E25: =SUMIFS(Ingresos!$J$9:$J$3900, Ingresos!$L$9:$L$3900, $E$3, Ingresos!$M$9:$M$3900, $E$4, Ingresos!$D$9:$D$3900, B25) -> 0 | F25: =SUMIFS(Ingresos!$J$9:$J$3900, Ingresos!$L$9:$L$3900, $F$3, Ingresos!$M$9:$M$3900, $F$4, Ingresos!$D$9:$D$3900, B25) -> 0 | G25: =SUMIFS(Ingresos!$J$9:$J$3900, Ingresos!$L$9:$L$3900, $G$3, Ingresos!$M$9:$M$3900, $G$4, Ingresos!$D$9:$D$3900, B25) -> 0 | H25: =SUMIFS(Ingresos!$J$9:$J$3900, Ingresos!$L$9:$L$3900, $H$3, Ingresos!$M$9:$M$3900, $H$4, Ingresos!$D$9:$D$3900, B25) -> 0 | I25: =SUMIFS(Ingresos!$J$9:$J$3900, Ingresos!$L$9:$L$3900, $I$3, Ingresos!$M$9:$M$3900, $I$4, Ingresos!$D$9:$D$3900, B25) -> 0 | J25: =SUMIFS(Ingresos!$J$9:$J$3900, Ingresos!$L$9:$L$3900, $J$3, Ingresos!$M$9:$M$3900, $J$4, Ingresos!$D$9:$D$3900, B25) -> 0 | K25: =SUMIFS(Ingresos!$J$9:$J$3900, Ingresos!$L$9:$L$3900, $K$3, Ingresos!$M$9:$M$3900, $K$4, Ingresos!$D$9:$D$3900, B25) -> 0 | L25: =SUMIFS(Ingresos!$J$9:$J$3900, Ingresos!$L$9:$L$3900, $L$3, Ingresos!$M$9:$M$3900, $L$4, Ingresos!$D$9:$D$3900, B25) -> 0 | M25: =SUMIFS(Ingresos!$J$9:$J$3900, Ingresos!$L$9:$L$3900, $M$3, Ingresos!$M$9:$M$3900, $M$4, Ingresos!$D$9:$D$3900, B25) -> 0 | N25: =SUMIFS(Ingresos!$J$9:$J$3900, Ingresos!$L$9:$L$3900, $N$3, Ingresos!$M$9:$M$3900, $N$4, Ingresos!$D$9:$D$3900, B25) -> 0 | O25: =SUM(C25:N25) -> 0 | Q25: =#REF! -> #REF! | R25: =SUMIFS(Gastos!$J$9:$J$4091, Gastos!$L$9:$L$4091, $R$3, Gastos!$M$9:$M$4091, $R$4, Gastos!$D$9:$D$4091, Q25) -> 0 | S25: =SUMIFS(Gastos!$J$9:$J$4091, Gastos!$L$9:$L$4091, $S$3, Gastos!$M$9:$M$4091, $S$4, Gastos!$D$9:$D$4091, Q25) -> 0 | T25: =SUMIFS(Gastos!$J$9:$J$4091, Gastos!$L$9:$L$4091, $T$3, Gastos!$M$9:$M$4091, $T$4, Gastos!$D$9:$D$4091, Q25) -> 0 | U25: =SUMIFS(Gastos!$J$9:$J$4091, Gastos!$L$9:$L$4091, $U$3, Gastos!$M$9:$M$4091, $U$4, Gastos!$D$9:$D$4091, Q25) -> 0 | V25: =SUMIFS(Gastos!$J$9:$J$4091, Gastos!$L$9:$L$4091, $V$3, Gastos!$M$9:$M$4091, $V$4, Gastos!$D$9:$D$4091, Q25) -> 0 | W25: =SUMIFS(Gastos!$J$9:$J$4091, Gastos!$L$9:$L$4091, $W$3, Gastos!$M$9:$M$4091, $W$4, Gastos!$D$9:$D$4091, Q25) -> 0 | X25: =SUMIFS(Gastos!$J$9:$J$4091, Gastos!$L$9:$L$4091, $X$3, Gastos!$M$9:$M$4091, $X$4, Gastos!$D$9:$D$4091, Q25) -> 0 | Y25: =SUMIFS(Gastos!$J$9:$J$4091, Gastos!$L$9:$L$4091, $Y$3, Gastos!$M$9:$M$4091, $Y$4, Gastos!$D$9:$D$4091, Q25) -> 0 | Z25: =SUMIFS(Gastos!$J$9:$J$4091, Gastos!$L$9:$L$4091, $Z$3, Gastos!$M$9:$M$4091, $Z$4, Gastos!$D$9:$D$4091, Q25) -> 0 | AA25: =SUMIFS(Gastos!$J$9:$J$4091, Gastos!$L$9:$L$4091, $AA$3, Gastos!$M$9:$M$4091, $AA$4, Gastos!$D$9:$D$4091, Q25) -> 0 | AB25: =SUMIFS(Gastos!$J$9:$J$4091, Gastos!$L$9:$L$4091, $AB$3, Gastos!$M$9:$M$4091, $AB$4, Gastos!$D$9:$D$4091, Q25) -> 0 | AC25: =SUMIFS(Gastos!$J$9:$J$4091, Gastos!$L$9:$L$4091, $AC$3, Gastos!$M$9:$M$4091, $AC$4, Gastos!$D$9:$D$4091, Q25) -> 0 | AD25: =SUM(R25:AC25) -> 0 | AK25: =#REF! -> #REF! | AL25: =#REF! -> #REF! | AM25: =#REF! -> #REF! | AN25: =AL25-AM25 -> #REF! | AO25: =AO24+AL25 -> #REF! | AP25: =AP24+AM25 -> #REF!
B26: =#REF! -> #REF! | C26: =SUMIFS(Ingresos!$J$9:$J$3900, Ingresos!$L$9:$L$3900, $C$3, Ingresos!$M$9:$M$3900, $C$4, Ingresos!$D$9:$D$3900, B26) -> 0 | D26: =SUMIFS(Ingresos!$J$9:$J$3900, Ingresos!$L$9:$L$3900, $D$3, Ingresos!$M$9:$M$3900, $D$4, Ingresos!$D$9:$D$3900, B26) -> 0 | E26: =SUMIFS(Ingresos!$J$9:$J$3900, Ingresos!$L$9:$L$3900, $E$3, Ingresos!$M$9:$M$3900, $E$4, Ingresos!$D$9:$D$3900, B26) -> 0 | F26: =SUMIFS(Ingresos!$J$9:$J$3900, Ingresos!$L$9:$L$3900, $F$3, Ingresos!$M$9:$M$3900, $F$4, Ingresos!$D$9:$D$3900, B26) -> 0 | G26: =SUMIFS(Ingresos!$J$9:$J$3900, Ingresos!$L$9:$L$3900, $G$3, Ingresos!$M$9:$M$3900, $G$4, Ingresos!$D$9:$D$3900, B26) -> 0 | H26: =SUMIFS(Ingresos!$J$9:$J$3900, Ingresos!$L$9:$L$3900, $H$3, Ingresos!$M$9:$M$3900, $H$4, Ingresos!$D$9:$D$3900, B26) -> 0 | I26: =SUMIFS(Ingresos!$J$9:$J$3900, Ingresos!$L$9:$L$3900, $I$3, Ingresos!$M$9:$M$3900, $I$4, Ingresos!$D$9:$D$3900, B26) -> 0 | J26: =SUMIFS(Ingresos!$J$9:$J$3900, Ingresos!$L$9:$L$3900, $J$3, Ingresos!$M$9:$M$3900, $J$4, Ingresos!$D$9:$D$3900, B26) -> 0 | K26: =SUMIFS(Ingresos!$J$9:$J$3900, Ingresos!$L$9:$L$3900, $K$3, Ingresos!$M$9:$M$3900, $K$4, Ingresos!$D$9:$D$3900, B26) -> 0 | L26: =SUMIFS(Ingresos!$J$9:$J$3900, Ingresos!$L$9:$L$3900, $L$3, Ingresos!$M$9:$M$3900, $L$4, Ingresos!$D$9:$D$3900, B26) -> 0 | M26: =SUMIFS(Ingresos!$J$9:$J$3900, Ingresos!$L$9:$L$3900, $M$3, Ingresos!$M$9:$M$3900, $M$4, Ingresos!$D$9:$D$3900, B26) -> 0 | N26: =SUMIFS(Ingresos!$J$9:$J$3900, Ingresos!$L$9:$L$3900, $N$3, Ingresos!$M$9:$M$3900, $N$4, Ingresos!$D$9:$D$3900, B26) -> 0 | O26: =SUM(C26:N26) -> 0 | Q26: =#REF! -> #REF! | R26: =SUMIFS(Gastos!$J$9:$J$4091, Gastos!$L$9:$L$4091, $R$3, Gastos!$M$9:$M$4091, $R$4, Gastos!$D$9:$D$4091, Q26) -> 0 | S26: =SUMIFS(Gastos!$J$9:$J$4091, Gastos!$L$9:$L$4091, $S$3, Gastos!$M$9:$M$4091, $S$4, Gastos!$D$9:$D$4091, Q26) -> 0 | T26: =SUMIFS(Gastos!$J$9:$J$4091, Gastos!$L$9:$L$4091, $T$3, Gastos!$M$9:$M$4091, $T$4, Gastos!$D$9:$D$4091, Q26) -> 0 | U26: =SUMIFS(Gastos!$J$9:$J$4091, Gastos!$L$9:$L$4091, $U$3, Gastos!$M$9:$M$4091, $U$4, Gastos!$D$9:$D$4091, Q26) -> 0 | V26: =SUMIFS(Gastos!$J$9:$J$4091, Gastos!$L$9:$L$4091, $V$3, Gastos!$M$9:$M$4091, $V$4, Gastos!$D$9:$D$4091, Q26) -> 0 | W26: =SUMIFS(Gastos!$J$9:$J$4091, Gastos!$L$9:$L$4091, $W$3, Gastos!$M$9:$M$4091, $W$4, Gastos!$D$9:$D$4091, Q26) -> 0 | X26: =SUMIFS(Gastos!$J$9:$J$4091, Gastos!$L$9:$L$4091, $X$3, Gastos!$M$9:$M$4091, $X$4, Gastos!$D$9:$D$4091, Q26) -> 0 | Y26: =SUMIFS(Gastos!$J$9:$J$4091, Gastos!$L$9:$L$4091, $Y$3, Gastos!$M$9:$M$4091, $Y$4, Gastos!$D$9:$D$4091, Q26) -> 0 | Z26: =SUMIFS(Gastos!$J$9:$J$4091, Gastos!$L$9:$L$4091, $Z$3, Gastos!$M$9:$M$4091, $Z$4, Gastos!$D$9:$D$4091, Q26) -> 0 | AA26: =SUMIFS(Gastos!$J$9:$J$4091, Gastos!$L$9:$L$4091, $AA$3, Gastos!$M$9:$M$4091, $AA$4, Gastos!$D$9:$D$4091, Q26) -> 0 | AB26: =SUMIFS(Gastos!$J$9:$J$4091, Gastos!$L$9:$L$4091, $AB$3, Gastos!$M$9:$M$4091, $AB$4, Gastos!$D$9:$D$4091, Q26) -> 0 | AC26: =SUMIFS(Gastos!$J$9:$J$4091, Gastos!$L$9:$L$4091, $AC$3, Gastos!$M$9:$M$4091, $AC$4, Gastos!$D$9:$D$4091, Q26) -> 0 | AD26: =SUM(R26:AC26) -> 0 | AK26: =#REF! -> #REF! | AL26: =#REF! -> #REF! | AM26: =#REF! -> #REF! | AN26: =AL26-AM26 -> #REF! | AO26: =AO25+AL26 -> #REF! | AP26: =AP25+AM26 -> #REF!
B27: =#REF! -> #REF! | C27: =SUMIFS(Ingresos!$J$9:$J$3900, Ingresos!$L$9:$L$3900, $C$3, Ingresos!$M$9:$M$3900, $C$4, Ingresos!$D$9:$D$3900, B27) -> 0 | D27: =SUMIFS(Ingresos!$J$9:$J$3900, Ingresos!$L$9:$L$3900, $D$3, Ingresos!$M$9:$M$3900, $D$4, Ingresos!$D$9:$D$3900, B27) -> 0 | E27: =SUMIFS(Ingresos!$J$9:$J$3900, Ingresos!$L$9:$L$3900, $E$3, Ingresos!$M$9:$M$3900, $E$4, Ingresos!$D$9:$D$3900, B27) -> 0 | F27: =SUMIFS(Ingresos!$J$9:$J$3900, Ingresos!$L$9:$L$3900, $F$3, Ingresos!$M$9:$M$3900, $F$4, Ingresos!$D$9:$D$3900, B27) -> 0 | G27: =SUMIFS(Ingresos!$J$9:$J$3900, Ingresos!$L$9:$L$3900, $G$3, Ingresos!$M$9:$M$3900, $G$4, Ingresos!$D$9:$D$3900, B27) -> 0 | H27: =SUMIFS(Ingresos!$J$9:$J$3900, Ingresos!$L$9:$L$3900, $H$3, Ingresos!$M$9:$M$3900, $H$4, Ingresos!$D$9:$D$3900, B27) -> 0 | I27: =SUMIFS(Ingresos!$J$9:$J$3900, Ingresos!$L$9:$L$3900, $I$3, Ingresos!$M$9:$M$3900, $I$4, Ingresos!$D$9:$D$3900, B27) -> 0 | J27: =SUMIFS(Ingresos!$J$9:$J$3900, Ingresos!$L$9:$L$3900, $J$3, Ingresos!$M$9:$M$3900, $J$4, Ingresos!$D$9:$D$3900, B27) -> 0 | K27: =SUMIFS(Ingresos!$J$9:$J$3900, Ingresos!$L$9:$L$3900, $K$3, Ingresos!$M$9:$M$3900, $K$4, Ingresos!$D$9:$D$3900, B27) -> 0 | L27: =SUMIFS(Ingresos!$J$9:$J$3900, Ingresos!$L$9:$L$3900, $L$3, Ingresos!$M$9:$M$3900, $L$4, Ingresos!$D$9:$D$3900, B27) -> 0 | M27: =SUMIFS(Ingresos!$J$9:$J$3900, Ingresos!$L$9:$L$3900, $M$3, Ingresos!$M$9:$M$3900, $M$4, Ingresos!$D$9:$D$3900, B27) -> 0 | N27: =SUMIFS(Ingresos!$J$9:$J$3900, Ingresos!$L$9:$L$3900, $N$3, Ingresos!$M$9:$M$3900, $N$4, Ingresos!$D$9:$D$3900, B27) -> 0 | O27: =SUM(C27:N27) -> 0 | Q27: =#REF! -> #REF! | R27: =SUMIFS(Gastos!$J$9:$J$4091, Gastos!$L$9:$L$4091, $R$3, Gastos!$M$9:$M$4091, $R$4, Gastos!$D$9:$D$4091, Q27) -> 0 | S27: =SUMIFS(Gastos!$J$9:$J$4091, Gastos!$L$9:$L$4091, $S$3, Gastos!$M$9:$M$4091, $S$4, Gastos!$D$9:$D$4091, Q27) -> 0 | T27: =SUMIFS(Gastos!$J$9:$J$4091, Gastos!$L$9:$L$4091, $T$3, Gastos!$M$9:$M$4091, $T$4, Gastos!$D$9:$D$4091, Q27) -> 0 | U27: =SUMIFS(Gastos!$J$9:$J$4091, Gastos!$L$9:$L$4091, $U$3, Gastos!$M$9:$M$4091, $U$4, Gastos!$D$9:$D$4091, Q27) -> 0 | V27: =SUMIFS(Gastos!$J$9:$J$4091, Gastos!$L$9:$L$4091, $V$3, Gastos!$M$9:$M$4091, $V$4, Gastos!$D$9:$D$4091, Q27) -> 0 | W27: =SUMIFS(Gastos!$J$9:$J$4091, Gastos!$L$9:$L$4091, $W$3, Gastos!$M$9:$M$4091, $W$4, Gastos!$D$9:$D$4091, Q27) -> 0 | X27: =SUMIFS(Gastos!$J$9:$J$4091, Gastos!$L$9:$L$4091, $X$3, Gastos!$M$9:$M$4091, $X$4, Gastos!$D$9:$D$4091, Q27) -> 0 | Y27: =SUMIFS(Gastos!$J$9:$J$4091, Gastos!$L$9:$L$4091, $Y$3, Gastos!$M$9:$M$4091, $Y$4, Gastos!$D$9:$D$4091, Q27) -> 0 | Z27: =SUMIFS(Gastos!$J$9:$J$4091, Gastos!$L$9:$L$4091, $Z$3, Gastos!$M$9:$M$4091, $Z$4, Gastos!$D$9:$D$4091, Q27) -> 0 | AA27: =SUMIFS(Gastos!$J$9:$J$4091, Gastos!$L$9:$L$4091, $AA$3, Gastos!$M$9:$M$4091, $AA$4, Gastos!$D$9:$D$4091, Q27) -> 0 | AB27: =SUMIFS(Gastos!$J$9:$J$4091, Gastos!$L$9:$L$4091, $AB$3, Gastos!$M$9:$M$4091, $AB$4, Gastos!$D$9:$D$4091, Q27) -> 0 | AC27: =SUMIFS(Gastos!$J$9:$J$4091, Gastos!$L$9:$L$4091, $AC$3, Gastos!$M$9:$M$4091, $AC$4, Gastos!$D$9:$D$4091, Q27) -> 0 | AD27: =SUM(R27:AC27) -> 0 | AK27: TOTAL | AL27: =SUM(AL15:AL26) -> #REF! | AM27: =SUM(AM15:AM26) -> #REF! | AN27: =SUM(AN15:AN26) -> #REF! | AO27: =SUM(AO15:AO26) -> #REF! | AP27: =SUM(AP15:AP26) -> #REF!
B28: =#REF! -> #REF! | C28: =SUMIFS(Ingresos!$J$9:$J$3900, Ingresos!$L$9:$L$3900, $C$3, Ingresos!$M$9:$M$3900, $C$4, Ingresos!$D$9:$D$3900, B28) -> 0 | D28: =SUMIFS(Ingresos!$J$9:$J$3900, Ingresos!$L$9:$L$3900, $D$3, Ingresos!$M$9:$M$3900, $D$4, Ingresos!$D$9:$D$3900, B28) -> 0 | E28: =SUMIFS(Ingresos!$J$9:$J$3900, Ingresos!$L$9:$L$3900, $E$3, Ingresos!$M$9:$M$3900, $E$4, Ingresos!$D$9:$D$3900, B28) -> 0 | F28: =SUMIFS(Ingresos!$J$9:$J$3900, Ingresos!$L$9:$L$3900, $F$3, Ingresos!$M$9:$M$3900, $F$4, Ingresos!$D$9:$D$3900, B28) -> 0 | G28: =SUMIFS(Ingresos!$J$9:$J$3900, Ingresos!$L$9:$L$3900, $G$3, Ingresos!$M$9:$M$3900, $G$4, Ingresos!$D$9:$D$3900, B28) -> 0 | H28: =SUMIFS(Ingresos!$J$9:$J$3900, Ingresos!$L$9:$L$3900, $H$3, Ingresos!$M$9:$M$3900, $H$4, Ingresos!$D$9:$D$3900, B28) -> 0 | I28: =SUMIFS(Ingresos!$J$9:$J$3900, Ingresos!$L$9:$L$3900, $I$3, Ingresos!$M$9:$M$3900, $I$4, Ingresos!$D$9:$D$3900, B28) -> 0 | J28: =SUMIFS(Ingresos!$J$9:$J$3900, Ingresos!$L$9:$L$3900, $J$3, Ingresos!$M$9:$M$3900, $J$4, Ingresos!$D$9:$D$3900, B28) -> 0 | K28: =SUMIFS(Ingresos!$J$9:$J$3900, Ingresos!$L$9:$L$3900, $K$3, Ingresos!$M$9:$M$3900, $K$4, Ingresos!$D$9:$D$3900, B28) -> 0 | L28: =SUMIFS(Ingresos!$J$9:$J$3900, Ingresos!$L$9:$L$3900, $L$3, Ingresos!$M$9:$M$3900, $L$4, Ingresos!$D$9:$D$3900, B28) -> 0 | M28: =SUMIFS(Ingresos!$J$9:$J$3900, Ingresos!$L$9:$L$3900, $M$3, Ingresos!$M$9:$M$3900, $M$4, Ingresos!$D$9:$D$3900, B28) -> 0 | N28: =SUMIFS(Ingresos!$J$9:$J$3900, Ingresos!$L$9:$L$3900, $N$3, Ingresos!$M$9:$M$3900, $N$4, Ingresos!$D$9:$D$3900, B28) -> 0 | O28: =SUM(C28:N28) -> 0 | Q28: =#REF! -> #REF! | R28: =SUMIFS(Gastos!$J$9:$J$4091, Gastos!$L$9:$L$4091, $R$3, Gastos!$M$9:$M$4091, $R$4, Gastos!$D$9:$D$4091, Q28) -> 0 | S28: =SUMIFS(Gastos!$J$9:$J$4091, Gastos!$L$9:$L$4091, $S$3, Gastos!$M$9:$M$4091, $S$4, Gastos!$D$9:$D$4091, Q28) -> 0 | T28: =SUMIFS(Gastos!$J$9:$J$4091, Gastos!$L$9:$L$4091, $T$3, Gastos!$M$9:$M$4091, $T$4, Gastos!$D$9:$D$4091, Q28) -> 0 | U28: =SUMIFS(Gastos!$J$9:$J$4091, Gastos!$L$9:$L$4091, $U$3, Gastos!$M$9:$M$4091, $U$4, Gastos!$D$9:$D$4091, Q28) -> 0 | V28: =SUMIFS(Gastos!$J$9:$J$4091, Gastos!$L$9:$L$4091, $V$3, Gastos!$M$9:$M$4091, $V$4, Gastos!$D$9:$D$4091, Q28) -> 0 | W28: =SUMIFS(Gastos!$J$9:$J$4091, Gastos!$L$9:$L$4091, $W$3, Gastos!$M$9:$M$4091, $W$4, Gastos!$D$9:$D$4091, Q28) -> 0 | X28: =SUMIFS(Gastos!$J$9:$J$4091, Gastos!$L$9:$L$4091, $X$3, Gastos!$M$9:$M$4091, $X$4, Gastos!$D$9:$D$4091, Q28) -> 0 | Y28: =SUMIFS(Gastos!$J$9:$J$4091, Gastos!$L$9:$L$4091, $Y$3, Gastos!$M$9:$M$4091, $Y$4, Gastos!$D$9:$D$4091, Q28) -> 0 | Z28: =SUMIFS(Gastos!$J$9:$J$4091, Gastos!$L$9:$L$4091, $Z$3, Gastos!$M$9:$M$4091, $Z$4, Gastos!$D$9:$D$4091, Q28) -> 0 | AA28: =SUMIFS(Gastos!$J$9:$J$4091, Gastos!$L$9:$L$4091, $AA$3, Gastos!$M$9:$M$4091, $AA$4, Gastos!$D$9:$D$4091, Q28) -> 0 | AB28: =SUMIFS(Gastos!$J$9:$J$4091, Gastos!$L$9:$L$4091, $AB$3, Gastos!$M$9:$M$4091, $AB$4, Gastos!$D$9:$D$4091, Q28) -> 0 | AC28: =SUMIFS(Gastos!$J$9:$J$4091, Gastos!$L$9:$L$4091, $AC$3, Gastos!$M$9:$M$4091, $AC$4, Gastos!$D$9:$D$4091, Q28) -> 0 | AD28: =SUM(R28:AC28) -> 0
B29: =#REF! -> #REF! | C29: =SUMIFS(Ingresos!$J$9:$J$3900, Ingresos!$L$9:$L$3900, $C$3, Ingresos!$M$9:$M$3900, $C$4, Ingresos!$D$9:$D$3900, B29) -> 0 | D29: =SUMIFS(Ingresos!$J$9:$J$3900, Ingresos!$L$9:$L$3900, $D$3, Ingresos!$M$9:$M$3900, $D$4, Ingresos!$D$9:$D$3900, B29) -> 0 | E29: =SUMIFS(Ingresos!$J$9:$J$3900, Ingresos!$L$9:$L$3900, $E$3, Ingresos!$M$9:$M$3900, $E$4, Ingresos!$D$9:$D$3900, B29) -> 0 | F29: =SUMIFS(Ingresos!$J$9:$J$3900, Ingresos!$L$9:$L$3900, $F$3, Ingresos!$M$9:$M$3900, $F$4, Ingresos!$D$9:$D$3900, B29) -> 0 | G29: =SUMIFS(Ingresos!$J$9:$J$3900, Ingresos!$L$9:$L$3900, $G$3, Ingresos!$M$9:$M$3900, $G$4, Ingresos!$D$9:$D$3900, B29) -> 0 | H29: =SUMIFS(Ingresos!$J$9:$J$3900, Ingresos!$L$9:$L$3900, $H$3, Ingresos!$M$9:$M$3900, $H$4, Ingresos!$D$9:$D$3900, B29) -> 0 | I29: =SUMIFS(Ingresos!$J$9:$J$3900, Ingresos!$L$9:$L$3900, $I$3, Ingresos!$M$9:$M$3900, $I$4, Ingresos!$D$9:$D$3900, B29) -> 0 | J29: =SUMIFS(Ingresos!$J$9:$J$3900, Ingresos!$L$9:$L$3900, $J$3, Ingresos!$M$9:$M$3900, $J$4, Ingresos!$D$9:$D$3900, B29) -> 0 | K29: =SUMIFS(Ingresos!$J$9:$J$3900, Ingresos!$L$9:$L$3900, $K$3, Ingresos!$M$9:$M$3900, $K$4, Ingresos!$D$9:$D$3900, B29) -> 0 | L29: =SUMIFS(Ingresos!$J$9:$J$3900, Ingresos!$L$9:$L$3900, $L$3, Ingresos!$M$9:$M$3900, $L$4, Ingresos!$D$9:$D$3900, B29) -> 0 | M29: =SUMIFS(Ingresos!$J$9:$J$3900, Ingresos!$L$9:$L$3900, $M$3, Ingresos!$M$9:$M$3900, $M$4, Ingresos!$D$9:$D$3900, B29) -> 0 | N29: =SUMIFS(Ingresos!$J$9:$J$3900, Ingresos!$L$9:$L$3900, $N$3, Ingresos!$M$9:$M$3900, $N$4, Ingresos!$D$9:$D$3900, B29) -> 0 | O29: =SUM(C29:N29) -> 0 | Q29: =#REF! -> #REF! | R29: =SUMIFS(Gastos!$J$9:$J$4091, Gastos!$L$9:$L$4091, $R$3, Gastos!$M$9:$M$4091, $R$4, Gastos!$D$9:$D$4091, Q29) -> 0 | S29: =SUMIFS(Gastos!$J$9:$J$4091, Gastos!$L$9:$L$4091, $S$3, Gastos!$M$9:$M$4091, $S$4, Gastos!$D$9:$D$4091, Q29) -> 0 | T29: =SUMIFS(Gastos!$J$9:$J$4091, Gastos!$L$9:$L$4091, $T$3, Gastos!$M$9:$M$4091, $T$4, Gastos!$D$9:$D$4091, Q29) -> 0 | U29: =SUMIFS(Gastos!$J$9:$J$4091, Gastos!$L$9:$L$4091, $U$3, Gastos!$M$9:$M$4091, $U$4, Gastos!$D$9:$D$4091, Q29) -> 0 | V29: =SUMIFS(Gastos!$J$9:$J$4091, Gastos!$L$9:$L$4091, $V$3, Gastos!$M$9:$M$4091, $V$4, Gastos!$D$9:$D$4091, Q29) -> 0 | W29: =SUMIFS(Gastos!$J$9:$J$4091, Gastos!$L$9:$L$4091, $W$3, Gastos!$M$9:$M$4091, $W$4, Gastos!$D$9:$D$4091, Q29) -> 0 | X29: =SUMIFS(Gastos!$J$9:$J$4091, Gastos!$L$9:$L$4091, $X$3, Gastos!$M$9:$M$4091, $X$4, Gastos!$D$9:$D$4091, Q29) -> 0 | Y29: =SUMIFS(Gastos!$J$9:$J$4091, Gastos!$L$9:$L$4091, $Y$3, Gastos!$M$9:$M$4091, $Y$4, Gastos!$D$9:$D$4091, Q29) -> 0 | Z29: =SUMIFS(Gastos!$J$9:$J$4091, Gastos!$L$9:$L$4091, $Z$3, Gastos!$M$9:$M$4091, $Z$4, Gastos!$D$9:$D$4091, Q29) -> 0 | AA29: =SUMIFS(Gastos!$J$9:$J$4091, Gastos!$L$9:$L$4091, $AA$3, Gastos!$M$9:$M$4091, $AA$4, Gastos!$D$9:$D$4091, Q29) -> 0 | AB29: =SUMIFS(Gastos!$J$9:$J$4091, Gastos!$L$9:$L$4091, $AB$3, Gastos!$M$9:$M$4091, $AB$4, Gastos!$D$9:$D$4091, Q29) -> 0 | AC29: =SUMIFS(Gastos!$J$9:$J$4091, Gastos!$L$9:$L$4091, $AC$3, Gastos!$M$9:$M$4091, $AC$4, Gastos!$D$9:$D$4091, Q29) -> 0 | AD29: =SUM(R29:AC29) -> 0 | AK29: GASTOS | AL29: Presupuesto | AM29: Actual | AN29: Variación | AO29: Pre. Acumulativo | AP29: Gastos Acumulativos
B30: =#REF! -> #REF! | C30: =SUMIFS(Ingresos!$J$9:$J$3900, Ingresos!$L$9:$L$3900, $C$3, Ingresos!$M$9:$M$3900, $C$4, Ingresos!$D$9:$D$3900, B30) -> 0 | D30: =SUMIFS(Ingresos!$J$9:$J$3900, Ingresos!$L$9:$L$3900, $D$3, Ingresos!$M$9:$M$3900, $D$4, Ingresos!$D$9:$D$3900, B30) -> 0 | E30: =SUMIFS(Ingresos!$J$9:$J$3900, Ingresos!$L$9:$L$3900, $E$3, Ingresos!$M$9:$M$3900, $E$4, Ingresos!$D$9:$D$3900, B30) -> 0 | F30: =SUMIFS(Ingresos!$J$9:$J$3900, Ingresos!$L$9:$L$3900, $F$3, Ingresos!$M$9:$M$3900, $F$4, Ingresos!$D$9:$D$3900, B30) -> 0 | G30: =SUMIFS(Ingresos!$J$9:$J$3900, Ingresos!$L$9:$L$3900, $G$3, Ingresos!$M$9:$M$3900, $G$4, Ingresos!$D$9:$D$3900, B30) -> 0 | H30: =SUMIFS(Ingresos!$J$9:$J$3900, Ingresos!$L$9:$L$3900, $H$3, Ingresos!$M$9:$M$3900, $H$4, Ingresos!$D$9:$D$3900, B30) -> 0 | I30: =SUMIFS(Ingresos!$J$9:$J$3900, Ingresos!$L$9:$L$3900, $I$3, Ingresos!$M$9:$M$3900, $I$4, Ingresos!$D$9:$D$3900, B30) -> 0 | J30: =SUMIFS(Ingresos!$J$9:$J$3900, Ingresos!$L$9:$L$3900, $J$3, Ingresos!$M$9:$M$3900, $J$4, Ingresos!$D$9:$D$3900, B30) -> 0 | K30: =SUMIFS(Ingresos!$J$9:$J$3900, Ingresos!$L$9:$L$3900, $K$3, Ingresos!$M$9:$M$3900, $K$4, Ingresos!$D$9:$D$3900, B30) -> 0 | L30: =SUMIFS(Ingresos!$J$9:$J$3900, Ingresos!$L$9:$L$3900, $L$3, Ingresos!$M$9:$M$3900, $L$4, Ingresos!$D$9:$D$3900, B30) -> 0 | M30: =SUMIFS(Ingresos!$J$9:$J$3900, Ingresos!$L$9:$L$3900, $M$3, Ingresos!$M$9:$M$3900, $M$4, Ingresos!$D$9:$D$3900, B30) -> 0 | N30: =SUMIFS(Ingresos!$J$9:$J$3900, Ingresos!$L$9:$L$3900, $N$3, Ingresos!$M$9:$M$3900, $N$4, Ingresos!$D$9:$D$3900, B30) -> 0 | O30: =SUM(C30:N30) -> 0 | Q30: =#REF! -> #REF! | R30: =SUMIFS(Gastos!$J$9:$J$4091, Gastos!$L$9:$L$4091, $R$3, Gastos!$M$9:$M$4091, $R$4, Gastos!$D$9:$D$4091, Q30) -> 0 | S30: =SUMIFS(Gastos!$J$9:$J$4091, Gastos!$L$9:$L$4091, $S$3, Gastos!$M$9:$M$4091, $S$4, Gastos!$D$9:$D$4091, Q30) -> 0 | T30: =SUMIFS(Gastos!$J$9:$J$4091, Gastos!$L$9:$L$4091, $T$3, Gastos!$M$9:$M$4091, $T$4, Gastos!$D$9:$D$4091, Q30) -> 0 | U30: =SUMIFS(Gastos!$J$9:$J$4091, Gastos!$L$9:$L$4091, $U$3, Gastos!$M$9:$M$4091, $U$4, Gastos!$D$9:$D$4091, Q30) -> 0 | V30: =SUMIFS(Gastos!$J$9:$J$4091, Gastos!$L$9:$L$4091, $V$3, Gastos!$M$9:$M$4091, $V$4, Gastos!$D$9:$D$4091, Q30) -> 0 | W30: =SUMIFS(Gastos!$J$9:$J$4091, Gastos!$L$9:$L$4091, $W$3, Gastos!$M$9:$M$4091, $W$4, Gastos!$D$9:$D$4091, Q30) -> 0 | X30: =SUMIFS(Gastos!$J$9:$J$4091, Gastos!$L$9:$L$4091, $X$3, Gastos!$M$9:$M$4091, $X$4, Gastos!$D$9:$D$4091, Q30) -> 0 | Y30: =SUMIFS(Gastos!$J$9:$J$4091, Gastos!$L$9:$L$4091, $Y$3, Gastos!$M$9:$M$4091, $Y$4, Gastos!$D$9:$D$4091, Q30) -> 0 | Z30: =SUMIFS(Gastos!$J$9:$J$4091, Gastos!$L$9:$L$4091, $Z$3, Gastos!$M$9:$M$4091, $Z$4, Gastos!$D$9:$D$4091, Q30) -> 0 | AA30: =SUMIFS(Gastos!$J$9:$J$4091, Gastos!$L$9:$L$4091, $AA$3, Gastos!$M$9:$M$4091, $AA$4, Gastos!$D$9:$D$4091, Q30) -> 0 | AB30: =SUMIFS(Gastos!$J$9:$J$4091, Gastos!$L$9:$L$4091, $AB$3, Gastos!$M$9:$M$4091, $AB$4, Gastos!$D$9:$D$4091, Q30) -> 0 | AC30: =SUMIFS(Gastos!$J$9:$J$4091, Gastos!$L$9:$L$4091, $AC$3, Gastos!$M$9:$M$4091, $AC$4, Gastos!$D$9:$D$4091, Q30) -> 0 | AD30: =SUM(R30:AC30) -> 0 | AK30: =#REF! -> #REF! | AL30: =#REF! -> #REF! | AM30: =#REF! -> #REF! | AN30: =AL30-AM30 -> #REF! | AO30: =AL30 -> #REF! | AP30: =AM30 -> #REF!
B31: =#REF! -> #REF! | C31: =SUMIFS(Ingresos!$J$9:$J$3900, Ingresos!$L$9:$L$3900, $C$3, Ingresos!$M$9:$M$3900, $C$4, Ingresos!$D$9:$D$3900, B31) -> 0 | D31: =SUMIFS(Ingresos!$J$9:$J$3900, Ingresos!$L$9:$L$3900, $D$3, Ingresos!$M$9:$M$3900, $D$4, Ingresos!$D$9:$D$3900, B31) -> 0 | E31: =SUMIFS(Ingresos!$J$9:$J$3900, Ingresos!$L$9:$L$3900, $E$3, Ingresos!$M$9:$M$3900, $E$4, Ingresos!$D$9:$D$3900, B31) -> 0 | F31: =SUMIFS(Ingresos!$J$9:$J$3900, Ingresos!$L$9:$L$3900, $F$3, Ingresos!$M$9:$M$3900, $F$4, Ingresos!$D$9:$D$3900, B31) -> 0 | G31: =SUMIFS(Ingresos!$J$9:$J$3900, Ingresos!$L$9:$L$3900, $G$3, Ingresos!$M$9:$M$3900, $G$4, Ingresos!$D$9:$D$3900, B31) -> 0 | H31: =SUMIFS(Ingresos!$J$9:$J$3900, Ingresos!$L$9:$L$3900, $H$3, Ingresos!$M$9:$M$3900, $H$4, Ingresos!$D$9:$D$3900, B31) -> 0 | I31: =SUMIFS(Ingresos!$J$9:$J$3900, Ingresos!$L$9:$L$3900, $I$3, Ingresos!$M$9:$M$3900, $I$4, Ingresos!$D$9:$D$3900, B31) -> 0 | J31: =SUMIFS(Ingresos!$J$9:$J$3900, Ingresos!$L$9:$L$3900, $J$3, Ingresos!$M$9:$M$3900, $J$4, Ingresos!$D$9:$D$3900, B31) -> 0 | K31: =SUMIFS(Ingresos!$J$9:$J$3900, Ingresos!$L$9:$L$3900, $K$3, Ingresos!$M$9:$M$3900, $K$4, Ingresos!$D$9:$D$3900, B31) -> 0 | L31: =SUMIFS(Ingresos!$J$9:$J$3900, Ingresos!$L$9:$L$3900, $L$3, Ingresos!$M$9:$M$3900, $L$4, Ingresos!$D$9:$D$3900, B31) -> 0 | M31: =SUMIFS(Ingresos!$J$9:$J$3900, Ingresos!$L$9:$L$3900, $M$3, Ingresos!$M$9:$M$3900, $M$4, Ingresos!$D$9:$D$3900, B31) -> 0 | N31: =SUMIFS(Ingresos!$J$9:$J$3900, Ingresos!$L$9:$L$3900, $N$3, Ingresos!$M$9:$M$3900, $N$4, Ingresos!$D$9:$D$3900, B31) -> 0 | O31: =SUM(C31:N31) -> 0 | Q31: =#REF! -> #REF! | R31: =SUMIFS(Gastos!$J$9:$J$4091, Gastos!$L$9:$L$4091, $R$3, Gastos!$M$9:$M$4091, $R$4, Gastos!$D$9:$D$4091, Q31) -> 0 | S31: =SUMIFS(Gastos!$J$9:$J$4091, Gastos!$L$9:$L$4091, $S$3, Gastos!$M$9:$M$4091, $S$4, Gastos!$D$9:$D$4091, Q31) -> 0 | T31: =SUMIFS(Gastos!$J$9:$J$4091, Gastos!$L$9:$L$4091, $T$3, Gastos!$M$9:$M$4091, $T$4, Gastos!$D$9:$D$4091, Q31) -> 0 | U31: =SUMIFS(Gastos!$J$9:$J$4091, Gastos!$L$9:$L$4091, $U$3, Gastos!$M$9:$M$4091, $U$4, Gastos!$D$9:$D$4091, Q31) -> 0 | V31: =SUMIFS(Gastos!$J$9:$J$4091, Gastos!$L$9:$L$4091, $V$3, Gastos!$M$9:$M$4091, $V$4, Gastos!$D$9:$D$4091, Q31) -> 0 | W31: =SUMIFS(Gastos!$J$9:$J$4091, Gastos!$L$9:$L$4091, $W$3, Gastos!$M$9:$M$4091, $W$4, Gastos!$D$9:$D$4091, Q31) -> 0 | X31: =SUMIFS(Gastos!$J$9:$J$4091, Gastos!$L$9:$L$4091, $X$3, Gastos!$M$9:$M$4091, $X$4, Gastos!$D$9:$D$4091, Q31) -> 0 | Y31: =SUMIFS(Gastos!$J$9:$J$4091, Gastos!$L$9:$L$4091, $Y$3, Gastos!$M$9:$M$4091, $Y$4, Gastos!$D$9:$D$4091, Q31) -> 0 | Z31: =SUMIFS(Gastos!$J$9:$J$4091, Gastos!$L$9:$L$4091, $Z$3, Gastos!$M$9:$M$4091, $Z$4, Gastos!$D$9:$D$4091, Q31) -> 0 | AA31: =SUMIFS(Gastos!$J$9:$J$4091, Gastos!$L$9:$L$4091, $AA$3, Gastos!$M$9:$M$4091, $AA$4, Gastos!$D$9:$D$4091, Q31) -> 0 | AB31: =SUMIFS(Gastos!$J$9:$J$4091, Gastos!$L$9:$L$4091, $AB$3, Gastos!$M$9:$M$4091, $AB$4, Gastos!$D$9:$D$4091, Q31) -> 0 | AC31: =SUMIFS(Gastos!$J$9:$J$4091, Gastos!$L$9:$L$4091, $AC$3, Gastos!$M$9:$M$4091, $AC$4, Gastos!$D$9:$D$4091, Q31) -> 0 | AD31: =SUM(R31:AC31) -> 0 | AK31: =#REF! -> #REF! | AL31: =#REF! -> #REF! | AM31: =#REF! -> #REF! | AN31: =AL31-AM31 -> #REF! | AO31: =AO30+AL31 -> #REF! | AP31: =AP30+AM31 -> #REF!
B32: =#REF! -> #REF! | C32: =SUMIFS(Ingresos!$J$9:$J$3900, Ingresos!$L$9:$L$3900, $C$3, Ingresos!$M$9:$M$3900, $C$4, Ingresos!$D$9:$D$3900, B32) -> 0 | D32: =SUMIFS(Ingresos!$J$9:$J$3900, Ingresos!$L$9:$L$3900, $D$3, Ingresos!$M$9:$M$3900, $D$4, Ingresos!$D$9:$D$3900, B32) -> 0 | E32: =SUMIFS(Ingresos!$J$9:$J$3900, Ingresos!$L$9:$L$3900, $E$3, Ingresos!$M$9:$M$3900, $E$4, Ingresos!$D$9:$D$3900, B32) -> 0 | F32: =SUMIFS(Ingresos!$J$9:$J$3900, Ingresos!$L$9:$L$3900, $F$3, Ingresos!$M$9:$M$3900, $F$4, Ingresos!$D$9:$D$3900, B32) -> 0 | G32: =SUMIFS(Ingresos!$J$9:$J$3900, Ingresos!$L$9:$L$3900, $G$3, Ingresos!$M$9:$M$3900, $G$4, Ingresos!$D$9:$D$3900, B32) -> 0 | H32: =SUMIFS(Ingresos!$J$9:$J$3900, Ingresos!$L$9:$L$3900, $H$3, Ingresos!$M$9:$M$3900, $H$4, Ingresos!$D$9:$D$3900, B32) -> 0 | I32: =SUMIFS(Ingresos!$J$9:$J$3900, Ingresos!$L$9:$L$3900, $I$3, Ingresos!$M$9:$M$3900, $I$4, Ingresos!$D$9:$D$3900, B32) -> 0 | J32: =SUMIFS(Ingresos!$J$9:$J$3900, Ingresos!$L$9:$L$3900, $J$3, Ingresos!$M$9:$M$3900, $J$4, Ingresos!$D$9:$D$3900, B32) -> 0 | K32: =SUMIFS(Ingresos!$J$9:$J$3900, Ingresos!$L$9:$L$3900, $K$3, Ingresos!$M$9:$M$3900, $K$4, Ingresos!$D$9:$D$3900, B32) -> 0 | L32: =SUMIFS(Ingresos!$J$9:$J$3900, Ingresos!$L$9:$L$3900, $L$3, Ingresos!$M$9:$M$3900, $L$4, Ingresos!$D$9:$D$3900, B32) -> 0 | M32: =SUMIFS(Ingresos!$J$9:$J$3900, Ingresos!$L$9:$L$3900, $M$3, Ingresos!$M$9:$M$3900, $M$4, Ingresos!$D$9:$D$3900, B32) -> 0 | N32: =SUMIFS(Ingresos!$J$9:$J$3900, Ingresos!$L$9:$L$3900, $N$3, Ingresos!$M$9:$M$3900, $N$4, Ingresos!$D$9:$D$3900, B32) -> 0 | O32: =SUM(C32:N32) -> 0 | Q32: =#REF! -> #REF! | R32: =SUMIFS(Gastos!$J$9:$J$4091, Gastos!$L$9:$L$4091, $R$3, Gastos!$M$9:$M$4091, $R$4, Gastos!$D$9:$D$4091, Q32) -> 0 | S32: =SUMIFS(Gastos!$J$9:$J$4091, Gastos!$L$9:$L$4091, $S$3, Gastos!$M$9:$M$4091, $S$4, Gastos!$D$9:$D$4091, Q32) -> 0 | T32: =SUMIFS(Gastos!$J$9:$J$4091, Gastos!$L$9:$L$4091, $T$3, Gastos!$M$9:$M$4091, $T$4, Gastos!$D$9:$D$4091, Q32) -> 0 | U32: =SUMIFS(Gastos!$J$9:$J$4091, Gastos!$L$9:$L$4091, $U$3, Gastos!$M$9:$M$4091, $U$4, Gastos!$D$9:$D$4091, Q32) -> 0 | V32: =SUMIFS(Gastos!$J$9:$J$4091, Gastos!$L$9:$L$4091, $V$3, Gastos!$M$9:$M$4091, $V$4, Gastos!$D$9:$D$4091, Q32) -> 0 | W32: =SUMIFS(Gastos!$J$9:$J$4091, Gastos!$L$9:$L$4091, $W$3, Gastos!$M$9:$M$4091, $W$4, Gastos!$D$9:$D$4091, Q32) -> 0 | X32: =SUMIFS(Gastos!$J$9:$J$4091, Gastos!$L$9:$L$4091, $X$3, Gastos!$M$9:$M$4091, $X$4, Gastos!$D$9:$D$4091, Q32) -> 0 | Y32: =SUMIFS(Gastos!$J$9:$J$4091, Gastos!$L$9:$L$4091, $Y$3, Gastos!$M$9:$M$4091, $Y$4, Gastos!$D$9:$D$4091, Q32) -> 0 | Z32: =SUMIFS(Gastos!$J$9:$J$4091, Gastos!$L$9:$L$4091, $Z$3, Gastos!$M$9:$M$4091, $Z$4, Gastos!$D$9:$D$4091, Q32) -> 0 | AA32: =SUMIFS(Gastos!$J$9:$J$4091, Gastos!$L$9:$L$4091, $AA$3, Gastos!$M$9:$M$4091, $AA$4, Gastos!$D$9:$D$4091, Q32) -> 0 | AB32: =SUMIFS(Gastos!$J$9:$J$4091, Gastos!$L$9:$L$4091, $AB$3, Gastos!$M$9:$M$4091, $AB$4, Gastos!$D$9:$D$4091, Q32) -> 0 | AC32: =SUMIFS(Gastos!$J$9:$J$4091, Gastos!$L$9:$L$4091, $AC$3, Gastos!$M$9:$M$4091, $AC$4, Gastos!$D$9:$D$4091, Q32) -> 0 | AD32: =SUM(R32:AC32) -> 0 | AK32: =#REF! -> #REF! | AL32: =#REF! -> #REF! | AM32: =#REF! -> #REF! | AN32: =AL32-AM32 -> #REF! | AO32: =AO31+AL32 -> #REF! | AP32: =AP31+AM32 -> #REF!
B33: =#REF! -> #REF! | C33: =SUMIFS(Ingresos!$J$9:$J$3900, Ingresos!$L$9:$L$3900, $C$3, Ingresos!$M$9:$M$3900, $C$4, Ingresos!$D$9:$D$3900, B33) -> 0 | D33: =SUMIFS(Ingresos!$J$9:$J$3900, Ingresos!$L$9:$L$3900, $D$3, Ingresos!$M$9:$M$3900, $D$4, Ingresos!$D$9:$D$3900, B33) -> 0 | E33: =SUMIFS(Ingresos!$J$9:$J$3900, Ingresos!$L$9:$L$3900, $E$3, Ingresos!$M$9:$M$3900, $E$4, Ingresos!$D$9:$D$3900, B33) -> 0 | F33: =SUMIFS(Ingresos!$J$9:$J$3900, Ingresos!$L$9:$L$3900, $F$3, Ingresos!$M$9:$M$3900, $F$4, Ingresos!$D$9:$D$3900, B33) -> 0 | G33: =SUMIFS(Ingresos!$J$9:$J$3900, Ingresos!$L$9:$L$3900, $G$3, Ingresos!$M$9:$M$3900, $G$4, Ingresos!$D$9:$D$3900, B33) -> 0 | H33: =SUMIFS(Ingresos!$J$9:$J$3900, Ingresos!$L$9:$L$3900, $H$3, Ingresos!$M$9:$M$3900, $H$4, Ingresos!$D$9:$D$3900, B33) -> 0 | I33: =SUMIFS(Ingresos!$J$9:$J$3900, Ingresos!$L$9:$L$3900, $I$3, Ingresos!$M$9:$M$3900, $I$4, Ingresos!$D$9:$D$3900, B33) -> 0 | J33: =SUMIFS(Ingresos!$J$9:$J$3900, Ingresos!$L$9:$L$3900, $J$3, Ingresos!$M$9:$M$3900, $J$4, Ingresos!$D$9:$D$3900, B33) -> 0 | K33: =SUMIFS(Ingresos!$J$9:$J$3900, Ingresos!$L$9:$L$3900, $K$3, Ingresos!$M$9:$M$3900, $K$4, Ingresos!$D$9:$D$3900, B33) -> 0 | L33: =SUMIFS(Ingresos!$J$9:$J$3900, Ingresos!$L$9:$L$3900, $L$3, Ingresos!$M$9:$M$3900, $L$4, Ingresos!$D$9:$D$3900, B33) -> 0 | M33: =SUMIFS(Ingresos!$J$9:$J$3900, Ingresos!$L$9:$L$3900, $M$3, Ingresos!$M$9:$M$3900, $M$4, Ingresos!$D$9:$D$3900, B33) -> 0 | N33: =SUMIFS(Ingresos!$J$9:$J$3900, Ingresos!$L$9:$L$3900, $N$3, Ingresos!$M$9:$M$3900, $N$4, Ingresos!$D$9:$D$3900, B33) -> 0 | O33: =SUM(C33:N33) -> 0 | Q33: =#REF! -> #REF! | R33: =SUMIFS(Gastos!$J$9:$J$4091, Gastos!$L$9:$L$4091, $R$3, Gastos!$M$9:$M$4091, $R$4, Gastos!$D$9:$D$4091, Q33) -> 0 | S33: =SUMIFS(Gastos!$J$9:$J$4091, Gastos!$L$9:$L$4091, $S$3, Gastos!$M$9:$M$4091, $S$4, Gastos!$D$9:$D$4091, Q33) -> 0 | T33: =SUMIFS(Gastos!$J$9:$J$4091, Gastos!$L$9:$L$4091, $T$3, Gastos!$M$9:$M$4091, $T$4, Gastos!$D$9:$D$4091, Q33) -> 0 | U33: =SUMIFS(Gastos!$J$9:$J$4091, Gastos!$L$9:$L$4091, $U$3, Gastos!$M$9:$M$4091, $U$4, Gastos!$D$9:$D$4091, Q33) -> 0 | V33: =SUMIFS(Gastos!$J$9:$J$4091, Gastos!$L$9:$L$4091, $V$3, Gastos!$M$9:$M$4091, $V$4, Gastos!$D$9:$D$4091, Q33) -> 0 | W33: =SUMIFS(Gastos!$J$9:$J$4091, Gastos!$L$9:$L$4091, $W$3, Gastos!$M$9:$M$4091, $W$4, Gastos!$D$9:$D$4091, Q33) -> 0 | X33: =SUMIFS(Gastos!$J$9:$J$4091, Gastos!$L$9:$L$4091, $X$3, Gastos!$M$9:$M$4091, $X$4, Gastos!$D$9:$D$4091, Q33) -> 0 | Y33: =SUMIFS(Gastos!$J$9:$J$4091, Gastos!$L$9:$L$4091, $Y$3, Gastos!$M$9:$M$4091, $Y$4, Gastos!$D$9:$D$4091, Q33) -> 0 | Z33: =SUMIFS(Gastos!$J$9:$J$4091, Gastos!$L$9:$L$4091, $Z$3, Gastos!$M$9:$M$4091, $Z$4, Gastos!$D$9:$D$4091, Q33) -> 0 | AA33: =SUMIFS(Gastos!$J$9:$J$4091, Gastos!$L$9:$L$4091, $AA$3, Gastos!$M$9:$M$4091, $AA$4, Gastos!$D$9:$D$4091, Q33) -> 0 | AB33: =SUMIFS(Gastos!$J$9:$J$4091, Gastos!$L$9:$L$4091, $AB$3, Gastos!$M$9:$M$4091, $AB$4, Gastos!$D$9:$D$4091, Q33) -> 0 | AC33: =SUMIFS(Gastos!$J$9:$J$4091, Gastos!$L$9:$L$4091, $AC$3, Gastos!$M$9:$M$4091, $AC$4, Gastos!$D$9:$D$4091, Q33) -> 0 | AD33: =SUM(R33:AC33) -> 0 | AK33: =#REF! -> #REF! | AL33: =#REF! -> #REF! | AM33: =#REF! -> #REF! | AN33: =AL33-AM33 -> #REF! | AO33: =AO32+AL33 -> #REF! | AP33: =AP32+AM33 -> #REF!
B34: =#REF! -> #REF! | C34: =SUMIFS(Ingresos!$J$9:$J$3900, Ingresos!$L$9:$L$3900, $C$3, Ingresos!$M$9:$M$3900, $C$4, Ingresos!$D$9:$D$3900, B34) -> 0 | D34: =SUMIFS(Ingresos!$J$9:$J$3900, Ingresos!$L$9:$L$3900, $D$3, Ingresos!$M$9:$M$3900, $D$4, Ingresos!$D$9:$D$3900, B34) -> 0 | E34: =SUMIFS(Ingresos!$J$9:$J$3900, Ingresos!$L$9:$L$3900, $E$3, Ingresos!$M$9:$M$3900, $E$4, Ingresos!$D$9:$D$3900, B34) -> 0 | F34: =SUMIFS(Ingresos!$J$9:$J$3900, Ingresos!$L$9:$L$3900, $F$3, Ingresos!$M$9:$M$3900, $F$4, Ingresos!$D$9:$D$3900, B34) -> 0 | G34: =SUMIFS(Ingresos!$J$9:$J$3900, Ingresos!$L$9:$L$3900, $G$3, Ingresos!$M$9:$M$3900, $G$4, Ingresos!$D$9:$D$3900, B34) -> 0 | H34: =SUMIFS(Ingresos!$J$9:$J$3900, Ingresos!$L$9:$L$3900, $H$3, Ingresos!$M$9:$M$3900, $H$4, Ingresos!$D$9:$D$3900, B34) -> 0 | I34: =SUMIFS(Ingresos!$J$9:$J$3900, Ingresos!$L$9:$L$3900, $I$3, Ingresos!$M$9:$M$3900, $I$4, Ingresos!$D$9:$D$3900, B34) -> 0 | J34: =SUMIFS(Ingresos!$J$9:$J$3900, Ingresos!$L$9:$L$3900, $J$3, Ingresos!$M$9:$M$3900, $J$4, Ingresos!$D$9:$D$3900, B34) -> 0 | K34: =SUMIFS(Ingresos!$J$9:$J$3900, Ingresos!$L$9:$L$3900, $K$3, Ingresos!$M$9:$M$3900, $K$4, Ingresos!$D$9:$D$3900, B34) -> 0 | L34: =SUMIFS(Ingresos!$J$9:$J$3900, Ingresos!$L$9:$L$3900, $L$3, Ingresos!$M$9:$M$3900, $L$4, Ingresos!$D$9:$D$3900, B34) -> 0 | M34: =SUMIFS(Ingresos!$J$9:$J$3900, Ingresos!$L$9:$L$3900, $M$3, Ingresos!$M$9:$M$3900, $M$4, Ingresos!$D$9:$D$3900, B34) -> 0 | N34: =SUMIFS(Ingresos!$J$9:$J$3900, Ingresos!$L$9:$L$3900, $N$3, Ingresos!$M$9:$M$3900, $N$4, Ingresos!$D$9:$D$3900, B34) -> 0 | O34: =SUM(C34:N34) -> 0 | Q34: =#REF! -> #REF! | R34: =SUMIFS(Gastos!$J$9:$J$4091, Gastos!$L$9:$L$4091, $R$3, Gastos!$M$9:$M$4091, $R$4, Gastos!$D$9:$D$4091, Q34) -> 0 | S34: =SUMIFS(Gastos!$J$9:$J$4091, Gastos!$L$9:$L$4091, $S$3, Gastos!$M$9:$M$4091, $S$4, Gastos!$D$9:$D$4091, Q34) -> 0 | T34: =SUMIFS(Gastos!$J$9:$J$4091, Gastos!$L$9:$L$4091, $T$3, Gastos!$M$9:$M$4091, $T$4, Gastos!$D$9:$D$4091, Q34) -> 0 | U34: =SUMIFS(Gastos!$J$9:$J$4091, Gastos!$L$9:$L$4091, $U$3, Gastos!$M$9:$M$4091, $U$4, Gastos!$D$9:$D$4091, Q34) -> 0 | V34: =SUMIFS(Gastos!$J$9:$J$4091, Gastos!$L$9:$L$4091, $V$3, Gastos!$M$9:$M$4091, $V$4, Gastos!$D$9:$D$4091, Q34) -> 0 | W34: =SUMIFS(Gastos!$J$9:$J$4091, Gastos!$L$9:$L$4091, $W$3, Gastos!$M$9:$M$4091, $W$4, Gastos!$D$9:$D$4091, Q34) -> 0 | X34: =SUMIFS(Gastos!$J$9:$J$4091, Gastos!$L$9:$L$4091, $X$3, Gastos!$M$9:$M$4091, $X$4, Gastos!$D$9:$D$4091, Q34) -> 0 | Y34: =SUMIFS(Gastos!$J$9:$J$4091, Gastos!$L$9:$L$4091, $Y$3, Gastos!$M$9:$M$4091, $Y$4, Gastos!$D$9:$D$4091, Q34) -> 0 | Z34: =SUMIFS(Gastos!$J$9:$J$4091, Gastos!$L$9:$L$4091, $Z$3, Gastos!$M$9:$M$4091, $Z$4, Gastos!$D$9:$D$4091, Q34) -> 0 | AA34: =SUMIFS(Gastos!$J$9:$J$4091, Gastos!$L$9:$L$4091, $AA$3, Gastos!$M$9:$M$4091, $AA$4, Gastos!$D$9:$D$4091, Q34) -> 0 | AB34: =SUMIFS(Gastos!$J$9:$J$4091, Gastos!$L$9:$L$4091, $AB$3, Gastos!$M$9:$M$4091, $AB$4, Gastos!$D$9:$D$4091, Q34) -> 0 | AC34: =SUMIFS(Gastos!$J$9:$J$4091, Gastos!$L$9:$L$4091, $AC$3, Gastos!$M$9:$M$4091, $AC$4, Gastos!$D$9:$D$4091, Q34) -> 0 | AD34: =SUM(R34:AC34) -> 0 | AK34: =#REF! -> #REF! | AL34: =#REF! -> #REF! | AM34: =#REF! -> #REF! | AN34: =AL34-AM34 -> #REF! | AO34: =AO33+AL34 -> #REF! | AP34: =AP33+AM34 -> #REF!
B35: =#REF! -> #REF! | C35: =SUMIFS(Ingresos!$J$9:$J$3900, Ingresos!$L$9:$L$3900, $C$3, Ingresos!$M$9:$M$3900, $C$4, Ingresos!$D$9:$D$3900, B35) -> 0 | D35: =SUMIFS(Ingresos!$J$9:$J$3900, Ingresos!$L$9:$L$3900, $D$3, Ingresos!$M$9:$M$3900, $D$4, Ingresos!$D$9:$D$3900, B35) -> 0 | E35: =SUMIFS(Ingresos!$J$9:$J$3900, Ingresos!$L$9:$L$3900, $E$3, Ingresos!$M$9:$M$3900, $E$4, Ingresos!$D$9:$D$3900, B35) -> 0 | F35: =SUMIFS(Ingresos!$J$9:$J$3900, Ingresos!$L$9:$L$3900, $F$3, Ingresos!$M$9:$M$3900, $F$4, Ingresos!$D$9:$D$3900, B35) -> 0 | G35: =SUMIFS(Ingresos!$J$9:$J$3900, Ingresos!$L$9:$L$3900, $G$3, Ingresos!$M$9:$M$3900, $G$4, Ingresos!$D$9:$D$3900, B35) -> 0 | H35: =SUMIFS(Ingresos!$J$9:$J$3900, Ingresos!$L$9:$L$3900, $H$3, Ingresos!$M$9:$M$3900, $H$4, Ingresos!$D$9:$D$3900, B35) -> 0 | I35: =SUMIFS(Ingresos!$J$9:$J$3900, Ingresos!$L$9:$L$3900, $I$3, Ingresos!$M$9:$M$3900, $I$4, Ingresos!$D$9:$D$3900, B35) -> 0 | J35: =SUMIFS(Ingresos!$J$9:$J$3900, Ingresos!$L$9:$L$3900, $J$3, Ingresos!$M$9:$M$3900, $J$4, Ingresos!$D$9:$D$3900, B35) -> 0 | K35: =SUMIFS(Ingresos!$J$9:$J$3900, Ingresos!$L$9:$L$3900, $K$3, Ingresos!$M$9:$M$3900, $K$4, Ingresos!$D$9:$D$3900, B35) -> 0 | L35: =SUMIFS(Ingresos!$J$9:$J$3900, Ingresos!$L$9:$L$3900, $L$3, Ingresos!$M$9:$M$3900, $L$4, Ingresos!$D$9:$D$3900, B35) -> 0 | M35: =SUMIFS(Ingresos!$J$9:$J$3900, Ingresos!$L$9:$L$3900, $M$3, Ingresos!$M$9:$M$3900, $M$4, Ingresos!$D$9:$D$3900, B35) -> 0 | N35: =SUMIFS(Ingresos!$J$9:$J$3900, Ingresos!$L$9:$L$3900, $N$3, Ingresos!$M$9:$M$3900, $N$4, Ingresos!$D$9:$D$3900, B35) -> 0 | O35: =SUM(C35:N35) -> 0 | Q35: =#REF! -> #REF! | R35: =SUMIFS(Gastos!$J$9:$J$4091, Gastos!$L$9:$L$4091, $R$3, Gastos!$M$9:$M$4091, $R$4, Gastos!$D$9:$D$4091, Q35) -> 0 | S35: =SUMIFS(Gastos!$J$9:$J$4091, Gastos!$L$9:$L$4091, $S$3, Gastos!$M$9:$M$4091, $S$4, Gastos!$D$9:$D$4091, Q35) -> 0 | T35: =SUMIFS(Gastos!$J$9:$J$4091, Gastos!$L$9:$L$4091, $T$3, Gastos!$M$9:$M$4091, $T$4, Gastos!$D$9:$D$4091, Q35) -> 0 | U35: =SUMIFS(Gastos!$J$9:$J$4091, Gastos!$L$9:$L$4091, $U$3, Gastos!$M$9:$M$4091, $U$4, Gastos!$D$9:$D$4091, Q35) -> 0 | V35: =SUMIFS(Gastos!$J$9:$J$4091, Gastos!$L$9:$L$4091, $V$3, Gastos!$M$9:$M$4091, $V$4, Gastos!$D$9:$D$4091, Q35) -> 0 | W35: =SUMIFS(Gastos!$J$9:$J$4091, Gastos!$L$9:$L$4091, $W$3, Gastos!$M$9:$M$4091, $W$4, Gastos!$D$9:$D$4091, Q35) -> 0 | X35: =SUMIFS(Gastos!$J$9:$J$4091, Gastos!$L$9:$L$4091, $X$3, Gastos!$M$9:$M$4091, $X$4, Gastos!$D$9:$D$4091, Q35) -> 0 | Y35: =SUMIFS(Gastos!$J$9:$J$4091, Gastos!$L$9:$L$4091, $Y$3, Gastos!$M$9:$M$4091, $Y$4, Gastos!$D$9:$D$4091, Q35) -> 0 | Z35: =SUMIFS(Gastos!$J$9:$J$4091, Gastos!$L$9:$L$4091, $Z$3, Gastos!$M$9:$M$4091, $Z$4, Gastos!$D$9:$D$4091, Q35) -> 0 | AA35: =SUMIFS(Gastos!$J$9:$J$4091, Gastos!$L$9:$L$4091, $AA$3, Gastos!$M$9:$M$4091, $AA$4, Gastos!$D$9:$D$4091, Q35) -> 0 | AB35: =SUMIFS(Gastos!$J$9:$J$4091, Gastos!$L$9:$L$4091, $AB$3, Gastos!$M$9:$M$4091, $AB$4, Gastos!$D$9:$D$4091, Q35) -> 0 | AC35: =SUMIFS(Gastos!$J$9:$J$4091, Gastos!$L$9:$L$4091, $AC$3, Gastos!$M$9:$M$4091, $AC$4, Gastos!$D$9:$D$4091, Q35) -> 0 | AD35: =SUM(R35:AC35) -> 0 | AK35: =#REF! -> #REF! | AL35: =#REF! -> #REF! | AM35: =#REF! -> #REF! | AN35: =AL35-AM35 -> #REF! | AO35: =AO34+AL35 -> #REF! | AP35: =AP34+AM35 -> #REF!
B36: =#REF! -> #REF! | C36: =SUMIFS(Ingresos!$J$9:$J$3900, Ingresos!$L$9:$L$3900, $C$3, Ingresos!$M$9:$M$3900, $C$4, Ingresos!$D$9:$D$3900, B36) -> 0 | D36: =SUMIFS(Ingresos!$J$9:$J$3900, Ingresos!$L$9:$L$3900, $D$3, Ingresos!$M$9:$M$3900, $D$4, Ingresos!$D$9:$D$3900, B36) -> 0 | E36: =SUMIFS(Ingresos!$J$9:$J$3900, Ingresos!$L$9:$L$3900, $E$3, Ingresos!$M$9:$M$3900, $E$4, Ingresos!$D$9:$D$3900, B36) -> 0 | F36: =SUMIFS(Ingresos!$J$9:$J$3900, Ingresos!$L$9:$L$3900, $F$3, Ingresos!$M$9:$M$3900, $F$4, Ingresos!$D$9:$D$3900, B36) -> 0 | G36: =SUMIFS(Ingresos!$J$9:$J$3900, Ingresos!$L$9:$L$3900, $G$3, Ingresos!$M$9:$M$3900, $G$4, Ingresos!$D$9:$D$3900, B36) -> 0 | H36: =SUMIFS(Ingresos!$J$9:$J$3900, Ingresos!$L$9:$L$3900, $H$3, Ingresos!$M$9:$M$3900, $H$4, Ingresos!$D$9:$D$3900, B36) -> 0 | I36: =SUMIFS(Ingresos!$J$9:$J$3900, Ingresos!$L$9:$L$3900, $I$3, Ingresos!$M$9:$M$3900, $I$4, Ingresos!$D$9:$D$3900, B36) -> 0 | J36: =SUMIFS(Ingresos!$J$9:$J$3900, Ingresos!$L$9:$L$3900, $J$3, Ingresos!$M$9:$M$3900, $J$4, Ingresos!$D$9:$D$3900, B36) -> 0 | K36: =SUMIFS(Ingresos!$J$9:$J$3900, Ingresos!$L$9:$L$3900, $K$3, Ingresos!$M$9:$M$3900, $K$4, Ingresos!$D$9:$D$3900, B36) -> 0 | L36: =SUMIFS(Ingresos!$J$9:$J$3900, Ingresos!$L$9:$L$3900, $L$3, Ingresos!$M$9:$M$3900, $L$4, Ingresos!$D$9:$D$3900, B36) -> 0 | M36: =SUMIFS(Ingresos!$J$9:$J$3900, Ingresos!$L$9:$L$3900, $M$3, Ingresos!$M$9:$M$3900, $M$4, Ingresos!$D$9:$D$3900, B36) -> 0 | N36: =SUMIFS(Ingresos!$J$9:$J$3900, Ingresos!$L$9:$L$3900, $N$3, Ingresos!$M$9:$M$3900, $N$4, Ingresos!$D$9:$D$3900, B36) -> 0 | O36: =SUM(C36:N36) -> 0 | Q36: =#REF! -> #REF! | R36: =SUMIFS(Gastos!$J$9:$J$4091, Gastos!$L$9:$L$4091, $R$3, Gastos!$M$9:$M$4091, $R$4, Gastos!$D$9:$D$4091, Q36) -> 0 | S36: =SUMIFS(Gastos!$J$9:$J$4091, Gastos!$L$9:$L$4091, $S$3, Gastos!$M$9:$M$4091, $S$4, Gastos!$D$9:$D$4091, Q36) -> 0 | T36: =SUMIFS(Gastos!$J$9:$J$4091, Gastos!$L$9:$L$4091, $T$3, Gastos!$M$9:$M$4091, $T$4, Gastos!$D$9:$D$4091, Q36) -> 0 | U36: =SUMIFS(Gastos!$J$9:$J$4091, Gastos!$L$9:$L$4091, $U$3, Gastos!$M$9:$M$4091, $U$4, Gastos!$D$9:$D$4091, Q36) -> 0 | V36: =SUMIFS(Gastos!$J$9:$J$4091, Gastos!$L$9:$L$4091, $V$3, Gastos!$M$9:$M$4091, $V$4, Gastos!$D$9:$D$4091, Q36) -> 0 | W36: =SUMIFS(Gastos!$J$9:$J$4091, Gastos!$L$9:$L$4091, $W$3, Gastos!$M$9:$M$4091, $W$4, Gastos!$D$9:$D$4091, Q36) -> 0 | X36: =SUMIFS(Gastos!$J$9:$J$4091, Gastos!$L$9:$L$4091, $X$3, Gastos!$M$9:$M$4091, $X$4, Gastos!$D$9:$D$4091, Q36) -> 0 | Y36: =SUMIFS(Gastos!$J$9:$J$4091, Gastos!$L$9:$L$4091, $Y$3, Gastos!$M$9:$M$4091, $Y$4, Gastos!$D$9:$D$4091, Q36) -> 0 | Z36: =SUMIFS(Gastos!$J$9:$J$4091, Gastos!$L$9:$L$4091, $Z$3, Gastos!$M$9:$M$4091, $Z$4, Gastos!$D$9:$D$4091, Q36) -> 0 | AA36: =SUMIFS(Gastos!$J$9:$J$4091, Gastos!$L$9:$L$4091, $AA$3, Gastos!$M$9:$M$4091, $AA$4, Gastos!$D$9:$D$4091, Q36) -> 0 | AB36: =SUMIFS(Gastos!$J$9:$J$4091, Gastos!$L$9:$L$4091, $AB$3, Gastos!$M$9:$M$4091, $AB$4, Gastos!$D$9:$D$4091, Q36) -> 0 | AC36: =SUMIFS(Gastos!$J$9:$J$4091, Gastos!$L$9:$L$4091, $AC$3, Gastos!$M$9:$M$4091, $AC$4, Gastos!$D$9:$D$4091, Q36) -> 0 | AD36: =SUM(R36:AC36) -> 0 | AK36: =#REF! -> #REF! | AL36: =#REF! -> #REF! | AM36: =#REF! -> #REF! | AN36: =AL36-AM36 -> #REF! | AO36: =AO35+AL36 -> #REF! | AP36: =AP35+AM36 -> #REF!
B37: =#REF! -> #REF! | C37: =SUMIFS(Ingresos!$J$9:$J$3900, Ingresos!$L$9:$L$3900, $C$3, Ingresos!$M$9:$M$3900, $C$4, Ingresos!$D$9:$D$3900, B37) -> 0 | D37: =SUMIFS(Ingresos!$J$9:$J$3900, Ingresos!$L$9:$L$3900, $D$3, Ingresos!$M$9:$M$3900, $D$4, Ingresos!$D$9:$D$3900, B37) -> 0 | E37: =SUMIFS(Ingresos!$J$9:$J$3900, Ingresos!$L$9:$L$3900, $E$3, Ingresos!$M$9:$M$3900, $E$4, Ingresos!$D$9:$D$3900, B37) -> 0 | F37: =SUMIFS(Ingresos!$J$9:$J$3900, Ingresos!$L$9:$L$3900, $F$3, Ingresos!$M$9:$M$3900, $F$4, Ingresos!$D$9:$D$3900, B37) -> 0 | G37: =SUMIFS(Ingresos!$J$9:$J$3900, Ingresos!$L$9:$L$3900, $G$3, Ingresos!$M$9:$M$3900, $G$4, Ingresos!$D$9:$D$3900, B37) -> 0 | H37: =SUMIFS(Ingresos!$J$9:$J$3900, Ingresos!$L$9:$L$3900, $H$3, Ingresos!$M$9:$M$3900, $H$4, Ingresos!$D$9:$D$3900, B37) -> 0 | I37: =SUMIFS(Ingresos!$J$9:$J$3900, Ingresos!$L$9:$L$3900, $I$3, Ingresos!$M$9:$M$3900, $I$4, Ingresos!$D$9:$D$3900, B37) -> 0 | J37: =SUMIFS(Ingresos!$J$9:$J$3900, Ingresos!$L$9:$L$3900, $J$3, Ingresos!$M$9:$M$3900, $J$4, Ingresos!$D$9:$D$3900, B37) -> 0 | K37: =SUMIFS(Ingresos!$J$9:$J$3900, Ingresos!$L$9:$L$3900, $K$3, Ingresos!$M$9:$M$3900, $K$4, Ingresos!$D$9:$D$3900, B37) -> 0 | L37: =SUMIFS(Ingresos!$J$9:$J$3900, Ingresos!$L$9:$L$3900, $L$3, Ingresos!$M$9:$M$3900, $L$4, Ingresos!$D$9:$D$3900, B37) -> 0 | M37: =SUMIFS(Ingresos!$J$9:$J$3900, Ingresos!$L$9:$L$3900, $M$3, Ingresos!$M$9:$M$3900, $M$4, Ingresos!$D$9:$D$3900, B37) -> 0 | N37: =SUMIFS(Ingresos!$J$9:$J$3900, Ingresos!$L$9:$L$3900, $N$3, Ingresos!$M$9:$M$3900, $N$4, Ingresos!$D$9:$D$3900, B37) -> 0 | O37: =SUM(C37:N37) -> 0 | Q37: =#REF! -> #REF! | R37: =SUMIFS(Gastos!$J$9:$J$4091, Gastos!$L$9:$L$4091, $R$3, Gastos!$M$9:$M$4091, $R$4, Gastos!$D$9:$D$4091, Q37) -> 0 | S37: =SUMIFS(Gastos!$J$9:$J$4091, Gastos!$L$9:$L$4091, $S$3, Gastos!$M$9:$M$4091, $S$4, Gastos!$D$9:$D$4091, Q37) -> 0 | T37: =SUMIFS(Gastos!$J$9:$J$4091, Gastos!$L$9:$L$4091, $T$3, Gastos!$M$9:$M$4091, $T$4, Gastos!$D$9:$D$4091, Q37) -> 0 | U37: =SUMIFS(Gastos!$J$9:$J$4091, Gastos!$L$9:$L$4091, $U$3, Gastos!$M$9:$M$4091, $U$4, Gastos!$D$9:$D$4091, Q37) -> 0 | V37: =SUMIFS(Gastos!$J$9:$J$4091, Gastos!$L$9:$L$4091, $V$3, Gastos!$M$9:$M$4091, $V$4, Gastos!$D$9:$D$4091, Q37) -> 0 | W37: =SUMIFS(Gastos!$J$9:$J$4091, Gastos!$L$9:$L$4091, $W$3, Gastos!$M$9:$M$4091, $W$4, Gastos!$D$9:$D$4091, Q37) -> 0 | X37: =SUMIFS(Gastos!$J$9:$J$4091, Gastos!$L$9:$L$4091, $X$3, Gastos!$M$9:$M$4091, $X$4, Gastos!$D$9:$D$4091, Q37) -> 0 | Y37: =SUMIFS(Gastos!$J$9:$J$4091, Gastos!$L$9:$L$4091, $Y$3, Gastos!$M$9:$M$4091, $Y$4, Gastos!$D$9:$D$4091, Q37) -> 0 | Z37: =SUMIFS(Gastos!$J$9:$J$4091, Gastos!$L$9:$L$4091, $Z$3, Gastos!$M$9:$M$4091, $Z$4, Gastos!$D$9:$D$4091, Q37) -> 0 | AA37: =SUMIFS(Gastos!$J$9:$J$4091, Gastos!$L$9:$L$4091, $AA$3, Gastos!$M$9:$M$4091, $AA$4, Gastos!$D$9:$D$4091, Q37) -> 0 | AB37: =SUMIFS(Gastos!$J$9:$J$4091, Gastos!$L$9:$L$4091, $AB$3, Gastos!$M$9:$M$4091, $AB$4, Gastos!$D$9:$D$4091, Q37) -> 0 | AC37: =SUMIFS(Gastos!$J$9:$J$4091, Gastos!$L$9:$L$4091, $AC$3, Gastos!$M$9:$M$4091, $AC$4, Gastos!$D$9:$D$4091, Q37) -> 0 | AD37: =SUM(R37:AC37) -> 0 | AK37: =#REF! -> #REF! | AL37: =#REF! -> #REF! | AM37: =#REF! -> #REF! | AN37: =AL37-AM37 -> #REF! | AO37: =AO36+AL37 -> #REF! | AP37: =AP36+AM37 -> #REF!
B38: =#REF! -> #REF! | C38: =SUMIFS(Ingresos!$J$9:$J$3900, Ingresos!$L$9:$L$3900, $C$3, Ingresos!$M$9:$M$3900, $C$4, Ingresos!$D$9:$D$3900, B38) -> 0 | D38: =SUMIFS(Ingresos!$J$9:$J$3900, Ingresos!$L$9:$L$3900, $D$3, Ingresos!$M$9:$M$3900, $D$4, Ingresos!$D$9:$D$3900, B38) -> 0 | E38: =SUMIFS(Ingresos!$J$9:$J$3900, Ingresos!$L$9:$L$3900, $E$3, Ingresos!$M$9:$M$3900, $E$4, Ingresos!$D$9:$D$3900, B38) -> 0 | F38: =SUMIFS(Ingresos!$J$9:$J$3900, Ingresos!$L$9:$L$3900, $F$3, Ingresos!$M$9:$M$3900, $F$4, Ingresos!$D$9:$D$3900, B38) -> 0 | G38: =SUMIFS(Ingresos!$J$9:$J$3900, Ingresos!$L$9:$L$3900, $G$3, Ingresos!$M$9:$M$3900, $G$4, Ingresos!$D$9:$D$3900, B38) -> 0 | H38: =SUMIFS(Ingresos!$J$9:$J$3900, Ingresos!$L$9:$L$3900, $H$3, Ingresos!$M$9:$M$3900, $H$4, Ingresos!$D$9:$D$3900, B38) -> 0 | I38: =SUMIFS(Ingresos!$J$9:$J$3900, Ingresos!$L$9:$L$3900, $I$3, Ingresos!$M$9:$M$3900, $I$4, Ingresos!$D$9:$D$3900, B38) -> 0 | J38: =SUMIFS(Ingresos!$J$9:$J$3900, Ingresos!$L$9:$L$3900, $J$3, Ingresos!$M$9:$M$3900, $J$4, Ingresos!$D$9:$D$3900, B38) -> 0 | K38: =SUMIFS(Ingresos!$J$9:$J$3900, Ingresos!$L$9:$L$3900, $K$3, Ingresos!$M$9:$M$3900, $K$4, Ingresos!$D$9:$D$3900, B38) -> 0 | L38: =SUMIFS(Ingresos!$J$9:$J$3900, Ingresos!$L$9:$L$3900, $L$3, Ingresos!$M$9:$M$3900, $L$4, Ingresos!$D$9:$D$3900, B38) -> 0 | M38: =SUMIFS(Ingresos!$J$9:$J$3900, Ingresos!$L$9:$L$3900, $M$3, Ingresos!$M$9:$M$3900, $M$4, Ingresos!$D$9:$D$3900, B38) -> 0 | N38: =SUMIFS(Ingresos!$J$9:$J$3900, Ingresos!$L$9:$L$3900, $N$3, Ingresos!$M$9:$M$3900, $N$4, Ingresos!$D$9:$D$3900, B38) -> 0 | O38: =SUM(C38:N38) -> 0 | Q38: =#REF! -> #REF! | R38: =SUMIFS(Gastos!$J$9:$J$4091, Gastos!$L$9:$L$4091, $R$3, Gastos!$M$9:$M$4091, $R$4, Gastos!$D$9:$D$4091, Q38) -> 0 | S38: =SUMIFS(Gastos!$J$9:$J$4091, Gastos!$L$9:$L$4091, $S$3, Gastos!$M$9:$M$4091, $S$4, Gastos!$D$9:$D$4091, Q38) -> 0 | T38: =SUMIFS(Gastos!$J$9:$J$4091, Gastos!$L$9:$L$4091, $T$3, Gastos!$M$9:$M$4091, $T$4, Gastos!$D$9:$D$4091, Q38) -> 0 | U38: =SUMIFS(Gastos!$J$9:$J$4091, Gastos!$L$9:$L$4091, $U$3, Gastos!$M$9:$M$4091, $U$4, Gastos!$D$9:$D$4091, Q38) -> 0 | V38: =SUMIFS(Gastos!$J$9:$J$4091, Gastos!$L$9:$L$4091, $V$3, Gastos!$M$9:$M$4091, $V$4, Gastos!$D$9:$D$4091, Q38) -> 0 | W38: =SUMIFS(Gastos!$J$9:$J$4091, Gastos!$L$9:$L$4091, $W$3, Gastos!$M$9:$M$4091, $W$4, Gastos!$D$9:$D$4091, Q38) -> 0 | X38: =SUMIFS(Gastos!$J$9:$J$4091, Gastos!$L$9:$L$4091, $X$3, Gastos!$M$9:$M$4091, $X$4, Gastos!$D$9:$D$4091, Q38) -> 0 | Y38: =SUMIFS(Gastos!$J$9:$J$4091, Gastos!$L$9:$L$4091, $Y$3, Gastos!$M$9:$M$4091, $Y$4, Gastos!$D$9:$D$4091, Q38) -> 0 | Z38: =SUMIFS(Gastos!$J$9:$J$4091, Gastos!$L$9:$L$4091, $Z$3, Gastos!$M$9:$M$4091, $Z$4, Gastos!$D$9:$D$4091, Q38) -> 0 | AA38: =SUMIFS(Gastos!$J$9:$J$4091, Gastos!$L$9:$L$4091, $AA$3, Gastos!$M$9:$M$4091, $AA$4, Gastos!$D$9:$D$4091, Q38) -> 0 | AB38: =SUMIFS(Gastos!$J$9:$J$4091, Gastos!$L$9:$L$4091, $AB$3, Gastos!$M$9:$M$4091, $AB$4, Gastos!$D$9:$D$4091, Q38) -> 0 | AC38: =SUMIFS(Gastos!$J$9:$J$4091, Gastos!$L$9:$L$4091, $AC$3, Gastos!$M$9:$M$4091, $AC$4, Gastos!$D$9:$D$4091, Q38) -> 0 | AD38: =SUM(R38:AC38) -> 0 | AK38: =#REF! -> #REF! | AL38: =#REF! -> #REF! | AM38: =#REF! -> #REF! | AN38: =AL38-AM38 -> #REF! | AO38: =AO37+AL38 -> #REF! | AP38: =AP37+AM38 -> #REF!
B39: =#REF! -> #REF! | C39: =SUMIFS(Ingresos!$J$9:$J$3900, Ingresos!$L$9:$L$3900, $C$3, Ingresos!$M$9:$M$3900, $C$4, Ingresos!$D$9:$D$3900, B39) -> 0 | D39: =SUMIFS(Ingresos!$J$9:$J$3900, Ingresos!$L$9:$L$3900, $D$3, Ingresos!$M$9:$M$3900, $D$4, Ingresos!$D$9:$D$3900, B39) -> 0 | E39: =SUMIFS(Ingresos!$J$9:$J$3900, Ingresos!$L$9:$L$3900, $E$3, Ingresos!$M$9:$M$3900, $E$4, Ingresos!$D$9:$D$3900, B39) -> 0 | F39: =SUMIFS(Ingresos!$J$9:$J$3900, Ingresos!$L$9:$L$3900, $F$3, Ingresos!$M$9:$M$3900, $F$4, Ingresos!$D$9:$D$3900, B39) -> 0 | G39: =SUMIFS(Ingresos!$J$9:$J$3900, Ingresos!$L$9:$L$3900, $G$3, Ingresos!$M$9:$M$3900, $G$4, Ingresos!$D$9:$D$3900, B39) -> 0 | H39: =SUMIFS(Ingresos!$J$9:$J$3900, Ingresos!$L$9:$L$3900, $H$3, Ingresos!$M$9:$M$3900, $H$4, Ingresos!$D$9:$D$3900, B39) -> 0 | I39: =SUMIFS(Ingresos!$J$9:$J$3900, Ingresos!$L$9:$L$3900, $I$3, Ingresos!$M$9:$M$3900, $I$4, Ingresos!$D$9:$D$3900, B39) -> 0 | J39: =SUMIFS(Ingresos!$J$9:$J$3900, Ingresos!$L$9:$L$3900, $J$3, Ingresos!$M$9:$M$3900, $J$4, Ingresos!$D$9:$D$3900, B39) -> 0 | K39: =SUMIFS(Ingresos!$J$9:$J$3900, Ingresos!$L$9:$L$3900, $K$3, Ingresos!$M$9:$M$3900, $K$4, Ingresos!$D$9:$D$3900, B39) -> 0 | L39: =SUMIFS(Ingresos!$J$9:$J$3900, Ingresos!$L$9:$L$3900, $L$3, Ingresos!$M$9:$M$3900, $L$4, Ingresos!$D$9:$D$3900, B39) -> 0 | M39: =SUMIFS(Ingresos!$J$9:$J$3900, Ingresos!$L$9:$L$3900, $M$3, Ingresos!$M$9:$M$3900, $M$4, Ingresos!$D$9:$D$3900, B39) -> 0 | N39: =SUMIFS(Ingresos!$J$9:$J$3900, Ingresos!$L$9:$L$3900, $N$3, Ingresos!$M$9:$M$3900, $N$4, Ingresos!$D$9:$D$3900, B39) -> 0 | O39: =SUM(C39:N39) -> 0 | Q39: =#REF! -> #REF! | R39: =SUMIFS(Gastos!$J$9:$J$4091, Gastos!$L$9:$L$4091, $R$3, Gastos!$M$9:$M$4091, $R$4, Gastos!$D$9:$D$4091, Q39) -> 0 | S39: =SUMIFS(Gastos!$J$9:$J$4091, Gastos!$L$9:$L$4091, $S$3, Gastos!$M$9:$M$4091, $S$4, Gastos!$D$9:$D$4091, Q39) -> 0 | T39: =SUMIFS(Gastos!$J$9:$J$4091, Gastos!$L$9:$L$4091, $T$3, Gastos!$M$9:$M$4091, $T$4, Gastos!$D$9:$D$4091, Q39) -> 0 | U39: =SUMIFS(Gastos!$J$9:$J$4091, Gastos!$L$9:$L$4091, $U$3, Gastos!$M$9:$M$4091, $U$4, Gastos!$D$9:$D$4091, Q39) -> 0 | V39: =SUMIFS(Gastos!$J$9:$J$4091, Gastos!$L$9:$L$4091, $V$3, Gastos!$M$9:$M$4091, $V$4, Gastos!$D$9:$D$4091, Q39) -> 0 | W39: =SUMIFS(Gastos!$J$9:$J$4091, Gastos!$L$9:$L$4091, $W$3, Gastos!$M$9:$M$4091, $W$4, Gastos!$D$9:$D$4091, Q39) -> 0 | X39: =SUMIFS(Gastos!$J$9:$J$4091, Gastos!$L$9:$L$4091, $X$3, Gastos!$M$9:$M$4091, $X$4, Gastos!$D$9:$D$4091, Q39) -> 0 | Y39: =SUMIFS(Gastos!$J$9:$J$4091, Gastos!$L$9:$L$4091, $Y$3, Gastos!$M$9:$M$4091, $Y$4, Gastos!$D$9:$D$4091, Q39) -> 0 | Z39: =SUMIFS(Gastos!$J$9:$J$4091, Gastos!$L$9:$L$4091, $Z$3, Gastos!$M$9:$M$4091, $Z$4, Gastos!$D$9:$D$4091, Q39) -> 0 | AA39: =SUMIFS(Gastos!$J$9:$J$4091, Gastos!$L$9:$L$4091, $AA$3, Gastos!$M$9:$M$4091, $AA$4, Gastos!$D$9:$D$4091, Q39) -> 0 | AB39: =SUMIFS(Gastos!$J$9:$J$4091, Gastos!$L$9:$L$4091, $AB$3, Gastos!$M$9:$M$4091, $AB$4, Gastos!$D$9:$D$4091, Q39) -> 0 | AC39: =SUMIFS(Gastos!$J$9:$J$4091, Gastos!$L$9:$L$4091, $AC$3, Gastos!$M$9:$M$4091, $AC$4, Gastos!$D$9:$D$4091, Q39) -> 0 | AD39: =SUM(R39:AC39) -> 0 | AK39: =#REF! -> #REF! | AL39: =#REF! -> #REF! | AM39: =#REF! -> #REF! | AN39: =AL39-AM39 -> #REF! | AO39: =AO38+AL39 -> #REF! | AP39: =AP38+AM39 -> #REF!
B40: =#REF! -> #REF! | C40: =SUMIFS(Ingresos!$J$9:$J$3900, Ingresos!$L$9:$L$3900, $C$3, Ingresos!$M$9:$M$3900, $C$4, Ingresos!$D$9:$D$3900, B40) -> 0 | D40: =SUMIFS(Ingresos!$J$9:$J$3900, Ingresos!$L$9:$L$3900, $D$3, Ingresos!$M$9:$M$3900, $D$4, Ingresos!$D$9:$D$3900, B40) -> 0 | E40: =SUMIFS(Ingresos!$J$9:$J$3900, Ingresos!$L$9:$L$3900, $E$3, Ingresos!$M$9:$M$3900, $E$4, Ingresos!$D$9:$D$3900, B40) -> 0 | F40: =SUMIFS(Ingresos!$J$9:$J$3900, Ingresos!$L$9:$L$3900, $F$3, Ingresos!$M$9:$M$3900, $F$4, Ingresos!$D$9:$D$3900, B40) -> 0 | G40: =SUMIFS(Ingresos!$J$9:$J$3900, Ingresos!$L$9:$L$3900, $G$3, Ingresos!$M$9:$M$3900, $G$4, Ingresos!$D$9:$D$3900, B40) -> 0 | H40: =SUMIFS(Ingresos!$J$9:$J$3900, Ingresos!$L$9:$L$3900, $H$3, Ingresos!$M$9:$M$3900, $H$4, Ingresos!$D$9:$D$3900, B40) -> 0 | I40: =SUMIFS(Ingresos!$J$9:$J$3900, Ingresos!$L$9:$L$3900, $I$3, Ingresos!$M$9:$M$3900, $I$4, Ingresos!$D$9:$D$3900, B40) -> 0 | J40: =SUMIFS(Ingresos!$J$9:$J$3900, Ingresos!$L$9:$L$3900, $J$3, Ingresos!$M$9:$M$3900, $J$4, Ingresos!$D$9:$D$3900, B40) -> 0 | K40: =SUMIFS(Ingresos!$J$9:$J$3900, Ingresos!$L$9:$L$3900, $K$3, Ingresos!$M$9:$M$3900, $K$4, Ingresos!$D$9:$D$3900, B40) -> 0 | L40: =SUMIFS(Ingresos!$J$9:$J$3900, Ingresos!$L$9:$L$3900, $L$3, Ingresos!$M$9:$M$3900, $L$4, Ingresos!$D$9:$D$3900, B40) -> 0 | M40: =SUMIFS(Ingresos!$J$9:$J$3900, Ingresos!$L$9:$L$3900, $M$3, Ingresos!$M$9:$M$3900, $M$4, Ingresos!$D$9:$D$3900, B40) -> 0 | N40: =SUMIFS(Ingresos!$J$9:$J$3900, Ingresos!$L$9:$L$3900, $N$3, Ingresos!$M$9:$M$3900, $N$4, Ingresos!$D$9:$D$3900, B40) -> 0 | O40: =SUM(C40:N40) -> 0 | Q40: =#REF! -> #REF! | R40: =SUMIFS(Gastos!$J$9:$J$4091, Gastos!$L$9:$L$4091, $R$3, Gastos!$M$9:$M$4091, $R$4, Gastos!$D$9:$D$4091, Q40) -> 0 | S40: =SUMIFS(Gastos!$J$9:$J$4091, Gastos!$L$9:$L$4091, $S$3, Gastos!$M$9:$M$4091, $S$4, Gastos!$D$9:$D$4091, Q40) -> 0 | T40: =SUMIFS(Gastos!$J$9:$J$4091, Gastos!$L$9:$L$4091, $T$3, Gastos!$M$9:$M$4091, $T$4, Gastos!$D$9:$D$4091, Q40) -> 0 | U40: =SUMIFS(Gastos!$J$9:$J$4091, Gastos!$L$9:$L$4091, $U$3, Gastos!$M$9:$M$4091, $U$4, Gastos!$D$9:$D$4091, Q40) -> 0 | V40: =SUMIFS(Gastos!$J$9:$J$4091, Gastos!$L$9:$L$4091, $V$3, Gastos!$M$9:$M$4091, $V$4, Gastos!$D$9:$D$4091, Q40) -> 0 | W40: =SUMIFS(Gastos!$J$9:$J$4091, Gastos!$L$9:$L$4091, $W$3, Gastos!$M$9:$M$4091, $W$4, Gastos!$D$9:$D$4091, Q40) -> 0 | X40: =SUMIFS(Gastos!$J$9:$J$4091, Gastos!$L$9:$L$4091, $X$3, Gastos!$M$9:$M$4091, $X$4, Gastos!$D$9:$D$4091, Q40) -> 0 | Y40: =SUMIFS(Gastos!$J$9:$J$4091, Gastos!$L$9:$L$4091, $Y$3, Gastos!$M$9:$M$4091, $Y$4, Gastos!$D$9:$D$4091, Q40) -> 0 | Z40: =SUMIFS(Gastos!$J$9:$J$4091, Gastos!$L$9:$L$4091, $Z$3, Gastos!$M$9:$M$4091, $Z$4, Gastos!$D$9:$D$4091, Q40) -> 0 | AA40: =SUMIFS(Gastos!$J$9:$J$4091, Gastos!$L$9:$L$4091, $AA$3, Gastos!$M$9:$M$4091, $AA$4, Gastos!$D$9:$D$4091, Q40) -> 0 | AB40: =SUMIFS(Gastos!$J$9:$J$4091, Gastos!$L$9:$L$4091, $AB$3, Gastos!$M$9:$M$4091, $AB$4, Gastos!$D$9:$D$4091, Q40) -> 0 | AC40: =SUMIFS(Gastos!$J$9:$J$4091, Gastos!$L$9:$L$4091, $AC$3, Gastos!$M$9:$M$4091, $AC$4, Gastos!$D$9:$D$4091, Q40) -> 0 | AD40: =SUM(R40:AC40) -> 0 | AK40: =#REF! -> #REF! | AL40: =#REF! -> #REF! | AM40: =#REF! -> #REF! | AN40: =AL40-AM40 -> #REF! | AO40: =AO39+AL40 -> #REF! | AP40: =AP39+AM40 -> #REF!
B41: =#REF! -> #REF! | C41: =SUMIFS(Ingresos!$J$9:$J$3900, Ingresos!$L$9:$L$3900, $C$3, Ingresos!$M$9:$M$3900, $C$4, Ingresos!$D$9:$D$3900, B41) -> 0 | D41: =SUMIFS(Ingresos!$J$9:$J$3900, Ingresos!$L$9:$L$3900, $D$3, Ingresos!$M$9:$M$3900, $D$4, Ingresos!$D$9:$D$3900, B41) -> 0 | E41: =SUMIFS(Ingresos!$J$9:$J$3900, Ingresos!$L$9:$L$3900, $E$3, Ingresos!$M$9:$M$3900, $E$4, Ingresos!$D$9:$D$3900, B41) -> 0 | F41: =SUMIFS(Ingresos!$J$9:$J$3900, Ingresos!$L$9:$L$3900, $F$3, Ingresos!$M$9:$M$3900, $F$4, Ingresos!$D$9:$D$3900, B41) -> 0 | G41: =SUMIFS(Ingresos!$J$9:$J$3900, Ingresos!$L$9:$L$3900, $G$3, Ingresos!$M$9:$M$3900, $G$4, Ingresos!$D$9:$D$3900, B41) -> 0 | H41: =SUMIFS(Ingresos!$J$9:$J$3900, Ingresos!$L$9:$L$3900, $H$3, Ingresos!$M$9:$M$3900, $H$4, Ingresos!$D$9:$D$3900, B41) -> 0 | I41: =SUMIFS(Ingresos!$J$9:$J$3900, Ingresos!$L$9:$L$3900, $I$3, Ingresos!$M$9:$M$3900, $I$4, Ingresos!$D$9:$D$3900, B41) -> 0 | J41: =SUMIFS(Ingresos!$J$9:$J$3900, Ingresos!$L$9:$L$3900, $J$3, Ingresos!$M$9:$M$3900, $J$4, Ingresos!$D$9:$D$3900, B41) -> 0 | K41: =SUMIFS(Ingresos!$J$9:$J$3900, Ingresos!$L$9:$L$3900, $K$3, Ingresos!$M$9:$M$3900, $K$4, Ingresos!$D$9:$D$3900, B41) -> 0 | L41: =SUMIFS(Ingresos!$J$9:$J$3900, Ingresos!$L$9:$L$3900, $L$3, Ingresos!$M$9:$M$3900, $L$4, Ingresos!$D$9:$D$3900, B41) -> 0 | M41: =SUMIFS(Ingresos!$J$9:$J$3900, Ingresos!$L$9:$L$3900, $M$3, Ingresos!$M$9:$M$3900, $M$4, Ingresos!$D$9:$D$3900, B41) -> 0 | N41: =SUMIFS(Ingresos!$J$9:$J$3900, Ingresos!$L$9:$L$3900, $N$3, Ingresos!$M$9:$M$3900, $N$4, Ingresos!$D$9:$D$3900, B41) -> 0 | O41: =SUM(C41:N41) -> 0 | Q41: =#REF! -> #REF! | R41: =SUMIFS(Gastos!$J$9:$J$4091, Gastos!$L$9:$L$4091, $R$3, Gastos!$M$9:$M$4091, $R$4, Gastos!$D$9:$D$4091, Q41) -> 0 | S41: =SUMIFS(Gastos!$J$9:$J$4091, Gastos!$L$9:$L$4091, $S$3, Gastos!$M$9:$M$4091, $S$4, Gastos!$D$9:$D$4091, Q41) -> 0 | T41: =SUMIFS(Gastos!$J$9:$J$4091, Gastos!$L$9:$L$4091, $T$3, Gastos!$M$9:$M$4091, $T$4, Gastos!$D$9:$D$4091, Q41) -> 0 | U41: =SUMIFS(Gastos!$J$9:$J$4091, Gastos!$L$9:$L$4091, $U$3, Gastos!$M$9:$M$4091, $U$4, Gastos!$D$9:$D$4091, Q41) -> 0 | V41: =SUMIFS(Gastos!$J$9:$J$4091, Gastos!$L$9:$L$4091, $V$3, Gastos!$M$9:$M$4091, $V$4, Gastos!$D$9:$D$4091, Q41) -> 0 | W41: =SUMIFS(Gastos!$J$9:$J$4091, Gastos!$L$9:$L$4091, $W$3, Gastos!$M$9:$M$4091, $W$4, Gastos!$D$9:$D$4091, Q41) -> 0 | X41: =SUMIFS(Gastos!$J$9:$J$4091, Gastos!$L$9:$L$4091, $X$3, Gastos!$M$9:$M$4091, $X$4, Gastos!$D$9:$D$4091, Q41) -> 0 | Y41: =SUMIFS(Gastos!$J$9:$J$4091, Gastos!$L$9:$L$4091, $Y$3, Gastos!$M$9:$M$4091, $Y$4, Gastos!$D$9:$D$4091, Q41) -> 0 | Z41: =SUMIFS(Gastos!$J$9:$J$4091, Gastos!$L$9:$L$4091, $Z$3, Gastos!$M$9:$M$4091, $Z$4, Gastos!$D$9:$D$4091, Q41) -> 0 | AA41: =SUMIFS(Gastos!$J$9:$J$4091, Gastos!$L$9:$L$4091, $AA$3, Gastos!$M$9:$M$4091, $AA$4, Gastos!$D$9:$D$4091, Q41) -> 0 | AB41: =SUMIFS(Gastos!$J$9:$J$4091, Gastos!$L$9:$L$4091, $AB$3, Gastos!$M$9:$M$4091, $AB$4, Gastos!$D$9:$D$4091, Q41) -> 0 | AC41: =SUMIFS(Gastos!$J$9:$J$4091, Gastos!$L$9:$L$4091, $AC$3, Gastos!$M$9:$M$4091, $AC$4, Gastos!$D$9:$D$4091, Q41) -> 0 | AD41: =SUM(R41:AC41) -> 0 | AK41: =#REF! -> #REF! | AL41: =#REF! -> #REF! | AM41: =#REF! -> #REF! | AN41: =AL41-AM41 -> #REF! | AO41: =AO40+AL41 -> #REF! | AP41: =AP40+AM41 -> #REF!
B42: =#REF! -> #REF! | C42: =SUMIFS(Ingresos!$J$9:$J$3900, Ingresos!$L$9:$L$3900, $C$3, Ingresos!$M$9:$M$3900, $C$4, Ingresos!$D$9:$D$3900, B42) -> 0 | D42: =SUMIFS(Ingresos!$J$9:$J$3900, Ingresos!$L$9:$L$3900, $D$3, Ingresos!$M$9:$M$3900, $D$4, Ingresos!$D$9:$D$3900, B42) -> 0 | E42: =SUMIFS(Ingresos!$J$9:$J$3900, Ingresos!$L$9:$L$3900, $E$3, Ingresos!$M$9:$M$3900, $E$4, Ingresos!$D$9:$D$3900, B42) -> 0 | F42: =SUMIFS(Ingresos!$J$9:$J$3900, Ingresos!$L$9:$L$3900, $F$3, Ingresos!$M$9:$M$3900, $F$4, Ingresos!$D$9:$D$3900, B42) -> 0 | G42: =SUMIFS(Ingresos!$J$9:$J$3900, Ingresos!$L$9:$L$3900, $G$3, Ingresos!$M$9:$M$3900, $G$4, Ingresos!$D$9:$D$3900, B42) -> 0 | H42: =SUMIFS(Ingresos!$J$9:$J$3900, Ingresos!$L$9:$L$3900, $H$3, Ingresos!$M$9:$M$3900, $H$4, Ingresos!$D$9:$D$3900, B42) -> 0 | I42: =SUMIFS(Ingresos!$J$9:$J$3900, Ingresos!$L$9:$L$3900, $I$3, Ingresos!$M$9:$M$3900, $I$4, Ingresos!$D$9:$D$3900, B42) -> 0 | J42: =SUMIFS(Ingresos!$J$9:$J$3900, Ingresos!$L$9:$L$3900, $J$3, Ingresos!$M$9:$M$3900, $J$4, Ingresos!$D$9:$D$3900, B42) -> 0 | K42: =SUMIFS(Ingresos!$J$9:$J$3900, Ingresos!$L$9:$L$3900, $K$3, Ingresos!$M$9:$M$3900, $K$4, Ingresos!$D$9:$D$3900, B42) -> 0 | L42: =SUMIFS(Ingresos!$J$9:$J$3900, Ingresos!$L$9:$L$3900, $L$3, Ingresos!$M$9:$M$3900, $L$4, Ingresos!$D$9:$D$3900, B42) -> 0 | M42: =SUMIFS(Ingresos!$J$9:$J$3900, Ingresos!$L$9:$L$3900, $M$3, Ingresos!$M$9:$M$3900, $M$4, Ingresos!$D$9:$D$3900, B42) -> 0 | N42: =SUMIFS(Ingresos!$J$9:$J$3900, Ingresos!$L$9:$L$3900, $N$3, Ingresos!$M$9:$M$3900, $N$4, Ingresos!$D$9:$D$3900, B42) -> 0 | O42: =SUM(C42:N42) -> 0 | Q42: =#REF! -> #REF! | R42: =SUMIFS(Gastos!$J$9:$J$4091, Gastos!$L$9:$L$4091, $R$3, Gastos!$M$9:$M$4091, $R$4, Gastos!$D$9:$D$4091, Q42) -> 0 | S42: =SUMIFS(Gastos!$J$9:$J$4091, Gastos!$L$9:$L$4091, $S$3, Gastos!$M$9:$M$4091, $S$4, Gastos!$D$9:$D$4091, Q42) -> 0 | T42: =SUMIFS(Gastos!$J$9:$J$4091, Gastos!$L$9:$L$4091, $T$3, Gastos!$M$9:$M$4091, $T$4, Gastos!$D$9:$D$4091, Q42) -> 0 | U42: =SUMIFS(Gastos!$J$9:$J$4091, Gastos!$L$9:$L$4091, $U$3, Gastos!$M$9:$M$4091, $U$4, Gastos!$D$9:$D$4091, Q42) -> 0 | V42: =SUMIFS(Gastos!$J$9:$J$4091, Gastos!$L$9:$L$4091, $V$3, Gastos!$M$9:$M$4091, $V$4, Gastos!$D$9:$D$4091, Q42) -> 0 | W42: =SUMIFS(Gastos!$J$9:$J$4091, Gastos!$L$9:$L$4091, $W$3, Gastos!$M$9:$M$4091, $W$4, Gastos!$D$9:$D$4091, Q42) -> 0 | X42: =SUMIFS(Gastos!$J$9:$J$4091, Gastos!$L$9:$L$4091, $X$3, Gastos!$M$9:$M$4091, $X$4, Gastos!$D$9:$D$4091, Q42) -> 0 | Y42: =SUMIFS(Gastos!$J$9:$J$4091, Gastos!$L$9:$L$4091, $Y$3, Gastos!$M$9:$M$4091, $Y$4, Gastos!$D$9:$D$4091, Q42) -> 0 | Z42: =SUMIFS(Gastos!$J$9:$J$4091, Gastos!$L$9:$L$4091, $Z$3, Gastos!$M$9:$M$4091, $Z$4, Gastos!$D$9:$D$4091, Q42) -> 0 | AA42: =SUMIFS(Gastos!$J$9:$J$4091, Gastos!$L$9:$L$4091, $AA$3, Gastos!$M$9:$M$4091, $AA$4, Gastos!$D$9:$D$4091, Q42) -> 0 | AB42: =SUMIFS(Gastos!$J$9:$J$4091, Gastos!$L$9:$L$4091, $AB$3, Gastos!$M$9:$M$4091, $AB$4, Gastos!$D$9:$D$4091, Q42) -> 0 | AC42: =SUMIFS(Gastos!$J$9:$J$4091, Gastos!$L$9:$L$4091, $AC$3, Gastos!$M$9:$M$4091, $AC$4, Gastos!$D$9:$D$4091, Q42) -> 0 | AD42: =SUM(R42:AC42) -> 0 | AK42: TOTAL | AL42: =SUM(AL30:AL41) -> #REF! | AM42: =SUM(AM30:AM41) -> #REF! | AN42: =SUM(AN30:AN41) -> #REF! | AO42: =SUM(AO30:AO41) -> #REF! | AP42: =SUM(AP30:AP41) -> #REF!
B43: =#REF! -> #REF! | C43: =SUMIFS(Ingresos!$J$9:$J$3900, Ingresos!$L$9:$L$3900, $C$3, Ingresos!$M$9:$M$3900, $C$4, Ingresos!$D$9:$D$3900, B43) -> 0 | D43: =SUMIFS(Ingresos!$J$9:$J$3900, Ingresos!$L$9:$L$3900, $D$3, Ingresos!$M$9:$M$3900, $D$4, Ingresos!$D$9:$D$3900, B43) -> 0 | E43: =SUMIFS(Ingresos!$J$9:$J$3900, Ingresos!$L$9:$L$3900, $E$3, Ingresos!$M$9:$M$3900, $E$4, Ingresos!$D$9:$D$3900, B43) -> 0 | F43: =SUMIFS(Ingresos!$J$9:$J$3900, Ingresos!$L$9:$L$3900, $F$3, Ingresos!$M$9:$M$3900, $F$4, Ingresos!$D$9:$D$3900, B43) -> 0 | G43: =SUMIFS(Ingresos!$J$9:$J$3900, Ingresos!$L$9:$L$3900, $G$3, Ingresos!$M$9:$M$3900, $G$4, Ingresos!$D$9:$D$3900, B43) -> 0 | H43: =SUMIFS(Ingresos!$J$9:$J$3900, Ingresos!$L$9:$L$3900, $H$3, Ingresos!$M$9:$M$3900, $H$4, Ingresos!$D$9:$D$3900, B43) -> 0 | I43: =SUMIFS(Ingresos!$J$9:$J$3900, Ingresos!$L$9:$L$3900, $I$3, Ingresos!$M$9:$M$3900, $I$4, Ingresos!$D$9:$D$3900, B43) -> 0 | J43: =SUMIFS(Ingresos!$J$9:$J$3900, Ingresos!$L$9:$L$3900, $J$3, Ingresos!$M$9:$M$3900, $J$4, Ingresos!$D$9:$D$3900, B43) -> 0 | K43: =SUMIFS(Ingresos!$J$9:$J$3900, Ingresos!$L$9:$L$3900, $K$3, Ingresos!$M$9:$M$3900, $K$4, Ingresos!$D$9:$D$3900, B43) -> 0 | L43: =SUMIFS(Ingresos!$J$9:$J$3900, Ingresos!$L$9:$L$3900, $L$3, Ingresos!$M$9:$M$3900, $L$4, Ingresos!$D$9:$D$3900, B43) -> 0 | M43: =SUMIFS(Ingresos!$J$9:$J$3900, Ingresos!$L$9:$L$3900, $M$3, Ingresos!$M$9:$M$3900, $M$4, Ingresos!$D$9:$D$3900, B43) -> 0 | N43: =SUMIFS(Ingresos!$J$9:$J$3900, Ingresos!$L$9:$L$3900, $N$3, Ingresos!$M$9:$M$3900, $N$4, Ingresos!$D$9:$D$3900, B43) -> 0 | O43: =SUM(C43:N43) -> 0 | Q43: =#REF! -> #REF! | R43: =SUMIFS(Gastos!$J$9:$J$4091, Gastos!$L$9:$L$4091, $R$3, Gastos!$M$9:$M$4091, $R$4, Gastos!$D$9:$D$4091, Q43) -> 0 | S43: =SUMIFS(Gastos!$J$9:$J$4091, Gastos!$L$9:$L$4091, $S$3, Gastos!$M$9:$M$4091, $S$4, Gastos!$D$9:$D$4091, Q43) -> 0 | T43: =SUMIFS(Gastos!$J$9:$J$4091, Gastos!$L$9:$L$4091, $T$3, Gastos!$M$9:$M$4091, $T$4, Gastos!$D$9:$D$4091, Q43) -> 0 | U43: =SUMIFS(Gastos!$J$9:$J$4091, Gastos!$L$9:$L$4091, $U$3, Gastos!$M$9:$M$4091, $U$4, Gastos!$D$9:$D$4091, Q43) -> 0 | V43: =SUMIFS(Gastos!$J$9:$J$4091, Gastos!$L$9:$L$4091, $V$3, Gastos!$M$9:$M$4091, $V$4, Gastos!$D$9:$D$4091, Q43) -> 0 | W43: =SUMIFS(Gastos!$J$9:$J$4091, Gastos!$L$9:$L$4091, $W$3, Gastos!$M$9:$M$4091, $W$4, Gastos!$D$9:$D$4091, Q43) -> 0 | X43: =SUMIFS(Gastos!$J$9:$J$4091, Gastos!$L$9:$L$4091, $X$3, Gastos!$M$9:$M$4091, $X$4, Gastos!$D$9:$D$4091, Q43) -> 0 | Y43: =SUMIFS(Gastos!$J$9:$J$4091, Gastos!$L$9:$L$4091, $Y$3, Gastos!$M$9:$M$4091, $Y$4, Gastos!$D$9:$D$4091, Q43) -> 0 | Z43: =SUMIFS(Gastos!$J$9:$J$4091, Gastos!$L$9:$L$4091, $Z$3, Gastos!$M$9:$M$4091, $Z$4, Gastos!$D$9:$D$4091, Q43) -> 0 | AA43: =SUMIFS(Gastos!$J$9:$J$4091, Gastos!$L$9:$L$4091, $AA$3, Gastos!$M$9:$M$4091, $AA$4, Gastos!$D$9:$D$4091, Q43) -> 0 | AB43: =SUMIFS(Gastos!$J$9:$J$4091, Gastos!$L$9:$L$4091, $AB$3, Gastos!$M$9:$M$4091, $AB$4, Gastos!$D$9:$D$4091, Q43) -> 0 | AC43: =SUMIFS(Gastos!$J$9:$J$4091, Gastos!$L$9:$L$4091, $AC$3, Gastos!$M$9:$M$4091, $AC$4, Gastos!$D$9:$D$4091, Q43) -> 0 | AD43: =SUM(R43:AC43) -> 0
B44: =#REF! -> #REF! | C44: =SUMIFS(Ingresos!$J$9:$J$3900, Ingresos!$L$9:$L$3900, $C$3, Ingresos!$M$9:$M$3900, $C$4, Ingresos!$D$9:$D$3900, B44) -> 0 | D44: =SUMIFS(Ingresos!$J$9:$J$3900, Ingresos!$L$9:$L$3900, $D$3, Ingresos!$M$9:$M$3900, $D$4, Ingresos!$D$9:$D$3900, B44) -> 0 | E44: =SUMIFS(Ingresos!$J$9:$J$3900, Ingresos!$L$9:$L$3900, $E$3, Ingresos!$M$9:$M$3900, $E$4, Ingresos!$D$9:$D$3900, B44) -> 0 | F44: =SUMIFS(Ingresos!$J$9:$J$3900, Ingresos!$L$9:$L$3900, $F$3, Ingresos!$M$9:$M$3900, $F$4, Ingresos!$D$9:$D$3900, B44) -> 0 | G44: =SUMIFS(Ingresos!$J$9:$J$3900, Ingresos!$L$9:$L$3900, $G$3, Ingresos!$M$9:$M$3900, $G$4, Ingresos!$D$9:$D$3900, B44) -> 0 | H44: =SUMIFS(Ingresos!$J$9:$J$3900, Ingresos!$L$9:$L$3900, $H$3, Ingresos!$M$9:$M$3900, $H$4, Ingresos!$D$9:$D$3900, B44) -> 0 | I44: =SUMIFS(Ingresos!$J$9:$J$3900, Ingresos!$L$9:$L$3900, $I$3, Ingresos!$M$9:$M$3900, $I$4, Ingresos!$D$9:$D$3900, B44) -> 0 | J44: =SUMIFS(Ingresos!$J$9:$J$3900, Ingresos!$L$9:$L$3900, $J$3, Ingresos!$M$9:$M$3900, $J$4, Ingresos!$D$9:$D$3900, B44) -> 0 | K44: =SUMIFS(Ingresos!$J$9:$J$3900, Ingresos!$L$9:$L$3900, $K$3, Ingresos!$M$9:$M$3900, $K$4, Ingresos!$D$9:$D$3900, B44) -> 0 | L44: =SUMIFS(Ingresos!$J$9:$J$3900, Ingresos!$L$9:$L$3900, $L$3, Ingresos!$M$9:$M$3900, $L$4, Ingresos!$D$9:$D$3900, B44) -> 0 | M44: =SUMIFS(Ingresos!$J$9:$J$3900, Ingresos!$L$9:$L$3900, $M$3, Ingresos!$M$9:$M$3900, $M$4, Ingresos!$D$9:$D$3900, B44) -> 0 | N44: =SUMIFS(Ingresos!$J$9:$J$3900, Ingresos!$L$9:$L$3900, $N$3, Ingresos!$M$9:$M$3900, $N$4, Ingresos!$D$9:$D$3900, B44) -> 0 | O44: =SUM(C44:N44) -> 0 | Q44: =#REF! -> #REF! | R44: =SUMIFS(Gastos!$J$9:$J$4091, Gastos!$L$9:$L$4091, $R$3, Gastos!$M$9:$M$4091, $R$4, Gastos!$D$9:$D$4091, Q44) -> 0 | S44: =SUMIFS(Gastos!$J$9:$J$4091, Gastos!$L$9:$L$4091, $S$3, Gastos!$M$9:$M$4091, $S$4, Gastos!$D$9:$D$4091, Q44) -> 0 | T44: =SUMIFS(Gastos!$J$9:$J$4091, Gastos!$L$9:$L$4091, $T$3, Gastos!$M$9:$M$4091, $T$4, Gastos!$D$9:$D$4091, Q44) -> 0 | U44: =SUMIFS(Gastos!$J$9:$J$4091, Gastos!$L$9:$L$4091, $U$3, Gastos!$M$9:$M$4091, $U$4, Gastos!$D$9:$D$4091, Q44) -> 0 | V44: =SUMIFS(Gastos!$J$9:$J$4091, Gastos!$L$9:$L$4091, $V$3, Gastos!$M$9:$M$4091, $V$4, Gastos!$D$9:$D$4091, Q44) -> 0 | W44: =SUMIFS(Gastos!$J$9:$J$4091, Gastos!$L$9:$L$4091, $W$3, Gastos!$M$9:$M$4091, $W$4, Gastos!$D$9:$D$4091, Q44) -> 0 | X44: =SUMIFS(Gastos!$J$9:$J$4091, Gastos!$L$9:$L$4091, $X$3, Gastos!$M$9:$M$4091, $X$4, Gastos!$D$9:$D$4091, Q44) -> 0 | Y44: =SUMIFS(Gastos!$J$9:$J$4091, Gastos!$L$9:$L$4091, $Y$3, Gastos!$M$9:$M$4091, $Y$4, Gastos!$D$9:$D$4091, Q44) -> 0 | Z44: =SUMIFS(Gastos!$J$9:$J$4091, Gastos!$L$9:$L$4091, $Z$3, Gastos!$M$9:$M$4091, $Z$4, Gastos!$D$9:$D$4091, Q44) -> 0 | AA44: =SUMIFS(Gastos!$J$9:$J$4091, Gastos!$L$9:$L$4091, $AA$3, Gastos!$M$9:$M$4091, $AA$4, Gastos!$D$9:$D$4091, Q44) -> 0 | AB44: =SUMIFS(Gastos!$J$9:$J$4091, Gastos!$L$9:$L$4091, $AB$3, Gastos!$M$9:$M$4091, $AB$4, Gastos!$D$9:$D$4091, Q44) -> 0 | AC44: =SUMIFS(Gastos!$J$9:$J$4091, Gastos!$L$9:$L$4091, $AC$3, Gastos!$M$9:$M$4091, $AC$4, Gastos!$D$9:$D$4091, Q44) -> 0 | AD44: =SUM(R44:AC44) -> 0 | AK44: Costos | AL44: Presupuesto | AM44: Actual | AN44: Variación
B45: =#REF! -> #REF! | C45: =SUMIFS(Ingresos!$J$9:$J$3900, Ingresos!$L$9:$L$3900, $C$3, Ingresos!$M$9:$M$3900, $C$4, Ingresos!$D$9:$D$3900, B45) -> 0 | D45: =SUMIFS(Ingresos!$J$9:$J$3900, Ingresos!$L$9:$L$3900, $D$3, Ingresos!$M$9:$M$3900, $D$4, Ingresos!$D$9:$D$3900, B45) -> 0 | E45: =SUMIFS(Ingresos!$J$9:$J$3900, Ingresos!$L$9:$L$3900, $E$3, Ingresos!$M$9:$M$3900, $E$4, Ingresos!$D$9:$D$3900, B45) -> 0 | F45: =SUMIFS(Ingresos!$J$9:$J$3900, Ingresos!$L$9:$L$3900, $F$3, Ingresos!$M$9:$M$3900, $F$4, Ingresos!$D$9:$D$3900, B45) -> 0 | G45: =SUMIFS(Ingresos!$J$9:$J$3900, Ingresos!$L$9:$L$3900, $G$3, Ingresos!$M$9:$M$3900, $G$4, Ingresos!$D$9:$D$3900, B45) -> 0 | H45: =SUMIFS(Ingresos!$J$9:$J$3900, Ingresos!$L$9:$L$3900, $H$3, Ingresos!$M$9:$M$3900, $H$4, Ingresos!$D$9:$D$3900, B45) -> 0 | I45: =SUMIFS(Ingresos!$J$9:$J$3900, Ingresos!$L$9:$L$3900, $I$3, Ingresos!$M$9:$M$3900, $I$4, Ingresos!$D$9:$D$3900, B45) -> 0 | J45: =SUMIFS(Ingresos!$J$9:$J$3900, Ingresos!$L$9:$L$3900, $J$3, Ingresos!$M$9:$M$3900, $J$4, Ingresos!$D$9:$D$3900, B45) -> 0 | K45: =SUMIFS(Ingresos!$J$9:$J$3900, Ingresos!$L$9:$L$3900, $K$3, Ingresos!$M$9:$M$3900, $K$4, Ingresos!$D$9:$D$3900, B45) -> 0 | L45: =SUMIFS(Ingresos!$J$9:$J$3900, Ingresos!$L$9:$L$3900, $L$3, Ingresos!$M$9:$M$3900, $L$4, Ingresos!$D$9:$D$3900, B45) -> 0 | M45: =SUMIFS(Ingresos!$J$9:$J$3900, Ingresos!$L$9:$L$3900, $M$3, Ingresos!$M$9:$M$3900, $M$4, Ingresos!$D$9:$D$3900, B45) -> 0 | N45: =SUMIFS(Ingresos!$J$9:$J$3900, Ingresos!$L$9:$L$3900, $N$3, Ingresos!$M$9:$M$3900, $N$4, Ingresos!$D$9:$D$3900, B45) -> 0 | O45: =SUM(C45:N45) -> 0 | Q45: =#REF! -> #REF! | R45: =SUMIFS(Gastos!$J$9:$J$4091, Gastos!$L$9:$L$4091, $R$3, Gastos!$M$9:$M$4091, $R$4, Gastos!$D$9:$D$4091, Q45) -> 0 | S45: =SUMIFS(Gastos!$J$9:$J$4091, Gastos!$L$9:$L$4091, $S$3, Gastos!$M$9:$M$4091, $S$4, Gastos!$D$9:$D$4091, Q45) -> 0 | T45: =SUMIFS(Gastos!$J$9:$J$4091, Gastos!$L$9:$L$4091, $T$3, Gastos!$M$9:$M$4091, $T$4, Gastos!$D$9:$D$4091, Q45) -> 0 | U45: =SUMIFS(Gastos!$J$9:$J$4091, Gastos!$L$9:$L$4091, $U$3, Gastos!$M$9:$M$4091, $U$4, Gastos!$D$9:$D$4091, Q45) -> 0 | V45: =SUMIFS(Gastos!$J$9:$J$4091, Gastos!$L$9:$L$4091, $V$3, Gastos!$M$9:$M$4091, $V$4, Gastos!$D$9:$D$4091, Q45) -> 0 | W45: =SUMIFS(Gastos!$J$9:$J$4091, Gastos!$L$9:$L$4091, $W$3, Gastos!$M$9:$M$4091, $W$4, Gastos!$D$9:$D$4091, Q45) -> 0 | X45: =SUMIFS(Gastos!$J$9:$J$4091, Gastos!$L$9:$L$4091, $X$3, Gastos!$M$9:$M$4091, $X$4, Gastos!$D$9:$D$4091, Q45) -> 0 | Y45: =SUMIFS(Gastos!$J$9:$J$4091, Gastos!$L$9:$L$4091, $Y$3, Gastos!$M$9:$M$4091, $Y$4, Gastos!$D$9:$D$4091, Q45) -> 0 | Z45: =SUMIFS(Gastos!$J$9:$J$4091, Gastos!$L$9:$L$4091, $Z$3, Gastos!$M$9:$M$4091, $Z$4, Gastos!$D$9:$D$4091, Q45) -> 0 | AA45: =SUMIFS(Gastos!$J$9:$J$4091, Gastos!$L$9:$L$4091, $AA$3, Gastos!$M$9:$M$4091, $AA$4, Gastos!$D$9:$D$4091, Q45) -> 0 | AB45: =SUMIFS(Gastos!$J$9:$J$4091, Gastos!$L$9:$L$4091, $AB$3, Gastos!$M$9:$M$4091, $AB$4, Gastos!$D$9:$D$4091, Q45) -> 0 | AC45: =SUMIFS(Gastos!$J$9:$J$4091, Gastos!$L$9:$L$4091, $AC$3, Gastos!$M$9:$M$4091, $AC$4, Gastos!$D$9:$D$4091, Q45) -> 0 | AD45: =SUM(R45:AC45) -> 0 | AK45: =#REF! -> #REF! | AL45: =#REF! -> #REF! | AM45: =#REF! -> #REF! | AN45: =AL45-AM45 -> #REF!
B46: =#REF! -> #REF! | C46: =SUMIFS(Ingresos!$J$9:$J$3900, Ingresos!$L$9:$L$3900, $C$3, Ingresos!$M$9:$M$3900, $C$4, Ingresos!$D$9:$D$3900, B46) -> 0 | D46: =SUMIFS(Ingresos!$J$9:$J$3900, Ingresos!$L$9:$L$3900, $D$3, Ingresos!$M$9:$M$3900, $D$4, Ingresos!$D$9:$D$3900, B46) -> 0 | E46: =SUMIFS(Ingresos!$J$9:$J$3900, Ingresos!$L$9:$L$3900, $E$3, Ingresos!$M$9:$M$3900, $E$4, Ingresos!$D$9:$D$3900, B46) -> 0 | F46: =SUMIFS(Ingresos!$J$9:$J$3900, Ingresos!$L$9:$L$3900, $F$3, Ingresos!$M$9:$M$3900, $F$4, Ingresos!$D$9:$D$3900, B46) -> 0 | G46: =SUMIFS(Ingresos!$J$9:$J$3900, Ingresos!$L$9:$L$3900, $G$3, Ingresos!$M$9:$M$3900, $G$4, Ingresos!$D$9:$D$3900, B46) -> 0 | H46: =SUMIFS(Ingresos!$J$9:$J$3900, Ingresos!$L$9:$L$3900, $H$3, Ingresos!$M$9:$M$3900, $H$4, Ingresos!$D$9:$D$3900, B46) -> 0 | I46: =SUMIFS(Ingresos!$J$9:$J$3900, Ingresos!$L$9:$L$3900, $I$3, Ingresos!$M$9:$M$3900, $I$4, Ingresos!$D$9:$D$3900, B46) -> 0 | J46: =SUMIFS(Ingresos!$J$9:$J$3900, Ingresos!$L$9:$L$3900, $J$3, Ingresos!$M$9:$M$3900, $J$4, Ingresos!$D$9:$D$3900, B46) -> 0 | K46: =SUMIFS(Ingresos!$J$9:$J$3900, Ingresos!$L$9:$L$3900, $K$3, Ingresos!$M$9:$M$3900, $K$4, Ingresos!$D$9:$D$3900, B46) -> 0 | L46: =SUMIFS(Ingresos!$J$9:$J$3900, Ingresos!$L$9:$L$3900, $L$3, Ingresos!$M$9:$M$3900, $L$4, Ingresos!$D$9:$D$3900, B46) -> 0 | M46: =SUMIFS(Ingresos!$J$9:$J$3900, Ingresos!$L$9:$L$3900, $M$3, Ingresos!$M$9:$M$3900, $M$4, Ingresos!$D$9:$D$3900, B46) -> 0 | N46: =SUMIFS(Ingresos!$J$9:$J$3900, Ingresos!$L$9:$L$3900, $N$3, Ingresos!$M$9:$M$3900, $N$4, Ingresos!$D$9:$D$3900, B46) -> 0 | O46: =SUM(C46:N46) -> 0 | Q46: =#REF! -> #REF! | R46: =SUMIFS(Gastos!$J$9:$J$4091, Gastos!$L$9:$L$4091, $R$3, Gastos!$M$9:$M$4091, $R$4, Gastos!$D$9:$D$4091, Q46) -> 0 | S46: =SUMIFS(Gastos!$J$9:$J$4091, Gastos!$L$9:$L$4091, $S$3, Gastos!$M$9:$M$4091, $S$4, Gastos!$D$9:$D$4091, Q46) -> 0 | T46: =SUMIFS(Gastos!$J$9:$J$4091, Gastos!$L$9:$L$4091, $T$3, Gastos!$M$9:$M$4091, $T$4, Gastos!$D$9:$D$4091, Q46) -> 0 | U46: =SUMIFS(Gastos!$J$9:$J$4091, Gastos!$L$9:$L$4091, $U$3, Gastos!$M$9:$M$4091, $U$4, Gastos!$D$9:$D$4091, Q46) -> 0 | V46: =SUMIFS(Gastos!$J$9:$J$4091, Gastos!$L$9:$L$4091, $V$3, Gastos!$M$9:$M$4091, $V$4, Gastos!$D$9:$D$4091, Q46) -> 0 | W46: =SUMIFS(Gastos!$J$9:$J$4091, Gastos!$L$9:$L$4091, $W$3, Gastos!$M$9:$M$4091, $W$4, Gastos!$D$9:$D$4091, Q46) -> 0 | X46: =SUMIFS(Gastos!$J$9:$J$4091, Gastos!$L$9:$L$4091, $X$3, Gastos!$M$9:$M$4091, $X$4, Gastos!$D$9:$D$4091, Q46) -> 0 | Y46: =SUMIFS(Gastos!$J$9:$J$4091, Gastos!$L$9:$L$4091, $Y$3, Gastos!$M$9:$M$4091, $Y$4, Gastos!$D$9:$D$4091, Q46) -> 0 | Z46: =SUMIFS(Gastos!$J$9:$J$4091, Gastos!$L$9:$L$4091, $Z$3, Gastos!$M$9:$M$4091, $Z$4, Gastos!$D$9:$D$4091, Q46) -> 0 | AA46: =SUMIFS(Gastos!$J$9:$J$4091, Gastos!$L$9:$L$4091, $AA$3, Gastos!$M$9:$M$4091, $AA$4, Gastos!$D$9:$D$4091, Q46) -> 0 | AB46: =SUMIFS(Gastos!$J$9:$J$4091, Gastos!$L$9:$L$4091, $AB$3, Gastos!$M$9:$M$4091, $AB$4, Gastos!$D$9:$D$4091, Q46) -> 0 | AC46: =SUMIFS(Gastos!$J$9:$J$4091, Gastos!$L$9:$L$4091, $AC$3, Gastos!$M$9:$M$4091, $AC$4, Gastos!$D$9:$D$4091, Q46) -> 0 | AD46: =SUM(R46:AC46) -> 0 | AK46: =#REF! -> #REF! | AL46: =#REF! -> #REF! | AM46: =#REF! -> #REF! | AN46: =AL46-AM46 -> #REF!
B47: =#REF! -> #REF! | C47: =SUMIFS(Ingresos!$J$9:$J$3900, Ingresos!$L$9:$L$3900, $C$3, Ingresos!$M$9:$M$3900, $C$4, Ingresos!$D$9:$D$3900, B47) -> 0 | D47: =SUMIFS(Ingresos!$J$9:$J$3900, Ingresos!$L$9:$L$3900, $D$3, Ingresos!$M$9:$M$3900, $D$4, Ingresos!$D$9:$D$3900, B47) -> 0 | E47: =SUMIFS(Ingresos!$J$9:$J$3900, Ingresos!$L$9:$L$3900, $E$3, Ingresos!$M$9:$M$3900, $E$4, Ingresos!$D$9:$D$3900, B47) -> 0 | F47: =SUMIFS(Ingresos!$J$9:$J$3900, Ingresos!$L$9:$L$3900, $F$3, Ingresos!$M$9:$M$3900, $F$4, Ingresos!$D$9:$D$3900, B47) -> 0 | G47: =SUMIFS(Ingresos!$J$9:$J$3900, Ingresos!$L$9:$L$3900, $G$3, Ingresos!$M$9:$M$3900, $G$4, Ingresos!$D$9:$D$3900, B47) -> 0 | H47: =SUMIFS(Ingresos!$J$9:$J$3900, Ingresos!$L$9:$L$3900, $H$3, Ingresos!$M$9:$M$3900, $H$4, Ingresos!$D$9:$D$3900, B47) -> 0 | I47: =SUMIFS(Ingresos!$J$9:$J$3900, Ingresos!$L$9:$L$3900, $I$3, Ingresos!$M$9:$M$3900, $I$4, Ingresos!$D$9:$D$3900, B47) -> 0 | J47: =SUMIFS(Ingresos!$J$9:$J$3900, Ingresos!$L$9:$L$3900, $J$3, Ingresos!$M$9:$M$3900, $J$4, Ingresos!$D$9:$D$3900, B47) -> 0 | K47: =SUMIFS(Ingresos!$J$9:$J$3900, Ingresos!$L$9:$L$3900, $K$3, Ingresos!$M$9:$M$3900, $K$4, Ingresos!$D$9:$D$3900, B47) -> 0 | L47: =SUMIFS(Ingresos!$J$9:$J$3900, Ingresos!$L$9:$L$3900, $L$3, Ingresos!$M$9:$M$3900, $L$4, Ingresos!$D$9:$D$3900, B47) -> 0 | M47: =SUMIFS(Ingresos!$J$9:$J$3900, Ingresos!$L$9:$L$3900, $M$3, Ingresos!$M$9:$M$3900, $M$4, Ingresos!$D$9:$D$3900, B47) -> 0 | N47: =SUMIFS(Ingresos!$J$9:$J$3900, Ingresos!$L$9:$L$3900, $N$3, Ingresos!$M$9:$M$3900, $N$4, Ingresos!$D$9:$D$3900, B47) -> 0 | O47: =SUM(C47:N47) -> 0 | Q47: =#REF! -> #REF! | R47: =SUMIFS(Gastos!$J$9:$J$4091, Gastos!$L$9:$L$4091, $R$3, Gastos!$M$9:$M$4091, $R$4, Gastos!$D$9:$D$4091, Q47) -> 0 | S47: =SUMIFS(Gastos!$J$9:$J$4091, Gastos!$L$9:$L$4091, $S$3, Gastos!$M$9:$M$4091, $S$4, Gastos!$D$9:$D$4091, Q47) -> 0 | T47: =SUMIFS(Gastos!$J$9:$J$4091, Gastos!$L$9:$L$4091, $T$3, Gastos!$M$9:$M$4091, $T$4, Gastos!$D$9:$D$4091, Q47) -> 0 | U47: =SUMIFS(Gastos!$J$9:$J$4091, Gastos!$L$9:$L$4091, $U$3, Gastos!$M$9:$M$4091, $U$4, Gastos!$D$9:$D$4091, Q47) -> 0 | V47: =SUMIFS(Gastos!$J$9:$J$4091, Gastos!$L$9:$L$4091, $V$3, Gastos!$M$9:$M$4091, $V$4, Gastos!$D$9:$D$4091, Q47) -> 0 | W47: =SUMIFS(Gastos!$J$9:$J$4091, Gastos!$L$9:$L$4091, $W$3, Gastos!$M$9:$M$4091, $W$4, Gastos!$D$9:$D$4091, Q47) -> 0 | X47: =SUMIFS(Gastos!$J$9:$J$4091, Gastos!$L$9:$L$4091, $X$3, Gastos!$M$9:$M$4091, $X$4, Gastos!$D$9:$D$4091, Q47) -> 0 | Y47: =SUMIFS(Gastos!$J$9:$J$4091, Gastos!$L$9:$L$4091, $Y$3, Gastos!$M$9:$M$4091, $Y$4, Gastos!$D$9:$D$4091, Q47) -> 0 | Z47: =SUMIFS(Gastos!$J$9:$J$4091, Gastos!$L$9:$L$4091, $Z$3, Gastos!$M$9:$M$4091, $Z$4, Gastos!$D$9:$D$4091, Q47) -> 0 | AA47: =SUMIFS(Gastos!$J$9:$J$4091, Gastos!$L$9:$L$4091, $AA$3, Gastos!$M$9:$M$4091, $AA$4, Gastos!$D$9:$D$4091, Q47) -> 0 | AB47: =SUMIFS(Gastos!$J$9:$J$4091, Gastos!$L$9:$L$4091, $AB$3, Gastos!$M$9:$M$4091, $AB$4, Gastos!$D$9:$D$4091, Q47) -> 0 | AC47: =SUMIFS(Gastos!$J$9:$J$4091, Gastos!$L$9:$L$4091, $AC$3, Gastos!$M$9:$M$4091, $AC$4, Gastos!$D$9:$D$4091, Q47) -> 0 | AD47: =SUM(R47:AC47) -> 0 | AK47: =#REF! -> #REF! | AL47: =#REF! -> #REF! | AM47: =#REF! -> #REF! | AN47: =AL47-AM47 -> #REF!
B48: =#REF! -> #REF! | C48: =SUMIFS(Ingresos!$J$9:$J$3900, Ingresos!$L$9:$L$3900, $C$3, Ingresos!$M$9:$M$3900, $C$4, Ingresos!$D$9:$D$3900, B48) -> 0 | D48: =SUMIFS(Ingresos!$J$9:$J$3900, Ingresos!$L$9:$L$3900, $D$3, Ingresos!$M$9:$M$3900, $D$4, Ingresos!$D$9:$D$3900, B48) -> 0 | E48: =SUMIFS(Ingresos!$J$9:$J$3900, Ingresos!$L$9:$L$3900, $E$3, Ingresos!$M$9:$M$3900, $E$4, Ingresos!$D$9:$D$3900, B48) -> 0 | F48: =SUMIFS(Ingresos!$J$9:$J$3900, Ingresos!$L$9:$L$3900, $F$3, Ingresos!$M$9:$M$3900, $F$4, Ingresos!$D$9:$D$3900, B48) -> 0 | G48: =SUMIFS(Ingresos!$J$9:$J$3900, Ingresos!$L$9:$L$3900, $G$3, Ingresos!$M$9:$M$3900, $G$4, Ingresos!$D$9:$D$3900, B48) -> 0 | H48: =SUMIFS(Ingresos!$J$9:$J$3900, Ingresos!$L$9:$L$3900, $H$3, Ingresos!$M$9:$M$3900, $H$4, Ingresos!$D$9:$D$3900, B48) -> 0 | I48: =SUMIFS(Ingresos!$J$9:$J$3900, Ingresos!$L$9:$L$3900, $I$3, Ingresos!$M$9:$M$3900, $I$4, Ingresos!$D$9:$D$3900, B48) -> 0 | J48: =SUMIFS(Ingresos!$J$9:$J$3900, Ingresos!$L$9:$L$3900, $J$3, Ingresos!$M$9:$M$3900, $J$4, Ingresos!$D$9:$D$3900, B48) -> 0 | K48: =SUMIFS(Ingresos!$J$9:$J$3900, Ingresos!$L$9:$L$3900, $K$3, Ingresos!$M$9:$M$3900, $K$4, Ingresos!$D$9:$D$3900, B48) -> 0 | L48: =SUMIFS(Ingresos!$J$9:$J$3900, Ingresos!$L$9:$L$3900, $L$3, Ingresos!$M$9:$M$3900, $L$4, Ingresos!$D$9:$D$3900, B48) -> 0 | M48: =SUMIFS(Ingresos!$J$9:$J$3900, Ingresos!$L$9:$L$3900, $M$3, Ingresos!$M$9:$M$3900, $M$4, Ingresos!$D$9:$D$3900, B48) -> 0 | N48: =SUMIFS(Ingresos!$J$9:$J$3900, Ingresos!$L$9:$L$3900, $N$3, Ingresos!$M$9:$M$3900, $N$4, Ingresos!$D$9:$D$3900, B48) -> 0 | O48: =SUM(C48:N48) -> 0 | Q48: =#REF! -> #REF! | R48: =SUMIFS(Gastos!$J$9:$J$4091, Gastos!$L$9:$L$4091, $R$3, Gastos!$M$9:$M$4091, $R$4, Gastos!$D$9:$D$4091, Q48) -> 0 | S48: =SUMIFS(Gastos!$J$9:$J$4091, Gastos!$L$9:$L$4091, $S$3, Gastos!$M$9:$M$4091, $S$4, Gastos!$D$9:$D$4091, Q48) -> 0 | T48: =SUMIFS(Gastos!$J$9:$J$4091, Gastos!$L$9:$L$4091, $T$3, Gastos!$M$9:$M$4091, $T$4, Gastos!$D$9:$D$4091, Q48) -> 0 | U48: =SUMIFS(Gastos!$J$9:$J$4091, Gastos!$L$9:$L$4091, $U$3, Gastos!$M$9:$M$4091, $U$4, Gastos!$D$9:$D$4091, Q48) -> 0 | V48: =SUMIFS(Gastos!$J$9:$J$4091, Gastos!$L$9:$L$4091, $V$3, Gastos!$M$9:$M$4091, $V$4, Gastos!$D$9:$D$4091, Q48) -> 0 | W48: =SUMIFS(Gastos!$J$9:$J$4091, Gastos!$L$9:$L$4091, $W$3, Gastos!$M$9:$M$4091, $W$4, Gastos!$D$9:$D$4091, Q48) -> 0 | X48: =SUMIFS(Gastos!$J$9:$J$4091, Gastos!$L$9:$L$4091, $X$3, Gastos!$M$9:$M$4091, $X$4, Gastos!$D$9:$D$4091, Q48) -> 0 | Y48: =SUMIFS(Gastos!$J$9:$J$4091, Gastos!$L$9:$L$4091, $Y$3, Gastos!$M$9:$M$4091, $Y$4, Gastos!$D$9:$D$4091, Q48) -> 0 | Z48: =SUMIFS(Gastos!$J$9:$J$4091, Gastos!$L$9:$L$4091, $Z$3, Gastos!$M$9:$M$4091, $Z$4, Gastos!$D$9:$D$4091, Q48) -> 0 | AA48: =SUMIFS(Gastos!$J$9:$J$4091, Gastos!$L$9:$L$4091, $AA$3, Gastos!$M$9:$M$4091, $AA$4, Gastos!$D$9:$D$4091, Q48) -> 0 | AB48: =SUMIFS(Gastos!$J$9:$J$4091, Gastos!$L$9:$L$4091, $AB$3, Gastos!$M$9:$M$4091, $AB$4, Gastos!$D$9:$D$4091, Q48) -> 0 | AC48: =SUMIFS(Gastos!$J$9:$J$4091, Gastos!$L$9:$L$4091, $AC$3, Gastos!$M$9:$M$4091, $AC$4, Gastos!$D$9:$D$4091, Q48) -> 0 | AD48: =SUM(R48:AC48) -> 0 | AK48: =#REF! -> #REF! | AL48: =#REF! -> #REF! | AM48: =#REF! -> #REF! | AN48: =AL48-AM48 -> #REF!
B49: =#REF! -> #REF! | C49: =SUMIFS(Ingresos!$J$9:$J$3900, Ingresos!$L$9:$L$3900, $C$3, Ingresos!$M$9:$M$3900, $C$4, Ingresos!$D$9:$D$3900, B49) -> 0 | D49: =SUMIFS(Ingresos!$J$9:$J$3900, Ingresos!$L$9:$L$3900, $D$3, Ingresos!$M$9:$M$3900, $D$4, Ingresos!$D$9:$D$3900, B49) -> 0 | E49: =SUMIFS(Ingresos!$J$9:$J$3900, Ingresos!$L$9:$L$3900, $E$3, Ingresos!$M$9:$M$3900, $E$4, Ingresos!$D$9:$D$3900, B49) -> 0 | F49: =SUMIFS(Ingresos!$J$9:$J$3900, Ingresos!$L$9:$L$3900, $F$3, Ingresos!$M$9:$M$3900, $F$4, Ingresos!$D$9:$D$3900, B49) -> 0 | G49: =SUMIFS(Ingresos!$J$9:$J$3900, Ingresos!$L$9:$L$3900, $G$3, Ingresos!$M$9:$M$3900, $G$4, Ingresos!$D$9:$D$3900, B49) -> 0 | H49: =SUMIFS(Ingresos!$J$9:$J$3900, Ingresos!$L$9:$L$3900, $H$3, Ingresos!$M$9:$M$3900, $H$4, Ingresos!$D$9:$D$3900, B49) -> 0 | I49: =SUMIFS(Ingresos!$J$9:$J$3900, Ingresos!$L$9:$L$3900, $I$3, Ingresos!$M$9:$M$3900, $I$4, Ingresos!$D$9:$D$3900, B49) -> 0 | J49: =SUMIFS(Ingresos!$J$9:$J$3900, Ingresos!$L$9:$L$3900, $J$3, Ingresos!$M$9:$M$3900, $J$4, Ingresos!$D$9:$D$3900, B49) -> 0 | K49: =SUMIFS(Ingresos!$J$9:$J$3900, Ingresos!$L$9:$L$3900, $K$3, Ingresos!$M$9:$M$3900, $K$4, Ingresos!$D$9:$D$3900, B49) -> 0 | L49: =SUMIFS(Ingresos!$J$9:$J$3900, Ingresos!$L$9:$L$3900, $L$3, Ingresos!$M$9:$M$3900, $L$4, Ingresos!$D$9:$D$3900, B49) -> 0 | M49: =SUMIFS(Ingresos!$J$9:$J$3900, Ingresos!$L$9:$L$3900, $M$3, Ingresos!$M$9:$M$3900, $M$4, Ingresos!$D$9:$D$3900, B49) -> 0 | N49: =SUMIFS(Ingresos!$J$9:$J$3900, Ingresos!$L$9:$L$3900, $N$3, Ingresos!$M$9:$M$3900, $N$4, Ingresos!$D$9:$D$3900, B49) -> 0 | O49: =SUM(C49:N49) -> 0 | Q49: =#REF! -> #REF! | R49: =SUMIFS(Gastos!$J$9:$J$4091, Gastos!$L$9:$L$4091, $R$3, Gastos!$M$9:$M$4091, $R$4, Gastos!$D$9:$D$4091, Q49) -> 0 | S49: =SUMIFS(Gastos!$J$9:$J$4091, Gastos!$L$9:$L$4091, $S$3, Gastos!$M$9:$M$4091, $S$4, Gastos!$D$9:$D$4091, Q49) -> 0 | T49: =SUMIFS(Gastos!$J$9:$J$4091, Gastos!$L$9:$L$4091, $T$3, Gastos!$M$9:$M$4091, $T$4, Gastos!$D$9:$D$4091, Q49) -> 0 | U49: =SUMIFS(Gastos!$J$9:$J$4091, Gastos!$L$9:$L$4091, $U$3, Gastos!$M$9:$M$4091, $U$4, Gastos!$D$9:$D$4091, Q49) -> 0 | V49: =SUMIFS(Gastos!$J$9:$J$4091, Gastos!$L$9:$L$4091, $V$3, Gastos!$M$9:$M$4091, $V$4, Gastos!$D$9:$D$4091, Q49) -> 0 | W49: =SUMIFS(Gastos!$J$9:$J$4091, Gastos!$L$9:$L$4091, $W$3, Gastos!$M$9:$M$4091, $W$4, Gastos!$D$9:$D$4091, Q49) -> 0 | X49: =SUMIFS(Gastos!$J$9:$J$4091, Gastos!$L$9:$L$4091, $X$3, Gastos!$M$9:$M$4091, $X$4, Gastos!$D$9:$D$4091, Q49) -> 0 | Y49: =SUMIFS(Gastos!$J$9:$J$4091, Gastos!$L$9:$L$4091, $Y$3, Gastos!$M$9:$M$4091, $Y$4, Gastos!$D$9:$D$4091, Q49) -> 0 | Z49: =SUMIFS(Gastos!$J$9:$J$4091, Gastos!$L$9:$L$4091, $Z$3, Gastos!$M$9:$M$4091, $Z$4, Gastos!$D$9:$D$4091, Q49) -> 0 | AA49: =SUMIFS(Gastos!$J$9:$J$4091, Gastos!$L$9:$L$4091, $AA$3, Gastos!$M$9:$M$4091, $AA$4, Gastos!$D$9:$D$4091, Q49) -> 0 | AB49: =SUMIFS(Gastos!$J$9:$J$4091, Gastos!$L$9:$L$4091, $AB$3, Gastos!$M$9:$M$4091, $AB$4, Gastos!$D$9:$D$4091, Q49) -> 0 | AC49: =SUMIFS(Gastos!$J$9:$J$4091, Gastos!$L$9:$L$4091, $AC$3, Gastos!$M$9:$M$4091, $AC$4, Gastos!$D$9:$D$4091, Q49) -> 0 | AD49: =SUM(R49:AC49) -> 0 | AK49: =#REF! -> #REF! | AL49: =#REF! -> #REF! | AM49: =#REF! -> #REF! | AN49: =AL49-AM49 -> #REF!
B50: =#REF! -> #REF! | C50: =SUMIFS(Ingresos!$J$9:$J$3900, Ingresos!$L$9:$L$3900, $C$3, Ingresos!$M$9:$M$3900, $C$4, Ingresos!$D$9:$D$3900, B50) -> 0 | D50: =SUMIFS(Ingresos!$J$9:$J$3900, Ingresos!$L$9:$L$3900, $D$3, Ingresos!$M$9:$M$3900, $D$4, Ingresos!$D$9:$D$3900, B50) -> 0 | E50: =SUMIFS(Ingresos!$J$9:$J$3900, Ingresos!$L$9:$L$3900, $E$3, Ingresos!$M$9:$M$3900, $E$4, Ingresos!$D$9:$D$3900, B50) -> 0 | F50: =SUMIFS(Ingresos!$J$9:$J$3900, Ingresos!$L$9:$L$3900, $F$3, Ingresos!$M$9:$M$3900, $F$4, Ingresos!$D$9:$D$3900, B50) -> 0 | G50: =SUMIFS(Ingresos!$J$9:$J$3900, Ingresos!$L$9:$L$3900, $G$3, Ingresos!$M$9:$M$3900, $G$4, Ingresos!$D$9:$D$3900, B50) -> 0 | H50: =SUMIFS(Ingresos!$J$9:$J$3900, Ingresos!$L$9:$L$3900, $H$3, Ingresos!$M$9:$M$3900, $H$4, Ingresos!$D$9:$D$3900, B50) -> 0 | I50: =SUMIFS(Ingresos!$J$9:$J$3900, Ingresos!$L$9:$L$3900, $I$3, Ingresos!$M$9:$M$3900, $I$4, Ingresos!$D$9:$D$3900, B50) -> 0 | J50: =SUMIFS(Ingresos!$J$9:$J$3900, Ingresos!$L$9:$L$3900, $J$3, Ingresos!$M$9:$M$3900, $J$4, Ingresos!$D$9:$D$3900, B50) -> 0 | K50: =SUMIFS(Ingresos!$J$9:$J$3900, Ingresos!$L$9:$L$3900, $K$3, Ingresos!$M$9:$M$3900, $K$4, Ingresos!$D$9:$D$3900, B50) -> 0 | L50: =SUMIFS(Ingresos!$J$9:$J$3900, Ingresos!$L$9:$L$3900, $L$3, Ingresos!$M$9:$M$3900, $L$4, Ingresos!$D$9:$D$3900, B50) -> 0 | M50: =SUMIFS(Ingresos!$J$9:$J$3900, Ingresos!$L$9:$L$3900, $M$3, Ingresos!$M$9:$M$3900, $M$4, Ingresos!$D$9:$D$3900, B50) -> 0 | N50: =SUMIFS(Ingresos!$J$9:$J$3900, Ingresos!$L$9:$L$3900, $N$3, Ingresos!$M$9:$M$3900, $N$4, Ingresos!$D$9:$D$3900, B50) -> 0 | O50: =SUM(C50:N50) -> 0 | Q50: =#REF! -> #REF! | R50: =SUMIFS(Gastos!$J$9:$J$4091, Gastos!$L$9:$L$4091, $R$3, Gastos!$M$9:$M$4091, $R$4, Gastos!$D$9:$D$4091, Q50) -> 0 | S50: =SUMIFS(Gastos!$J$9:$J$4091, Gastos!$L$9:$L$4091, $S$3, Gastos!$M$9:$M$4091, $S$4, Gastos!$D$9:$D$4091, Q50) -> 0 | T50: =SUMIFS(Gastos!$J$9:$J$4091, Gastos!$L$9:$L$4091, $T$3, Gastos!$M$9:$M$4091, $T$4, Gastos!$D$9:$D$4091, Q50) -> 0 | U50: =SUMIFS(Gastos!$J$9:$J$4091, Gastos!$L$9:$L$4091, $U$3, Gastos!$M$9:$M$4091, $U$4, Gastos!$D$9:$D$4091, Q50) -> 0 | V50: =SUMIFS(Gastos!$J$9:$J$4091, Gastos!$L$9:$L$4091, $V$3, Gastos!$M$9:$M$4091, $V$4, Gastos!$D$9:$D$4091, Q50) -> 0 | W50: =SUMIFS(Gastos!$J$9:$J$4091, Gastos!$L$9:$L$4091, $W$3, Gastos!$M$9:$M$4091, $W$4, Gastos!$D$9:$D$4091, Q50) -> 0 | X50: =SUMIFS(Gastos!$J$9:$J$4091, Gastos!$L$9:$L$4091, $X$3, Gastos!$M$9:$M$4091, $X$4, Gastos!$D$9:$D$4091, Q50) -> 0 | Y50: =SUMIFS(Gastos!$J$9:$J$4091, Gastos!$L$9:$L$4091, $Y$3, Gastos!$M$9:$M$4091, $Y$4, Gastos!$D$9:$D$4091, Q50) -> 0 | Z50: =SUMIFS(Gastos!$J$9:$J$4091, Gastos!$L$9:$L$4091, $Z$3, Gastos!$M$9:$M$4091, $Z$4, Gastos!$D$9:$D$4091, Q50) -> 0 | AA50: =SUMIFS(Gastos!$J$9:$J$4091, Gastos!$L$9:$L$4091, $AA$3, Gastos!$M$9:$M$4091, $AA$4, Gastos!$D$9:$D$4091, Q50) -> 0 | AB50: =SUMIFS(Gastos!$J$9:$J$4091, Gastos!$L$9:$L$4091, $AB$3, Gastos!$M$9:$M$4091, $AB$4, Gastos!$D$9:$D$4091, Q50) -> 0 | AC50: =SUMIFS(Gastos!$J$9:$J$4091, Gastos!$L$9:$L$4091, $AC$3, Gastos!$M$9:$M$4091, $AC$4, Gastos!$D$9:$D$4091, Q50) -> 0 | AD50: =SUM(R50:AC50) -> 0 | AK50: =#REF! -> #REF! | AL50: =#REF! -> #REF! | AM50: =#REF! -> #REF! | AN50: =AL50-AM50 -> #REF!
B51: =#REF! -> #REF! | C51: =SUMIFS(Ingresos!$J$9:$J$3900, Ingresos!$L$9:$L$3900, $C$3, Ingresos!$M$9:$M$3900, $C$4, Ingresos!$D$9:$D$3900, B51) -> 0 | D51: =SUMIFS(Ingresos!$J$9:$J$3900, Ingresos!$L$9:$L$3900, $D$3, Ingresos!$M$9:$M$3900, $D$4, Ingresos!$D$9:$D$3900, B51) -> 0 | E51: =SUMIFS(Ingresos!$J$9:$J$3900, Ingresos!$L$9:$L$3900, $E$3, Ingresos!$M$9:$M$3900, $E$4, Ingresos!$D$9:$D$3900, B51) -> 0 | F51: =SUMIFS(Ingresos!$J$9:$J$3900, Ingresos!$L$9:$L$3900, $F$3, Ingresos!$M$9:$M$3900, $F$4, Ingresos!$D$9:$D$3900, B51) -> 0 | G51: =SUMIFS(Ingresos!$J$9:$J$3900, Ingresos!$L$9:$L$3900, $G$3, Ingresos!$M$9:$M$3900, $G$4, Ingresos!$D$9:$D$3900, B51) -> 0 | H51: =SUMIFS(Ingresos!$J$9:$J$3900, Ingresos!$L$9:$L$3900, $H$3, Ingresos!$M$9:$M$3900, $H$4, Ingresos!$D$9:$D$3900, B51) -> 0 | I51: =SUMIFS(Ingresos!$J$9:$J$3900, Ingresos!$L$9:$L$3900, $I$3, Ingresos!$M$9:$M$3900, $I$4, Ingresos!$D$9:$D$3900, B51) -> 0 | J51: =SUMIFS(Ingresos!$J$9:$J$3900, Ingresos!$L$9:$L$3900, $J$3, Ingresos!$M$9:$M$3900, $J$4, Ingresos!$D$9:$D$3900, B51) -> 0 | K51: =SUMIFS(Ingresos!$J$9:$J$3900, Ingresos!$L$9:$L$3900, $K$3, Ingresos!$M$9:$M$3900, $K$4, Ingresos!$D$9:$D$3900, B51) -> 0 | L51: =SUMIFS(Ingresos!$J$9:$J$3900, Ingresos!$L$9:$L$3900, $L$3, Ingresos!$M$9:$M$3900, $L$4, Ingresos!$D$9:$D$3900, B51) -> 0 | M51: =SUMIFS(Ingresos!$J$9:$J$3900, Ingresos!$L$9:$L$3900, $M$3, Ingresos!$M$9:$M$3900, $M$4, Ingresos!$D$9:$D$3900, B51) -> 0 | N51: =SUMIFS(Ingresos!$J$9:$J$3900, Ingresos!$L$9:$L$3900, $N$3, Ingresos!$M$9:$M$3900, $N$4, Ingresos!$D$9:$D$3900, B51) -> 0 | O51: =SUM(C51:N51) -> 0 | Q51: =#REF! -> #REF! | R51: =SUMIFS(Gastos!$J$9:$J$4091, Gastos!$L$9:$L$4091, $R$3, Gastos!$M$9:$M$4091, $R$4, Gastos!$D$9:$D$4091, Q51) -> 0 | S51: =SUMIFS(Gastos!$J$9:$J$4091, Gastos!$L$9:$L$4091, $S$3, Gastos!$M$9:$M$4091, $S$4, Gastos!$D$9:$D$4091, Q51) -> 0 | T51: =SUMIFS(Gastos!$J$9:$J$4091, Gastos!$L$9:$L$4091, $T$3, Gastos!$M$9:$M$4091, $T$4, Gastos!$D$9:$D$4091, Q51) -> 0 | U51: =SUMIFS(Gastos!$J$9:$J$4091, Gastos!$L$9:$L$4091, $U$3, Gastos!$M$9:$M$4091, $U$4, Gastos!$D$9:$D$4091, Q51) -> 0 | V51: =SUMIFS(Gastos!$J$9:$J$4091, Gastos!$L$9:$L$4091, $V$3, Gastos!$M$9:$M$4091, $V$4, Gastos!$D$9:$D$4091, Q51) -> 0 | W51: =SUMIFS(Gastos!$J$9:$J$4091, Gastos!$L$9:$L$4091, $W$3, Gastos!$M$9:$M$4091, $W$4, Gastos!$D$9:$D$4091, Q51) -> 0 | X51: =SUMIFS(Gastos!$J$9:$J$4091, Gastos!$L$9:$L$4091, $X$3, Gastos!$M$9:$M$4091, $X$4, Gastos!$D$9:$D$4091, Q51) -> 0 | Y51: =SUMIFS(Gastos!$J$9:$J$4091, Gastos!$L$9:$L$4091, $Y$3, Gastos!$M$9:$M$4091, $Y$4, Gastos!$D$9:$D$4091, Q51) -> 0 | Z51: =SUMIFS(Gastos!$J$9:$J$4091, Gastos!$L$9:$L$4091, $Z$3, Gastos!$M$9:$M$4091, $Z$4, Gastos!$D$9:$D$4091, Q51) -> 0 | AA51: =SUMIFS(Gastos!$J$9:$J$4091, Gastos!$L$9:$L$4091, $AA$3, Gastos!$M$9:$M$4091, $AA$4, Gastos!$D$9:$D$4091, Q51) -> 0 | AB51: =SUMIFS(Gastos!$J$9:$J$4091, Gastos!$L$9:$L$4091, $AB$3, Gastos!$M$9:$M$4091, $AB$4, Gastos!$D$9:$D$4091, Q51) -> 0 | AC51: =SUMIFS(Gastos!$J$9:$J$4091, Gastos!$L$9:$L$4091, $AC$3, Gastos!$M$9:$M$4091, $AC$4, Gastos!$D$9:$D$4091, Q51) -> 0 | AD51: =SUM(R51:AC51) -> 0 | AK51: =#REF! -> #REF! | AL51: =#REF! -> #REF! | AM51: =#REF! -> #REF! | AN51: =AL51-AM51 -> #REF!
AK52: =#REF! -> #REF! | AL52: =#REF! -> #REF! | AM52: =#REF! -> #REF! | AN52: =AL52-AM52 -> #REF!
AK53: =#REF! -> #REF! | AL53: =#REF! -> #REF! | AM53: =#REF! -> #REF! | AN53: =AL53-AM53 -> #REF!
AK54: =#REF! -> #REF! | AL54: =#REF! -> #REF! | AM54: =#REF! -> #REF! | AN54: =AL54-AM54 -> #REF!
AK55: =#REF! -> #REF! | AL55: =#REF! -> #REF! | AM55: =#REF! -> #REF! | AN55: =AL55-AM55 -> #REF!
AK56: =#REF! -> #REF! | AL56: =#REF! -> #REF! | AM56: =#REF! -> #REF! | AN56: =AL56-AM56 -> #REF!
AK57: TOTAL | AL57: =SUM(AL45:AL56) -> #REF! | AM57: =SUM(AM45:AM56) -> #REF! | AN57: =SUM(AN45:AN56) -> #REF!
B59: CATEGORÍAS DE COSTOS
B60: =#REF! -> #REF! | C60: =SUMIFS(Costos!$J$10:$J$4174, Costos!$L$10:$L$4174, $C$3, Costos!$M$10:$M$4174, $C$4, Costos!$D$10:$D$4174, B60) -> 0 | D60: =SUMIFS(Costos!$J$10:$J$4174, Costos!$L$10:$L$4174, $D$3, Costos!$M$10:$M$4174, $D$4, Costos!$D$10:$D$4174, B60) -> 0 | E60: =SUMIFS(Costos!$J$10:$J$4174, Costos!$L$10:$L$4174, $E$3, Costos!$M$10:$M$4174, $E$4, Costos!$D$10:$D$4174, B60) -> 0 | F60: =SUMIFS(Costos!$J$10:$J$4174, Costos!$L$10:$L$4174, $F$3, Costos!$M$10:$M$4174, $F$4, Costos!$D$10:$D$4174, B60) -> 0 | G60: =SUMIFS(Costos!$J$10:$J$4174, Costos!$L$10:$L$4174, $G$3, Costos!$M$10:$M$4174, $G$4, Costos!$D$10:$D$4174, B60) -> 0 | H60: =SUMIFS(Costos!$J$10:$J$4174, Costos!$L$10:$L$4174, $H$3, Costos!$M$10:$M$4174, $H$4, Costos!$D$10:$D$4174, B60) -> 0 | I60: =SUMIFS(Costos!$J$10:$J$4174, Costos!$L$10:$L$4174, $I$3, Costos!$M$10:$M$4174, $I$4, Costos!$D$10:$D$4174, B60) -> 0 | J60: =SUMIFS(Costos!$J$10:$J$4174, Costos!$L$10:$L$4174, $J$3, Costos!$M$10:$M$4174, $J$4, Costos!$D$10:$D$4174, B60) -> 0 | K60: =SUMIFS(Costos!$J$10:$J$4174, Costos!$L$10:$L$4174, $K$3, Costos!$M$10:$M$4174, $K$4, Costos!$D$10:$D$4174, B60) -> 0 | L60: =SUMIFS(Costos!$J$10:$J$4174, Costos!$L$10:$L$4174, $L$3, Costos!$M$10:$M$4174, $L$4, Costos!$D$10:$D$4174, B60) -> 0 | M60: =SUMIFS(Costos!$J$10:$J$4174, Costos!$L$10:$L$4174, $M$3, Costos!$M$10:$M$4174, $M$4, Costos!$D$10:$D$4174, B60) -> 0 | N60: =SUMIFS(Costos!$J$10:$J$4174, Costos!$L$10:$L$4174, $N$3, Costos!$M$10:$M$4174, $N$4, Costos!$D$10:$D$4174, B60) -> 0 | O60: =SUM(C60:N60) -> 0
B61: =#REF! -> #REF! | C61: =SUMIFS(Costos!$J$10:$J$4174, Costos!$L$10:$L$4174, $C$3, Costos!$M$10:$M$4174, $C$4, Costos!$D$10:$D$4174, B61) -> 0 | D61: =SUMIFS(Costos!$J$10:$J$4174, Costos!$L$10:$L$4174, $D$3, Costos!$M$10:$M$4174, $D$4, Costos!$D$10:$D$4174, B61) -> 0 | E61: =SUMIFS(Costos!$J$10:$J$4174, Costos!$L$10:$L$4174, $E$3, Costos!$M$10:$M$4174, $E$4, Costos!$D$10:$D$4174, B61) -> 0 | F61: =SUMIFS(Costos!$J$10:$J$4174, Costos!$L$10:$L$4174, $F$3, Costos!$M$10:$M$4174, $F$4, Costos!$D$10:$D$4174, B61) -> 0 | G61: =SUMIFS(Costos!$J$10:$J$4174, Costos!$L$10:$L$4174, $G$3, Costos!$M$10:$M$4174, $G$4, Costos!$D$10:$D$4174, B61) -> 0 | H61: =SUMIFS(Costos!$J$10:$J$4174, Costos!$L$10:$L$4174, $H$3, Costos!$M$10:$M$4174, $H$4, Costos!$D$10:$D$4174, B61) -> 0 | I61: =SUMIFS(Costos!$J$10:$J$4174, Costos!$L$10:$L$4174, $I$3, Costos!$M$10:$M$4174, $I$4, Costos!$D$10:$D$4174, B61) -> 0 | J61: =SUMIFS(Costos!$J$10:$J$4174, Costos!$L$10:$L$4174, $J$3, Costos!$M$10:$M$4174, $J$4, Costos!$D$10:$D$4174, B61) -> 0 | K61: =SUMIFS(Costos!$J$10:$J$4174, Costos!$L$10:$L$4174, $K$3, Costos!$M$10:$M$4174, $K$4, Costos!$D$10:$D$4174, B61) -> 0 | L61: =SUMIFS(Costos!$J$10:$J$4174, Costos!$L$10:$L$4174, $L$3, Costos!$M$10:$M$4174, $L$4, Costos!$D$10:$D$4174, B61) -> 0 | M61: =SUMIFS(Costos!$J$10:$J$4174, Costos!$L$10:$L$4174, $M$3, Costos!$M$10:$M$4174, $M$4, Costos!$D$10:$D$4174, B61) -> 0 | N61: =SUMIFS(Costos!$J$10:$J$4174, Costos!$L$10:$L$4174, $N$3, Costos!$M$10:$M$4174, $N$4, Costos!$D$10:$D$4174, B61) -> 0 | O61: =SUM(C61:N61) -> 0
B62: =#REF! -> #REF! | C62: =SUMIFS(Costos!$J$10:$J$4174, Costos!$L$10:$L$4174, $C$3, Costos!$M$10:$M$4174, $C$4, Costos!$D$10:$D$4174, B62) -> 0 | D62: =SUMIFS(Costos!$J$10:$J$4174, Costos!$L$10:$L$4174, $D$3, Costos!$M$10:$M$4174, $D$4, Costos!$D$10:$D$4174, B62) -> 0 | E62: =SUMIFS(Costos!$J$10:$J$4174, Costos!$L$10:$L$4174, $E$3, Costos!$M$10:$M$4174, $E$4, Costos!$D$10:$D$4174, B62) -> 0 | F62: =SUMIFS(Costos!$J$10:$J$4174, Costos!$L$10:$L$4174, $F$3, Costos!$M$10:$M$4174, $F$4, Costos!$D$10:$D$4174, B62) -> 0 | G62: =SUMIFS(Costos!$J$10:$J$4174, Costos!$L$10:$L$4174, $G$3, Costos!$M$10:$M$4174, $G$4, Costos!$D$10:$D$4174, B62) -> 0 | H62: =SUMIFS(Costos!$J$10:$J$4174, Costos!$L$10:$L$4174, $H$3, Costos!$M$10:$M$4174, $H$4, Costos!$D$10:$D$4174, B62) -> 0 | I62: =SUMIFS(Costos!$J$10:$J$4174, Costos!$L$10:$L$4174, $I$3, Costos!$M$10:$M$4174, $I$4, Costos!$D$10:$D$4174, B62) -> 0 | J62: =SUMIFS(Costos!$J$10:$J$4174, Costos!$L$10:$L$4174, $J$3, Costos!$M$10:$M$4174, $J$4, Costos!$D$10:$D$4174, B62) -> 0 | K62: =SUMIFS(Costos!$J$10:$J$4174, Costos!$L$10:$L$4174, $K$3, Costos!$M$10:$M$4174, $K$4, Costos!$D$10:$D$4174, B62) -> 0 | L62: =SUMIFS(Costos!$J$10:$J$4174, Costos!$L$10:$L$4174, $L$3, Costos!$M$10:$M$4174, $L$4, Costos!$D$10:$D$4174, B62) -> 0 | M62: =SUMIFS(Costos!$J$10:$J$4174, Costos!$L$10:$L$4174, $M$3, Costos!$M$10:$M$4174, $M$4, Costos!$D$10:$D$4174, B62) -> 0 | N62: =SUMIFS(Costos!$J$10:$J$4174, Costos!$L$10:$L$4174, $N$3, Costos!$M$10:$M$4174, $N$4, Costos!$D$10:$D$4174, B62) -> 0 | O62: =SUM(C62:N62) -> 0
B63: =#REF! -> #REF! | C63: =SUMIFS(Costos!$J$10:$J$4174, Costos!$L$10:$L$4174, $C$3, Costos!$M$10:$M$4174, $C$4, Costos!$D$10:$D$4174, B63) -> 0 | D63: =SUMIFS(Costos!$J$10:$J$4174, Costos!$L$10:$L$4174, $D$3, Costos!$M$10:$M$4174, $D$4, Costos!$D$10:$D$4174, B63) -> 0 | E63: =SUMIFS(Costos!$J$10:$J$4174, Costos!$L$10:$L$4174, $E$3, Costos!$M$10:$M$4174, $E$4, Costos!$D$10:$D$4174, B63) -> 0 | F63: =SUMIFS(Costos!$J$10:$J$4174, Costos!$L$10:$L$4174, $F$3, Costos!$M$10:$M$4174, $F$4, Costos!$D$10:$D$4174, B63) -> 0 | G63: =SUMIFS(Costos!$J$10:$J$4174, Costos!$L$10:$L$4174, $G$3, Costos!$M$10:$M$4174, $G$4, Costos!$D$10:$D$4174, B63) -> 0 | H63: =SUMIFS(Costos!$J$10:$J$4174, Costos!$L$10:$L$4174, $H$3, Costos!$M$10:$M$4174, $H$4, Costos!$D$10:$D$4174, B63) -> 0 | I63: =SUMIFS(Costos!$J$10:$J$4174, Costos!$L$10:$L$4174, $I$3, Costos!$M$10:$M$4174, $I$4, Costos!$D$10:$D$4174, B63) -> 0 | J63: =SUMIFS(Costos!$J$10:$J$4174, Costos!$L$10:$L$4174, $J$3, Costos!$M$10:$M$4174, $J$4, Costos!$D$10:$D$4174, B63) -> 0 | K63: =SUMIFS(Costos!$J$10:$J$4174, Costos!$L$10:$L$4174, $K$3, Costos!$M$10:$M$4174, $K$4, Costos!$D$10:$D$4174, B63) -> 0 | L63: =SUMIFS(Costos!$J$10:$J$4174, Costos!$L$10:$L$4174, $L$3, Costos!$M$10:$M$4174, $L$4, Costos!$D$10:$D$4174, B63) -> 0 | M63: =SUMIFS(Costos!$J$10:$J$4174, Costos!$L$10:$L$4174, $M$3, Costos!$M$10:$M$4174, $M$4, Costos!$D$10:$D$4174, B63) -> 0 | N63: =SUMIFS(Costos!$J$10:$J$4174, Costos!$L$10:$L$4174, $N$3, Costos!$M$10:$M$4174, $N$4, Costos!$D$10:$D$4174, B63) -> 0 | O63: =SUM(C63:N63) -> 0
B64: =#REF! -> #REF! | C64: =SUMIFS(Costos!$J$10:$J$4174, Costos!$L$10:$L$4174, $C$3, Costos!$M$10:$M$4174, $C$4, Costos!$D$10:$D$4174, B64) -> 0 | D64: =SUMIFS(Costos!$J$10:$J$4174, Costos!$L$10:$L$4174, $D$3, Costos!$M$10:$M$4174, $D$4, Costos!$D$10:$D$4174, B64) -> 0 | E64: =SUMIFS(Costos!$J$10:$J$4174, Costos!$L$10:$L$4174, $E$3, Costos!$M$10:$M$4174, $E$4, Costos!$D$10:$D$4174, B64) -> 0 | F64: =SUMIFS(Costos!$J$10:$J$4174, Costos!$L$10:$L$4174, $F$3, Costos!$M$10:$M$4174, $F$4, Costos!$D$10:$D$4174, B64) -> 0 | G64: =SUMIFS(Costos!$J$10:$J$4174, Costos!$L$10:$L$4174, $G$3, Costos!$M$10:$M$4174, $G$4, Costos!$D$10:$D$4174, B64) -> 0 | H64: =SUMIFS(Costos!$J$10:$J$4174, Costos!$L$10:$L$4174, $H$3, Costos!$M$10:$M$4174, $H$4, Costos!$D$10:$D$4174, B64) -> 0 | I64: =SUMIFS(Costos!$J$10:$J$4174, Costos!$L$10:$L$4174, $I$3, Costos!$M$10:$M$4174, $I$4, Costos!$D$10:$D$4174, B64) -> 0 | J64: =SUMIFS(Costos!$J$10:$J$4174, Costos!$L$10:$L$4174, $J$3, Costos!$M$10:$M$4174, $J$4, Costos!$D$10:$D$4174, B64) -> 0 | K64: =SUMIFS(Costos!$J$10:$J$4174, Costos!$L$10:$L$4174, $K$3, Costos!$M$10:$M$4174, $K$4, Costos!$D$10:$D$4174, B64) -> 0 | L64: =SUMIFS(Costos!$J$10:$J$4174, Costos!$L$10:$L$4174, $L$3, Costos!$M$10:$M$4174, $L$4, Costos!$D$10:$D$4174, B64) -> 0 | M64: =SUMIFS(Costos!$J$10:$J$4174, Costos!$L$10:$L$4174, $M$3, Costos!$M$10:$M$4174, $M$4, Costos!$D$10:$D$4174, B64) -> 0 | N64: =SUMIFS(Costos!$J$10:$J$4174, Costos!$L$10:$L$4174, $N$3, Costos!$M$10:$M$4174, $N$4, Costos!$D$10:$D$4174, B64) -> 0 | O64: =SUM(C64:N64) -> 0
B65: =#REF! -> #REF! | C65: =SUMIFS(Costos!$J$10:$J$4174, Costos!$L$10:$L$4174, $C$3, Costos!$M$10:$M$4174, $C$4, Costos!$D$10:$D$4174, B65) -> 0 | D65: =SUMIFS(Costos!$J$10:$J$4174, Costos!$L$10:$L$4174, $D$3, Costos!$M$10:$M$4174, $D$4, Costos!$D$10:$D$4174, B65) -> 0 | E65: =SUMIFS(Costos!$J$10:$J$4174, Costos!$L$10:$L$4174, $E$3, Costos!$M$10:$M$4174, $E$4, Costos!$D$10:$D$4174, B65) -> 0 | F65: =SUMIFS(Costos!$J$10:$J$4174, Costos!$L$10:$L$4174, $F$3, Costos!$M$10:$M$4174, $F$4, Costos!$D$10:$D$4174, B65) -> 0 | G65: =SUMIFS(Costos!$J$10:$J$4174, Costos!$L$10:$L$4174, $G$3, Costos!$M$10:$M$4174, $G$4, Costos!$D$10:$D$4174, B65) -> 0 | H65: =SUMIFS(Costos!$J$10:$J$4174, Costos!$L$10:$L$4174, $H$3, Costos!$M$10:$M$4174, $H$4, Costos!$D$10:$D$4174, B65) -> 0 | I65: =SUMIFS(Costos!$J$10:$J$4174, Costos!$L$10:$L$4174, $I$3, Costos!$M$10:$M$4174, $I$4, Costos!$D$10:$D$4174, B65) -> 0 | J65: =SUMIFS(Costos!$J$10:$J$4174, Costos!$L$10:$L$4174, $J$3, Costos!$M$10:$M$4174, $J$4, Costos!$D$10:$D$4174, B65) -> 0 | K65: =SUMIFS(Costos!$J$10:$J$4174, Costos!$L$10:$L$4174, $K$3, Costos!$M$10:$M$4174, $K$4, Costos!$D$10:$D$4174, B65) -> 0 | L65: =SUMIFS(Costos!$J$10:$J$4174, Costos!$L$10:$L$4174, $L$3, Costos!$M$10:$M$4174, $L$4, Costos!$D$10:$D$4174, B65) -> 0 | M65: =SUMIFS(Costos!$J$10:$J$4174, Costos!$L$10:$L$4174, $M$3, Costos!$M$10:$M$4174, $M$4, Costos!$D$10:$D$4174, B65) -> 0 | N65: =SUMIFS(Costos!$J$10:$J$4174, Costos!$L$10:$L$4174, $N$3, Costos!$M$10:$M$4174, $N$4, Costos!$D$10:$D$4174, B65) -> 0 | O65: =SUM(C65:N65) -> 0
B66: =#REF! -> #REF! | C66: =SUMIFS(Costos!$J$10:$J$4174, Costos!$L$10:$L$4174, $C$3, Costos!$M$10:$M$4174, $C$4, Costos!$D$10:$D$4174, B66) -> 0 | D66: =SUMIFS(Costos!$J$10:$J$4174, Costos!$L$10:$L$4174, $D$3, Costos!$M$10:$M$4174, $D$4, Costos!$D$10:$D$4174, B66) -> 0 | E66: =SUMIFS(Costos!$J$10:$J$4174, Costos!$L$10:$L$4174, $E$3, Costos!$M$10:$M$4174, $E$4, Costos!$D$10:$D$4174, B66) -> 0 | F66: =SUMIFS(Costos!$J$10:$J$4174, Costos!$L$10:$L$4174, $F$3, Costos!$M$10:$M$4174, $F$4, Costos!$D$10:$D$4174, B66) -> 0 | G66: =SUMIFS(Costos!$J$10:$J$4174, Costos!$L$10:$L$4174, $G$3, Costos!$M$10:$M$4174, $G$4, Costos!$D$10:$D$4174, B66) -> 0 | H66: =SUMIFS(Costos!$J$10:$J$4174, Costos!$L$10:$L$4174, $H$3, Costos!$M$10:$M$4174, $H$4, Costos!$D$10:$D$4174, B66) -> 0 | I66: =SUMIFS(Costos!$J$10:$J$4174, Costos!$L$10:$L$4174, $I$3, Costos!$M$10:$M$4174, $I$4, Costos!$D$10:$D$4174, B66) -> 0 | J66: =SUMIFS(Costos!$J$10:$J$4174, Costos!$L$10:$L$4174, $J$3, Costos!$M$10:$M$4174, $J$4, Costos!$D$10:$D$4174, B66) -> 0 | K66: =SUMIFS(Costos!$J$10:$J$4174, Costos!$L$10:$L$4174, $K$3, Costos!$M$10:$M$4174, $K$4, Costos!$D$10:$D$4174, B66) -> 0 | L66: =SUMIFS(Costos!$J$10:$J$4174, Costos!$L$10:$L$4174, $L$3, Costos!$M$10:$M$4174, $L$4, Costos!$D$10:$D$4174, B66) -> 0 | M66: =SUMIFS(Costos!$J$10:$J$4174, Costos!$L$10:$L$4174, $M$3, Costos!$M$10:$M$4174, $M$4, Costos!$D$10:$D$4174, B66) -> 0 | N66: =SUMIFS(Costos!$J$10:$J$4174, Costos!$L$10:$L$4174, $N$3, Costos!$M$10:$M$4174, $N$4, Costos!$D$10:$D$4174, B66) -> 0 | O66: =SUM(C66:N66) -> 0
B67: =#REF! -> #REF! | C67: =SUMIFS(Costos!$J$10:$J$4174, Costos!$L$10:$L$4174, $C$3, Costos!$M$10:$M$4174, $C$4, Costos!$D$10:$D$4174, B67) -> 0 | D67: =SUMIFS(Costos!$J$10:$J$4174, Costos!$L$10:$L$4174, $D$3, Costos!$M$10:$M$4174, $D$4, Costos!$D$10:$D$4174, B67) -> 0 | E67: =SUMIFS(Costos!$J$10:$J$4174, Costos!$L$10:$L$4174, $E$3, Costos!$M$10:$M$4174, $E$4, Costos!$D$10:$D$4174, B67) -> 0 | F67: =SUMIFS(Costos!$J$10:$J$4174, Costos!$L$10:$L$4174, $F$3, Costos!$M$10:$M$4174, $F$4, Costos!$D$10:$D$4174, B67) -> 0 | G67: =SUMIFS(Costos!$J$10:$J$4174, Costos!$L$10:$L$4174, $G$3, Costos!$M$10:$M$4174, $G$4, Costos!$D$10:$D$4174, B67) -> 0 | H67: =SUMIFS(Costos!$J$10:$J$4174, Costos!$L$10:$L$4174, $H$3, Costos!$M$10:$M$4174, $H$4, Costos!$D$10:$D$4174, B67) -> 0 | I67: =SUMIFS(Costos!$J$10:$J$4174, Costos!$L$10:$L$4174, $I$3, Costos!$M$10:$M$4174, $I$4, Costos!$D$10:$D$4174, B67) -> 0 | J67: =SUMIFS(Costos!$J$10:$J$4174, Costos!$L$10:$L$4174, $J$3, Costos!$M$10:$M$4174, $J$4, Costos!$D$10:$D$4174, B67) -> 0 | K67: =SUMIFS(Costos!$J$10:$J$4174, Costos!$L$10:$L$4174, $K$3, Costos!$M$10:$M$4174, $K$4, Costos!$D$10:$D$4174, B67) -> 0 | L67: =SUMIFS(Costos!$J$10:$J$4174, Costos!$L$10:$L$4174, $L$3, Costos!$M$10:$M$4174, $L$4, Costos!$D$10:$D$4174, B67) -> 0 | M67: =SUMIFS(Costos!$J$10:$J$4174, Costos!$L$10:$L$4174, $M$3, Costos!$M$10:$M$4174, $M$4, Costos!$D$10:$D$4174, B67) -> 0 | N67: =SUMIFS(Costos!$J$10:$J$4174, Costos!$L$10:$L$4174, $N$3, Costos!$M$10:$M$4174, $N$4, Costos!$D$10:$D$4174, B67) -> 0 | O67: =SUM(C67:N67) -> 0
B68: =#REF! -> #REF! | C68: =SUMIFS(Costos!$J$10:$J$4174, Costos!$L$10:$L$4174, $C$3, Costos!$M$10:$M$4174, $C$4, Costos!$D$10:$D$4174, B68) -> 0 | D68: =SUMIFS(Costos!$J$10:$J$4174, Costos!$L$10:$L$4174, $D$3, Costos!$M$10:$M$4174, $D$4, Costos!$D$10:$D$4174, B68) -> 0 | E68: =SUMIFS(Costos!$J$10:$J$4174, Costos!$L$10:$L$4174, $E$3, Costos!$M$10:$M$4174, $E$4, Costos!$D$10:$D$4174, B68) -> 0 | F68: =SUMIFS(Costos!$J$10:$J$4174, Costos!$L$10:$L$4174, $F$3, Costos!$M$10:$M$4174, $F$4, Costos!$D$10:$D$4174, B68) -> 0 | G68: =SUMIFS(Costos!$J$10:$J$4174, Costos!$L$10:$L$4174, $G$3, Costos!$M$10:$M$4174, $G$4, Costos!$D$10:$D$4174, B68) -> 0 | H68: =SUMIFS(Costos!$J$10:$J$4174, Costos!$L$10:$L$4174, $H$3, Costos!$M$10:$M$4174, $H$4, Costos!$D$10:$D$4174, B68) -> 0 | I68: =SUMIFS(Costos!$J$10:$J$4174, Costos!$L$10:$L$4174, $I$3, Costos!$M$10:$M$4174, $I$4, Costos!$D$10:$D$4174, B68) -> 0 | J68: =SUMIFS(Costos!$J$10:$J$4174, Costos!$L$10:$L$4174, $J$3, Costos!$M$10:$M$4174, $J$4, Costos!$D$10:$D$4174, B68) -> 0 | K68: =SUMIFS(Costos!$J$10:$J$4174, Costos!$L$10:$L$4174, $K$3, Costos!$M$10:$M$4174, $K$4, Costos!$D$10:$D$4174, B68) -> 0 | L68: =SUMIFS(Costos!$J$10:$J$4174, Costos!$L$10:$L$4174, $L$3, Costos!$M$10:$M$4174, $L$4, Costos!$D$10:$D$4174, B68) -> 0 | M68: =SUMIFS(Costos!$J$10:$J$4174, Costos!$L$10:$L$4174, $M$3, Costos!$M$10:$M$4174, $M$4, Costos!$D$10:$D$4174, B68) -> 0 | N68: =SUMIFS(Costos!$J$10:$J$4174, Costos!$L$10:$L$4174, $N$3, Costos!$M$10:$M$4174, $N$4, Costos!$D$10:$D$4174, B68) -> 0 | O68: =SUM(C68:N68) -> 0
B69: =#REF! -> #REF! | C69: =SUMIFS(Costos!$J$10:$J$4174, Costos!$L$10:$L$4174, $C$3, Costos!$M$10:$M$4174, $C$4, Costos!$D$10:$D$4174, B69) -> 0 | D69: =SUMIFS(Costos!$J$10:$J$4174, Costos!$L$10:$L$4174, $D$3, Costos!$M$10:$M$4174, $D$4, Costos!$D$10:$D$4174, B69) -> 0 | E69: =SUMIFS(Costos!$J$10:$J$4174, Costos!$L$10:$L$4174, $E$3, Costos!$M$10:$M$4174, $E$4, Costos!$D$10:$D$4174, B69) -> 0 | F69: =SUMIFS(Costos!$J$10:$J$4174, Costos!$L$10:$L$4174, $F$3, Costos!$M$10:$M$4174, $F$4, Costos!$D$10:$D$4174, B69) -> 0 | G69: =SUMIFS(Costos!$J$10:$J$4174, Costos!$L$10:$L$4174, $G$3, Costos!$M$10:$M$4174, $G$4, Costos!$D$10:$D$4174, B69) -> 0 | H69: =SUMIFS(Costos!$J$10:$J$4174, Costos!$L$10:$L$4174, $H$3, Costos!$M$10:$M$4174, $H$4, Costos!$D$10:$D$4174, B69) -> 0 | I69: =SUMIFS(Costos!$J$10:$J$4174, Costos!$L$10:$L$4174, $I$3, Costos!$M$10:$M$4174, $I$4, Costos!$D$10:$D$4174, B69) -> 0 | J69: =SUMIFS(Costos!$J$10:$J$4174, Costos!$L$10:$L$4174, $J$3, Costos!$M$10:$M$4174, $J$4, Costos!$D$10:$D$4174, B69) -> 0 | K69: =SUMIFS(Costos!$J$10:$J$4174, Costos!$L$10:$L$4174, $K$3, Costos!$M$10:$M$4174, $K$4, Costos!$D$10:$D$4174, B69) -> 0 | L69: =SUMIFS(Costos!$J$10:$J$4174, Costos!$L$10:$L$4174, $L$3, Costos!$M$10:$M$4174, $L$4, Costos!$D$10:$D$4174, B69) -> 0 | M69: =SUMIFS(Costos!$J$10:$J$4174, Costos!$L$10:$L$4174, $M$3, Costos!$M$10:$M$4174, $M$4, Costos!$D$10:$D$4174, B69) -> 0 | N69: =SUMIFS(Costos!$J$10:$J$4174, Costos!$L$10:$L$4174, $N$3, Costos!$M$10:$M$4174, $N$4, Costos!$D$10:$D$4174, B69) -> 0 | O69: =SUM(C69:N69) -> 0
B70: =#REF! -> #REF! | C70: =SUMIFS(Costos!$J$10:$J$4174, Costos!$L$10:$L$4174, $C$3, Costos!$M$10:$M$4174, $C$4, Costos!$D$10:$D$4174, B70) -> 0 | D70: =SUMIFS(Costos!$J$10:$J$4174, Costos!$L$10:$L$4174, $D$3, Costos!$M$10:$M$4174, $D$4, Costos!$D$10:$D$4174, B70) -> 0 | E70: =SUMIFS(Costos!$J$10:$J$4174, Costos!$L$10:$L$4174, $E$3, Costos!$M$10:$M$4174, $E$4, Costos!$D$10:$D$4174, B70) -> 0 | F70: =SUMIFS(Costos!$J$10:$J$4174, Costos!$L$10:$L$4174, $F$3, Costos!$M$10:$M$4174, $F$4, Costos!$D$10:$D$4174, B70) -> 0 | G70: =SUMIFS(Costos!$J$10:$J$4174, Costos!$L$10:$L$4174, $G$3, Costos!$M$10:$M$4174, $G$4, Costos!$D$10:$D$4174, B70) -> 0 | H70: =SUMIFS(Costos!$J$10:$J$4174, Costos!$L$10:$L$4174, $H$3, Costos!$M$10:$M$4174, $H$4, Costos!$D$10:$D$4174, B70) -> 0 | I70: =SUMIFS(Costos!$J$10:$J$4174, Costos!$L$10:$L$4174, $I$3, Costos!$M$10:$M$4174, $I$4, Costos!$D$10:$D$4174, B70) -> 0 | J70: =SUMIFS(Costos!$J$10:$J$4174, Costos!$L$10:$L$4174, $J$3, Costos!$M$10:$M$4174, $J$4, Costos!$D$10:$D$4174, B70) -> 0 | K70: =SUMIFS(Costos!$J$10:$J$4174, Costos!$L$10:$L$4174, $K$3, Costos!$M$10:$M$4174, $K$4, Costos!$D$10:$D$4174, B70) -> 0 | L70: =SUMIFS(Costos!$J$10:$J$4174, Costos!$L$10:$L$4174, $L$3, Costos!$M$10:$M$4174, $L$4, Costos!$D$10:$D$4174, B70) -> 0 | M70: =SUMIFS(Costos!$J$10:$J$4174, Costos!$L$10:$L$4174, $M$3, Costos!$M$10:$M$4174, $M$4, Costos!$D$10:$D$4174, B70) -> 0 | N70: =SUMIFS(Costos!$J$10:$J$4174, Costos!$L$10:$L$4174, $N$3, Costos!$M$10:$M$4174, $N$4, Costos!$D$10:$D$4174, B70) -> 0 | O70: =SUM(C70:N70) -> 0
B71: =#REF! -> #REF! | C71: =SUMIFS(Costos!$J$10:$J$4174, Costos!$L$10:$L$4174, $C$3, Costos!$M$10:$M$4174, $C$4, Costos!$D$10:$D$4174, B71) -> 0 | D71: =SUMIFS(Costos!$J$10:$J$4174, Costos!$L$10:$L$4174, $D$3, Costos!$M$10:$M$4174, $D$4, Costos!$D$10:$D$4174, B71) -> 0 | E71: =SUMIFS(Costos!$J$10:$J$4174, Costos!$L$10:$L$4174, $E$3, Costos!$M$10:$M$4174, $E$4, Costos!$D$10:$D$4174, B71) -> 0 | F71: =SUMIFS(Costos!$J$10:$J$4174, Costos!$L$10:$L$4174, $F$3, Costos!$M$10:$M$4174, $F$4, Costos!$D$10:$D$4174, B71) -> 0 | G71: =SUMIFS(Costos!$J$10:$J$4174, Costos!$L$10:$L$4174, $G$3, Costos!$M$10:$M$4174, $G$4, Costos!$D$10:$D$4174, B71) -> 0 | H71: =SUMIFS(Costos!$J$10:$J$4174, Costos!$L$10:$L$4174, $H$3, Costos!$M$10:$M$4174, $H$4, Costos!$D$10:$D$4174, B71) -> 0 | I71: =SUMIFS(Costos!$J$10:$J$4174, Costos!$L$10:$L$4174, $I$3, Costos!$M$10:$M$4174, $I$4, Costos!$D$10:$D$4174, B71) -> 0 | J71: =SUMIFS(Costos!$J$10:$J$4174, Costos!$L$10:$L$4174, $J$3, Costos!$M$10:$M$4174, $J$4, Costos!$D$10:$D$4174, B71) -> 0 | K71: =SUMIFS(Costos!$J$10:$J$4174, Costos!$L$10:$L$4174, $K$3, Costos!$M$10:$M$4174, $K$4, Costos!$D$10:$D$4174, B71) -> 0 | L71: =SUMIFS(Costos!$J$10:$J$4174, Costos!$L$10:$L$4174, $L$3, Costos!$M$10:$M$4174, $L$4, Costos!$D$10:$D$4174, B71) -> 0 | M71: =SUMIFS(Costos!$J$10:$J$4174, Costos!$L$10:$L$4174, $M$3, Costos!$M$10:$M$4174, $M$4, Costos!$D$10:$D$4174, B71) -> 0 | N71: =SUMIFS(Costos!$J$10:$J$4174, Costos!$L$10:$L$4174, $N$3, Costos!$M$10:$M$4174, $N$4, Costos!$D$10:$D$4174, B71) -> 0 | O71: =SUM(C71:N71) -> 0
... B104: =#REF! -> #REF! | C104: =SUMIFS(Costos!$J$10:$J$4174, Costos!$L$10:$L$4174, $C$3, Costos!$M$10:$M$4174, $C$4, Costos!$D$10:$D$4174, B104) -> 0 | D104: =SUMIFS(Costos!$J$10:$J$4174, Costos!$L$10:$L$4174, $D$3, Costos!$M$10:$M$4174, $D$4, Costos!$D$10:$D$4174, B104) -> 0 | E104: =SUMIFS(Costos!$J$10:$J$4174, Costos!$L$10:$L$4174, $E$3, Costos!$M$10:$M$4174, $E$4, Costos!$D$10:$D$4174, B104) -> 0 | F104: =SUMIFS(Costos!$J$10:$J$4174, Costos!$L$10:$L$4174, $F$3, Costos!$M$10:$M$4174, $F$4, Costos!$D$10:$D$4174, B104) -> 0 | G104: =SUMIFS(Costos!$J$10:$J$4174, Costos!$L$10:$L$4174, $G$3, Costos!$M$10:$M$4174, $G$4, Costos!$D$10:$D$4174, B104) -> 0 | H104: =SUMIFS(Costos!$J$10:$J$4174, Costos!$L$10:$L$4174, $H$3, Costos!$M$10:$M$4174, $H$4, Costos!$D$10:$D$4174, B104) -> 0 | I104: =SUMIFS(Costos!$J$10:$J$4174, Costos!$L$10:$L$4174, $I$3, Costos!$M$10:$M$4174, $I$4, Costos!$D$10:$D$4174, B104) -> 0 | J104: =SUMIFS(Costos!$J$10:$J$4174, Costos!$L$10:$L$4174, $J$3, Costos!$M$10:$M$4174, $J$4, Costos!$D$10:$D$4174, B104) -> 0 | K104: =SUMIFS(Costos!$J$10:$J$4174, Costos!$L$10:$L$4174, $K$3, Costos!$M$10:$M$4174, $K$4, Costos!$D$10:$D$4174, B104) -> 0 | L104: =SUMIFS(Costos!$J$10:$J$4174, Costos!$L$10:$L$4174, $L$3, Costos!$M$10:$M$4174, $L$4, Costos!$D$10:$D$4174, B104) -> 0 | M104: =SUMIFS(Costos!$J$10:$J$4174, Costos!$L$10:$L$4174, $M$3, Costos!$M$10:$M$4174, $M$4, Costos!$D$10:$D$4174, B104) -> 0 | N104: =SUMIFS(Costos!$J$10:$J$4174, Costos!$L$10:$L$4174, $N$3, Costos!$M$10:$M$4174, $N$4, Costos!$D$10:$D$4174, B104) -> 0 | O104: =SUM(C104:N104) -> 0

Sheet CONTROL TERRENO
H1: DETALLE DE CAJAS
H2: A.S N°1 CAJA ___
H3: R.R N°2 CAJA___
H4: F.S N°3 CAJA___
H5: V.R N°4 CAJA___
C8: R.R N°2. 1
C9: FECHA | D9: TRABAJADOR | E9: TIPO REGISTRO | F9: CATEGORIA | G9: SUBCATEGORIA | H9: DESCRIPCION | I9: INGRESO | J9: EGRESO | M9: TIPO REGISTRO | N9: ANTICIPO
D10: OBLIGATORIO | E10: ANTICIPO | F10: VIATICOS | G10: ENTREGA | J10: RENDICION | N10: cuando entregas viático
C11: 46105 | D11: R.R | E11: ANTICIPO | F11: VIATICOS | G11: ENTREGA-TRANSFERENCIA | H11: TRABAJO PILOTO PARDO | J11: 30000 | M11: CATEGORIA | N11: VIATICO REGISTRA COMO GASTO
C12: 46105 | D12: R.R | E12: RENDICION | F12: TRASPORTE | G12: COMBUSTIBLE | H12: FAC 5795059 | J12: 18000 | M12: SUBCATEGORIA | N12: ENTREGA
C13: 46104 | D13: R.R | E13: RENDICION | F13: TRASPORTE | G13: PEAJE | H13: 4 PEAJES THNO-CHILLAN | J13: 13850
C14: 46105 | D14: R.R | E14: RENDICION | M14: EGRESO | N14: MONTO ENTREGADO
J15: =SUM(J12:J14) -> 31850
J16: =+J11-J15 -> -1850 | N16: RENDICION
C17: A.S N°1 .1
C18: FECHA | D18: TRABAJADOR | E18: TIPO REGISTRO | F18: CATEGORIA | G18: SUBCATEGORIA | H18: DESCRIPCION | I18: INGRESO | J18: EGRESO
D19: OBLIGATORIO | E19: ANTICIPO | F19: VIATICOS | G19: ENTREGA | J19: RENDICION | N19: cuando registras boletas
C20: 46106 | D20: A.S | E20: ANTICIPO | F20: VIATICO | G20: RETIRO CAJERO | H20: GASTOS OPERATIVOS | J20: 50000 | M20: CATEGORIA | N20: ALOJAMIENTO ALIMENTACION TRANSPORTE
C21: 46106 | D21: A.S | E21: RENDICION | F21: ENCOMIENDA | G21: ECOEX-TRANSPORTE | H21: RETIRO ENCOMIENDA | J21: 17000 | M21: SUBCATEGORIA | N21: HOTEL COLACION COMBUSTIBLE PEAJES
C22: 46106 | D22: A.S | E22: RENDICION | F22: ALIMENTACION | G22: COLACION | H22: COLACION | J22: 10180 | M22: EGRESO
C23: 46106 | D23: A.S | E23: RENDICION | F23: INSUMO | G23: INSUMO- MOTOBOMBA | H23: INSUMO- MOTOBOMBA | J23: 4960
C24: 45738 | D24: A.S | E24: RENDICION | F24: ALIMENTACION | G24: COLACION | H24: COLACION | J24: 17850
C25: 46105 | D25: A.S | E25: RENDICION | F25: INSUMO | G25: INSUMO- MOTOBOMBA | H25: ACEITE | J25: 10999
C26: 46106 | D26: A.S | E26: RENDICION | F26: INSUMO | H26: CUADRADA | I26: 60989
J27: =SUM(J21:J26) -> 60989 | M27: RESUMEN POR TRABAJADOR | N27: TOTAL VIATICO REGISTRO COMO GASTO
J28: =+J20-J27+I26 -> 50000 | N28: TOTAL COMBUSTIBLE REGISTRO COMO COSTO
J29: =+J20-J28 -> 0
C31: A.S 1.5
C32: FECHA | D32: TRABAJADOR | E32: TIPO REGISTRO | F32: CATEGORIA | G32: SUBCATEGORIA | H32: DESCRIPCION | I32: INGRESO | J32: EGRESO | M32: SALDO AZUL, POR RENDIR POR EL TRABAJADOR
D33: OBLIGATORIO | E33: ANTICIPO | F33: VIATICOS | G33: ENTREGA | J33: MONTO ENTREGADO | M33: SALDO ROJO, DEVOLVER A TRABAJADOR
C34: 46108 | D34: A.S | E34: GIRO | F34: ECOEX | G34: VARIOS | J34: 30000
C35: 46108 | D35: A.S | E35: RENDICION | F35: HIDROCENTRO | G35: F.266231 | H35: ACCESORIOS MATERIALES | J35: 27051
J36: =+J34-J35 -> 2949
C40: 46104 | D40: A.S | E40: RENDICION | F40: TRANSFERENCIA | G40: VARIOS | H40: GASTO EFECTICO | J40: 50000
C41: 46105 | D41: A.S | E41: RENDICION | F41: VARIO | G41: VARIOS | H41: EFECTICO ESTACIONAMIENTO/VIATICO | J41: 32930
C42: 46122 | D42: A.S | E42: RENDICION | F42: PASAJES | G42: PASAJES | H42: PASAJES- 3406159-34 CONCEPCION CHILLAN | I42: 2949 | J42: 3999
C43: 46126 | D43: A.S | E43: RENDICION | F43: REUNION | G43: REUNION | H43: REUNION PERSONAL TECNICO | J43: 24310
J44: =SUM(J41:J43) -> 61239
J45: =+J40+I42-J41-J42-J43 -> -8290
C52: A.S N°1 . 2
C53: FECHA | D53: TRABAJADOR | E53: TIPO REGISTRO | F53: CATEGORIA | G53: SUBCATEGORIA | H53: DESCRIPCION | I53: INGRESO | J53: EGRESO
D54: OBLIGATORIO | E54: ANTICIPO | F54: VIATICOS | G54: ENTREGA | H54: FACTURA/BOLETA | J54: RENDICION
C55: 46112 | D55: A.S | E55: RENDICION | F55: VIATICO | G55: RETIRO CAJERO | H55: GASTOS OPERATIVOS | J55: 20000
C56: 45748 | D56: A.S | E56: RENDICION | F56: VIATICO | G56: PEAJE | H56: BULNES | J56: 800
C57: 45748 | D57: A.S | E57: RENDICION | F57: VIATICO | G57: PEAJE | H57: NUEVA ALDEA | J57: 1000
C58: 45748 | D58: A.S | E58: RENDICION | F58: VIATICO | G58: PEAJE | H58: CHILLAN NORTE | J58: 800
C59: 46114 | D59: A.S | E59: RENDICION | F59: VIATICO | G59: PEAJE | H59: AGUA AMARILLA | J59: 4400
